Workbook
Name Account1: _xlfn.ANCHORARRAY(Dashboard!$H$35)
Name Account2: _xlfn.ANCHORARRAY(Dashboard!$I$35)
Name Account3: _xlfn.ANCHORARRAY(Dashboard!$J$35)
Name Account4: _xlfn.ANCHORARRAY(Dashboard!$K$35)
Name Account5: _xlfn.ANCHORARRAY(Dashboard!$L$35)
Name CheckingBalance: _xlfn.ANCHORARRAY(Dashboard!#REF!)
Name CreditBalance: _xlfn.ANCHORARRAY(Dashboard!#REF!)
Name DataTable: _xlfn.ANCHORARRAY('Helper - Dashboard'!$A$2)
Name DataTable2: _xlfn.ANCHORARRAY(Dashboard!$B$35):_xlfn.ANCHORARRAY(Dashboard!$Q$35)
Name DateList: Forecast!$D$7:$D$25
Name Dates: _xlfn.ANCHORARRAY(Dashboard!$C$35)
Name DescList: Forecast!$C$7:$C$25
Name IncomeRow: 'Monthly budget'!$B$9
Name NetBalance: _xlfn.ANCHORARRAY(Dashboard!$G$35)
Name SavingsBalance: _xlfn.ANCHORARRAY(Dashboard!$F$35)
Name Slicer_Account1: #N/A
Name Timeline_Dates: #N/A
Name TotalRow: 'Monthly budget'!$B$91
Name Transactions: _xlfn.ANCHORARRAY(Dashboard!$B$35)

Sheet Monthly budget
B1: MONTHLY BUDGET
C2: Use this sheet to enter your income and expenses. This will give you a monthly budget for you to review: use the totals - calculated based on the frequency of each item - to confirm your net budget. Once this sheet is completed the workbook will use this information to populate the other tools. If additional rows are needed, select the row where you want to add more > right click > Insert
B6: Unit | C6: Frequency | D6: Start | E6: Description | F6: US Bank | G6: Wells Fargo | H6: ADP | I6: Marcus | J6: T.Rowe Price | K6: Platinum | L6: Visa Go | M6: CareCredit | N6: Costco | P6: =F6&"/Mo" -> US Bank/Mo | Q6: =G6&"/Mo" -> Wells Fargo/Mo | R6: =H6&"/Mo" -> ADP/Mo | S6: =I6&"/Mo" -> Marcus/Mo | T6: =J6&"/Mo" -> T.Rowe Price/Mo | U6: =K6&"/Mo" -> Platinum/Mo | V6: =L6&"/Mo" -> Visa Go/Mo | W6: =M6&"/Mo" -> CareCredit/Mo | ... Y6: =O6&"/Mo" -> /Mo | Z6: =F6&"/Yr" -> US Bank/Yr | AA6: =G6&"/Yr" -> Wells Fargo/Yr | AB6: =H6&"/Yr" -> ADP/Yr | AC6: =I6&"/Yr" -> Marcus/Yr | AD6: =J6&"/Yr" -> T.Rowe Price/Yr | AE6: =K6&"/Yr" -> Platinum/Yr | AF6: =L6&"/Yr" -> Visa Go/Yr | AG6: =M6&"/Yr" -> CareCredit/Yr | ... AI6: =O6&"/Yr" -> /Yr | AJ6: Mo Subtotals | AK6: Yr Subtotals | AL6: /Mo | AM6: /Yr
F7: Checking | G7: Checking | H7: Savings | I7: Savings | J7: Savings | K7: Credit | L7: Credit | M7: Credit | N7: Credit
B9: INCOME | F9: Start | G9: Start | H9: Start | I9: Start | J9: Start | K9: Start | L9: Start | M9: Start | N9: Start | O9: Start
E10: Starting balance | F10: 2153.6 | G10: 40.01 | H10: 60.96 | I10: -4600 | J10: -1188.27 | K10: -2010 | L10: =Forecast!K7 -> -8503.82 | M10: =Forecast!L7 -> -4271.75 | N10: =Forecast!M7 -> 0 | O10: =Forecast!N7 -> 0 | P10: {=_xlfn.VSTACK("",SUMIFS(Forecast!$E$7:$E$1009,Forecast!$C$7:$C$1009,"="&OFFSET($E$11,0,0,ROW(TotalRow)-ROW(IncomeRow)-5,1),Forecast!$D$7:$D$1009,">="&'Helper - All dates'!$A$2)/'Helper - All dates'!$A$10)} | Q10: {=_xlfn.VSTACK("",SUMIFS(Forecast!$F$7:$F$1009,Forecast!$C$7:$C$1009,"="&OFFSET($E$11,0,0,ROW(TotalRow)-ROW(IncomeRow)-5,1),Forecast!$D$7:$D$1009,">="&'Helper - All dates'!$A$2)/'Helper - All dates'!$A$10)} | R10: {=_xlfn.VSTACK("",SUMIFS(Forecast!$G$7:$G$1009,Forecast!$C$7:$C$1009,"="&OFFSET($E$11,0,0,ROW(TotalRow)-ROW(IncomeRow)-5,1),Forecast!$D$7:$D$1009,">="&'Helper - All dates'!$A$2)/'Helper - All dates'!$A$10)} | S10: {=_xlfn.VSTACK("",SUMIFS(Forecast!$H$7:$H$1009,Forecast!$C$7:$C$1009,"="&OFFSET($E$11,0,0,ROW(TotalRow)-ROW(IncomeRow)-5,1),Forecast!$D$7:$D$1009,">="&'Helper - All dates'!$A$2)/'Helper - All dates'!$A$10)} | T10: {=_xlfn.VSTACK("",SUMIFS(Forecast!$I$7:$I$1009,Forecast!$C$7:$C$1009,"="&OFFSET($E$11,0,0,ROW(TotalRow)-ROW(IncomeRow)-5,1),Forecast!$D$7:$D$1009,">="&'Helper - All dates'!$A$2)/'Helper - All dates'!$A$10)} | U10: {=_xlfn.VSTACK("",SUMIFS(Forecast!$J$7:$J$1009,Forecast!$C$7:$C$1009,"="&OFFSET($E$11,0,0,ROW(TotalRow)-ROW(IncomeRow)-5,1),Forecast!$D$7:$D$1009,">="&'Helper - All dates'!$A$2)/'Helper - All dates'!$A$10)} | V10: {=_xlfn.VSTACK("",SUMIFS(Forecast!$K$7:$K$1009,Forecast!$C$7:$C$1009,"="&OFFSET($E$11,0,0,ROW(TotalRow)-ROW(IncomeRow)-5,1),Forecast!$D$7:$D$1009,">="&'Helper - All dates'!$A$2)/'Helper - All dates'!$A$10)} | W10: {=_xlfn.VSTACK("",SUMIFS(Forecast!$L$7:$L$1009,Forecast!$C$7:$C$1009,"="&OFFSET($E$11,0,0,ROW(TotalRow)-ROW(IncomeRow)-5,1),Forecast!$D$7:$D$1009,">="&'Helper - All dates'!$A$2)/'Helper - All dates'!$A$10)} | X10: {=_xlfn.VSTACK("",SUMIFS(Forecast!$M$7:$M$1009,Forecast!$C$7:$C$1009,"="&OFFSET($E$11,0,0,ROW(TotalRow)-ROW(IncomeRow)-5,1),Forecast!$D$7:$D$1009,">="&'Helper - All dates'!$A$2)/'Helper - All dates'!$A$10)} | Y10: {=_xlfn.VSTACK("",SUMIFS(Forecast!$N$7:$N$1009,Forecast!$C$7:$C$1009,"="&OFFSET($E$11,0,0,ROW(TotalRow)-ROW(IncomeRow)-5,1),Forecast!$D$7:$D$1009,">="&'Helper - All dates'!$A$2)/'Helper - All dates'!$A$10)} | Z10: {=IF(ISNUMBER(_xlfn.ANCHORARRAY(P10)),_xlfn.ANCHORARRAY(P10)*12,"")} | AA10: {=IF(ISNUMBER(_xlfn.ANCHORARRAY(Q10)),_xlfn.ANCHORARRAY(Q10)*12,"")} | AB10: {=IF(ISNUMBER(_xlfn.ANCHORARRAY(R10)),_xlfn.ANCHORARRAY(R10)*12,"")} | AC10: {=IF(ISNUMBER(_xlfn.ANCHORARRAY(S10)),_xlfn.ANCHORARRAY(S10)*12,"")} | AD10: {=IF(ISNUMBER(_xlfn.ANCHORARRAY(T10)),_xlfn.ANCHORARRAY(T10)*12,"")} | AE10: {=IF(ISNUMBER(_xlfn.ANCHORARRAY(U10)),_xlfn.ANCHORARRAY(U10)*12,"")} | AF10: {=IF(ISNUMBER(_xlfn.ANCHORARRAY(V10)),_xlfn.ANCHORARRAY(V10)*12,"")} | AG10: {=IF(ISNUMBER(_xlfn.ANCHORARRAY(W10)),_xlfn.ANCHORARRAY(W10)*12,"")} | ... AI10: {=IF(ISNUMBER(_xlfn.ANCHORARRAY(Y10)),_xlfn.ANCHORARRAY(Y10)*12,"")} | AL10: {=_xlfn.LET(_xlpm.SumList,IFERROR(_xlfn.ANCHORARRAY($P$10)+_xlfn.ANCHORARRAY($Q$10)+_xlfn.ANCHORARRAY($R$10)+_xlfn.ANCHORARRAY($S$10)+_xlfn.ANCHORARRAY($T$10)+_xlfn.ANCHORARRAY($U$10)+_xlfn.ANCHORARRAY($V$10)+_xlfn.ANCHORARRAY($W$10)+_xlfn.ANCHORARRAY($X$10)+_xlfn.ANCHORARRAY($Y$10),""),_xlfn.LET(_xlpm.BCol,OFFSET($B$1,ROW(IncomeRow),,ROW(TotalRow)-ROW(IncomeRow)-4),IF(_xlpm.BCol<>"TOTAL",_xlpm.SumList,OFFSET(_xlpm.BCol,0,34))))} | AM10: {=_xlfn.LET(_xlpm.SumList,IFERROR(_xlfn.ANCHORARRAY($Z$10)+_xlfn.ANCHORARRAY($AA$10)+_xlfn.ANCHORARRAY($AB$10)+_xlfn.ANCHORARRAY($AC$10)+_xlfn.ANCHORARRAY($AD$10)+_xlfn.ANCHORARRAY($AE$10)+_xlfn.ANCHORARRAY($AF$10)+_xlfn.ANCHORARRAY($AG$10)+_xlfn.ANCHORARRAY($AH$10)+_xlfn.ANCHORARRAY($AI$10),""),_xlfn.LET(_xlpm.BCol,OFFSET($B$1,ROW(IncomeRow),,ROW(TotalRow)-ROW(IncomeRow)-4),IF(_xlpm.BCol<>"TOTAL",_xlpm.SumList,OFFSET(_xlpm.BCol,0,35))))}
B11: 2 | C11: week(s) | D11: 45702 | E11: Paycheck | F11: 1140 | G11: 460 | P11: 2470 | Q11: 996.66667 | R11: 0 | S11: 0 | T11: 0 | U11: 0 | V11: 0 | W11: 0 | X11: 0 | Y11: 0 | Z11: 29640 | AA11: 11960 | AB11: 0 | AC11: 0 | AD11: 0 | AE11: 0 | AF11: 0 | AG11: 0 | AH11: 0 | AI11: 0 | AL11: 3466.6667 | AM11: 41600
B12: 1 | C12: month(s) | D12: 45627 | E12: Disability | G12: 356.66 | P12: 0 | Q12: 356.66 | R12: 0 | S12: 0 | T12: 0 | U12: 0 | V12: 0 | W12: 0 | X12: 0 | Y12: 0 | Z12: 0 | AA12: 4279.92 | AB12: 0 | AC12: 0 | AD12: 0 | AE12: 0 | AF12: 0 | AG12: 0 | AH12: 0 | AI12: 0 | AL12: 356.66 | AM12: 4279.92
B13: 2 | C13: week(s) | D13: 45702 | E13: Ameritas | H13: 112 | P13: 0 | Q13: 0 | R13: 242.66667 | S13: 0 | T13: 0 | U13: 0 | V13: 0 | W13: 0 | X13: 0 | Y13: 0 | Z13: 0 | AA13: 0 | AB13: 2912 | AC13: 0 | AD13: 0 | AE13: 0 | AF13: 0 | AG13: 0 | AH13: 0 | AI13: 0 | AL13: 242.66667 | AM13: 2912
P14: 0 | Q14: 0 | R14: 0 | S14: 0 | T14: 0 | U14: 0 | V14: 0 | W14: 0 | X14: 0 | Y14: 0 | Z14: 0 | AA14: 0 | AB14: 0 | AC14: 0 | AD14: 0 | AE14: 0 | AF14: 0 | AG14: 0 | AH14: 0 | AI14: 0 | AL14: 0 | AM14: 0
P15: 0 | Q15: 0 | R15: 0 | S15: 0 | T15: 0 | U15: 0 | V15: 0 | W15: 0 | X15: 0 | Y15: 0 | Z15: 0 | AA15: 0 | AB15: 0 | AC15: 0 | AD15: 0 | AE15: 0 | AF15: 0 | AG15: 0 | AH15: 0 | AI15: 0 | AL15: 0 | AM15: 0
P16: 0 | Q16: 0 | R16: 0 | S16: 0 | T16: 0 | U16: 0 | V16: 0 | W16: 0 | X16: 0 | Y16: 0 | Z16: 0 | AA16: 0 | AB16: 0 | AC16: 0 | AD16: 0 | AE16: 0 | AF16: 0 | AG16: 0 | AH16: 0 | AI16: 0 | AL16: 0 | AM16: 0
P17: 0 | Q17: 0 | R17: 0 | S17: 0 | T17: 0 | U17: 0 | V17: 0 | W17: 0 | X17: 0 | Y17: 0 | Z17: 0 | AA17: 0 | AB17: 0 | AC17: 0 | AD17: 0 | AE17: 0 | AF17: 0 | AG17: 0 | AH17: 0 | AI17: 0 | AL17: 0 | AM17: 0
P18: 0 | Q18: 0 | R18: 0 | S18: 0 | T18: 0 | U18: 0 | V18: 0 | W18: 0 | X18: 0 | Y18: 0 | Z18: 0 | AA18: 0 | AB18: 0 | AC18: 0 | AD18: 0 | AE18: 0 | AF18: 0 | AG18: 0 | AH18: 0 | AI18: 0 | AL18: 0 | AM18: 0
P19: 0 | Q19: 0 | R19: 0 | S19: 0 | T19: 0 | U19: 0 | V19: 0 | W19: 0 | X19: 0 | Y19: 0 | Z19: 0 | AA19: 0 | AB19: 0 | AC19: 0 | AD19: 0 | AE19: 0 | AF19: 0 | AG19: 0 | AH19: 0 | AI19: 0 | AL19: 0 | AM19: 0
P20: 0 | Q20: 0 | R20: 0 | S20: 0 | T20: 0 | U20: 0 | V20: 0 | W20: 0 | X20: 0 | Y20: 0 | Z20: 0 | AA20: 0 | AB20: 0 | AC20: 0 | AD20: 0 | AE20: 0 | AF20: 0 | AG20: 0 | AH20: 0 | AI20: 0 | AL20: 0 | AM20: 0
P21: 0 | Q21: 0 | R21: 0 | S21: 0 | T21: 0 | U21: 0 | V21: 0 | W21: 0 | X21: 0 | Y21: 0 | Z21: 0 | AA21: 0 | AB21: 0 | AC21: 0 | AD21: 0 | AE21: 0 | AF21: 0 | AG21: 0 | AH21: 0 | AI21: 0 | AL21: 0 | AM21: 0
P22: 0 | Q22: 0 | R22: 0 | S22: 0 | T22: 0 | U22: 0 | V22: 0 | W22: 0 | X22: 0 | Y22: 0 | Z22: 0 | AA22: 0 | AB22: 0 | AC22: 0 | AD22: 0 | AE22: 0 | AF22: 0 | AG22: 0 | AH22: 0 | AI22: 0 | AL22: 0 | AM22: 0
B23: TOTAL | P23: 0 | Q23: 0 | R23: 0 | S23: 0 | T23: 0 | U23: 0 | V23: 0 | W23: 0 | X23: 0 | Y23: 0 | Z23: 0 | AA23: 0 | AB23: 0 | AC23: 0 | AD23: 0 | AE23: 0 | AF23: 0 | AG23: 0 | AH23: 0 | AI23: 0 | AJ23: {=_xlfn.LET(_xlpm.StartRow,MATCH(2,1/(F$6:F22="Start")),SUM(OFFSET($P$6,_xlpm.StartRow+1,0,ROW(F22)-_xlpm.StartRow-1,10)))} -> 4065.9933 | AK23: {=_xlfn.LET(_xlpm.StartRow,MATCH(2,1/(F$6:F22="Start")),SUM(OFFSET($Z$6,_xlpm.StartRow+1,0,ROW(F22)-_xlpm.StartRow-1,10)))} -> 48791.92 | AL23: 4065.9933 | AM23: 48791.92
P24: 0 | Q24: 0 | R24: 0 | S24: 0 | T24: 0 | U24: 0 | V24: 0 | W24: 0 | X24: 0 | Y24: 0 | Z24: 0 | AA24: 0 | AB24: 0 | AC24: 0 | AD24: 0 | AE24: 0 | AF24: 0 | AG24: 0 | AH24: 0 | AI24: 0 | AL24: 0 | AM24: 0
B25: Savings | F25: Start | G25: Start | H25: Start | I25: Start | J25: Start | K25: Start | L25: Start | M25: Start | N25: Start | O25: Start | P25: 0 | Q25: 0 | R25: 0 | S25: 0 | T25: 0 | U25: 0 | V25: 0 | W25: 0 | X25: 0 | Y25: 0 | Z25: 0 | AA25: 0 | AB25: 0 | AC25: 0 | AD25: 0 | AE25: 0 | AF25: 0 | AG25: 0 | AH25: 0 | AI25: 0 | AL25: 0 | AM25: 0
P26: 0 | Q26: 0 | R26: 0 | S26: 0 | T26: 0 | U26: 0 | V26: 0 | W26: 0 | X26: 0 | Y26: 0 | Z26: 0 | AA26: 0 | AB26: 0 | AC26: 0 | AD26: 0 | AE26: 0 | AF26: 0 | AG26: 0 | AH26: 0 | AI26: 0 | AL26: 0 | AM26: 0
P27: 0 | Q27: 0 | R27: 0 | S27: 0 | T27: 0 | U27: 0 | V27: 0 | W27: 0 | X27: 0 | Y27: 0 | Z27: 0 | AA27: 0 | AB27: 0 | AC27: 0 | AD27: 0 | AE27: 0 | AF27: 0 | AG27: 0 | AH27: 0 | AI27: 0 | AL27: 0 | AM27: 0
P28: 0 | Q28: 0 | R28: 0 | S28: 0 | T28: 0 | U28: 0 | V28: 0 | W28: 0 | X28: 0 | Y28: 0 | Z28: 0 | AA28: 0 | AB28: 0 | AC28: 0 | AD28: 0 | AE28: 0 | AF28: 0 | AG28: 0 | AH28: 0 | AI28: 0 | AL28: 0 | AM28: 0
P29: 0 | Q29: 0 | R29: 0 | S29: 0 | T29: 0 | U29: 0 | V29: 0 | W29: 0 | X29: 0 | Y29: 0 | Z29: 0 | AA29: 0 | AB29: 0 | AC29: 0 | AD29: 0 | AE29: 0 | AF29: 0 | AG29: 0 | AH29: 0 | AI29: 0 | AL29: 0 | AM29: 0
P30: 0 | Q30: 0 | R30: 0 | S30: 0 | T30: 0 | U30: 0 | V30: 0 | W30: 0 | X30: 0 | Y30: 0 | Z30: 0 | AA30: 0 | AB30: 0 | AC30: 0 | AD30: 0 | AE30: 0 | AF30: 0 | AG30: 0 | AH30: 0 | AI30: 0 | AL30: 0 | AM30: 0
P31: 0 | Q31: 0 | R31: 0 | S31: 0 | T31: 0 | U31: 0 | V31: 0 | W31: 0 | X31: 0 | Y31: 0 | Z31: 0 | AA31: 0 | AB31: 0 | AC31: 0 | AD31: 0 | AE31: 0 | AF31: 0 | AG31: 0 | AH31: 0 | AI31: 0 | AL31: 0 | AM31: 0
P32: 0 | Q32: 0 | R32: 0 | S32: 0 | T32: 0 | U32: 0 | V32: 0 | W32: 0 | X32: 0 | Y32: 0 | Z32: 0 | AA32: 0 | AB32: 0 | AC32: 0 | AD32: 0 | AE32: 0 | AF32: 0 | AG32: 0 | AH32: 0 | AI32: 0 | AL32: 0 | AM32: 0
P33: 0 | Q33: 0 | R33: 0 | S33: 0 | T33: 0 | U33: 0 | V33: 0 | W33: 0 | X33: 0 | Y33: 0 | Z33: 0 | AA33: 0 | AB33: 0 | AC33: 0 | AD33: 0 | AE33: 0 | AF33: 0 | AG33: 0 | AH33: 0 | AI33: 0 | AL33: 0 | AM33: 0
P34: 0 | Q34: 0 | R34: 0 | S34: 0 | T34: 0 | U34: 0 | V34: 0 | W34: 0 | X34: 0 | Y34: 0 | Z34: 0 | AA34: 0 | AB34: 0 | AC34: 0 | AD34: 0 | AE34: 0 | AF34: 0 | AG34: 0 | AH34: 0 | AI34: 0 | AL34: 0 | AM34: 0
P35: 0 | Q35: 0 | R35: 0 | S35: 0 | T35: 0 | U35: 0 | V35: 0 | W35: 0 | X35: 0 | Y35: 0 | Z35: 0 | AA35: 0 | AB35: 0 | AC35: 0 | AD35: 0 | AE35: 0 | AF35: 0 | AG35: 0 | AH35: 0 | AI35: 0 | AL35: 0 | AM35: 0
P36: 0 | Q36: 0 | R36: 0 | S36: 0 | T36: 0 | U36: 0 | V36: 0 | W36: 0 | X36: 0 | Y36: 0 | Z36: 0 | AA36: 0 | AB36: 0 | AC36: 0 | AD36: 0 | AE36: 0 | AF36: 0 | AG36: 0 | AH36: 0 | AI36: 0 | AL36: 0 | AM36: 0
P37: 0 | Q37: 0 | R37: 0 | S37: 0 | T37: 0 | U37: 0 | V37: 0 | W37: 0 | X37: 0 | Y37: 0 | Z37: 0 | AA37: 0 | AB37: 0 | AC37: 0 | AD37: 0 | AE37: 0 | AF37: 0 | AG37: 0 | AH37: 0 | AI37: 0 | AL37: 0 | AM37: 0
B38: TOTAL | P38: 0 | Q38: 0 | R38: 0 | S38: 0 | T38: 0 | U38: 0 | V38: 0 | W38: 0 | X38: 0 | Y38: 0 | Z38: 0 | AA38: 0 | AB38: 0 | AC38: 0 | AD38: 0 | AE38: 0 | AF38: 0 | AG38: 0 | AH38: 0 | AI38: 0 | AJ38: {=_xlfn.LET(_xlpm.StartRow,MATCH(2,1/(F$6:F37="Start")),SUM(OFFSET($P$6,_xlpm.StartRow+1,0,ROW(F37)-_xlpm.StartRow-7,10)))} -> 0 | AK38: {=_xlfn.LET(_xlpm.StartRow,MATCH(2,1/(F$6:F37="Start")),SUM(OFFSET($Z$6,_xlpm.StartRow+1,0,ROW(F37)-_xlpm.StartRow-7,10)))} -> 0 | AL38: 0 | AM38: 0
P39: 0 | Q39: 0 | R39: 0 | S39: 0 | T39: 0 | U39: 0 | V39: 0 | W39: 0 | X39: 0 | Y39: 0 | Z39: 0 | AA39: 0 | AB39: 0 | AC39: 0 | AD39: 0 | AE39: 0 | AF39: 0 | AG39: 0 | AH39: 0 | AI39: 0 | AL39: 0 | AM39: 0
B40: Transfers | F40: Start | G40: Start | H40: Start | I40: Start | J40: Start | K40: Start | L40: Start | M40: Start | N40: Start | O40: Start | P40: 0 | Q40: 0 | R40: 0 | S40: 0 | T40: 0 | U40: 0 | V40: 0 | W40: 0 | X40: 0 | Y40: 0 | Z40: 0 | AA40: 0 | AB40: 0 | AC40: 0 | AD40: 0 | AE40: 0 | AF40: 0 | AG40: 0 | AH40: 0 | AI40: 0 | AL40: 0 | AM40: 0
P41: 0 | Q41: 0 | R41: 0 | S41: 0 | T41: 0 | U41: 0 | V41: 0 | W41: 0 | X41: 0 | Y41: 0 | Z41: 0 | AA41: 0 | AB41: 0 | AC41: 0 | AD41: 0 | AE41: 0 | AF41: 0 | AG41: 0 | AH41: 0 | AI41: 0 | AL41: 0 | AM41: 0
B42: 1 | C42: month(s) | D42: 45629 | E42: Visa Platinum | F42: -229 | K42: 311 | P42: -229 | Q42: 0 | R42: 0 | S42: 0 | T42: 0 | U42: 311 | V42: 0 | W42: 0 | X42: 0 | Y42: 0 | Z42: -2748 | AA42: 0 | AB42: 0 | AC42: 0 | AD42: 0 | AE42: 3732 | AF42: 0 | AG42: 0 | AH42: 0 | AI42: 0 | AL42: 82 | AM42: 984
B43: 1 | C43: month(s) | D43: 45637 | E43: Viso Go | F43: -275 | L43: 146 | P43: -275 | Q43: 0 | R43: 0 | S43: 0 | T43: 0 | U43: 0 | V43: 146 | W43: 0 | X43: 0 | Y43: 0 | Z43: -3300 | AA43: 0 | AB43: 0 | AC43: 0 | AD43: 0 | AE43: 0 | AF43: 1752 | AG43: 0 | AH43: 0 | AI43: 0 | AL43: -129 | AM43: -1548
B44: 1 | C44: month(s) | D44: 46050 | E44: Costco Citi | F44: -140 | O44: 140 | P44: -140 | Q44: 0 | R44: 0 | S44: 0 | T44: 0 | U44: 0 | V44: 0 | W44: 0 | X44: 0 | Y44: 140 | Z44: -1680 | AA44: 0 | AB44: 0 | AC44: 0 | AD44: 0 | AE44: 0 | AF44: 0 | AG44: 0 | AH44: 0 | AI44: 1680 | AL44: 0 | AM44: 0
B45: 1 | C45: month(s) | D45: 45654 | E45: Kulo Transfer | F45: 1050 | P45: 1050 | Q45: 0 | R45: 0 | S45: 0 | T45: 0 | U45: 0 | V45: 0 | W45: 0 | X45: 0 | Y45: 0 | Z45: 12600 | AA45: 0 | AB45: 0 | AC45: 0 | AD45: 0 | AE45: 0 | AF45: 0 | AG45: 0 | AH45: 0 | AI45: 0 | AL45: 1050 | AM45: 12600
B46: 1 | C46: month(s) | D46: 45627 | E46: Kulo Rent | F46: -959 | P46: -959 | Q46: 0 | R46: 0 | S46: 0 | T46: 0 | U46: 0 | V46: 0 | W46: 0 | X46: 0 | Y46: 0 | Z46: -11508 | AA46: 0 | AB46: 0 | AC46: 0 | AD46: 0 | AE46: 0 | AF46: 0 | AG46: 0 | AH46: 0 | AI46: 0 | AL46: -959 | AM46: -11508
B47: 1 | C47: month(s) | D47: 45928 | E47: Kulo SDGE | F47: -82 | P47: -82 | Q47: 0 | R47: 0 | S47: 0 | T47: 0 | U47: 0 | V47: 0 | W47: 0 | X47: 0 | Y47: 0 | Z47: -984 | AA47: 0 | AB47: 0 | AC47: 0 | AD47: 0 | AE47: 0 | AF47: 0 | AG47: 0 | AH47: 0 | AI47: 0 | AL47: -82 | AM47: -984
B48: 1 | C48: month(s) | D48: 45935 | E48: Kulo Internet | F48: -28 | P48: -28 | Q48: 0 | R48: 0 | S48: 0 | T48: 0 | U48: 0 | V48: 0 | W48: 0 | X48: 0 | Y48: 0 | Z48: -336 | AA48: 0 | AB48: 0 | AC48: 0 | AD48: 0 | AE48: 0 | AF48: 0 | AG48: 0 | AH48: 0 | AI48: 0 | AL48: -28 | AM48: -336
B49: 1 | C49: month(s) | D49: 45651 | E49: Cese Transfer | F49: 142 | P49: 142 | Q49: 0 | R49: 0 | S49: 0 | T49: 0 | U49: 0 | V49: 0 | W49: 0 | X49: 0 | Y49: 0 | Z49: 1704 | AA49: 0 | AB49: 0 | AC49: 0 | AD49: 0 | AE49: 0 | AF49: 0 | AG49: 0 | AH49: 0 | AI49: 0 | AL49: 142 | AM49: 1704
B50: 1 | C50: month(s) | D50: 45631 | E50: Cese Phone | F50: -142 | P50: -142 | Q50: 0 | R50: 0 | S50: 0 | T50: 0 | U50: 0 | V50: 0 | W50: 0 | X50: 0 | Y50: 0 | Z50: -1704 | AA50: 0 | AB50: 0 | AC50: 0 | AD50: 0 | AE50: 0 | AF50: 0 | AG50: 0 | AH50: 0 | AI50: 0 | AL50: -142 | AM50: -1704
P51: 0 | Q51: 0 | R51: 0 | S51: 0 | T51: 0 | U51: 0 | V51: 0 | W51: 0 | X51: 0 | Y51: 0 | Z51: 0 | AA51: 0 | AB51: 0 | AC51: 0 | AD51: 0 | AE51: 0 | AF51: 0 | AG51: 0 | AH51: 0 | AI51: 0 | AL51: 0 | AM51: 0
P52: 0 | Q52: 0 | R52: 0 | S52: 0 | T52: 0 | U52: 0 | V52: 0 | W52: 0 | X52: 0 | Y52: 0 | Z52: 0 | AA52: 0 | AB52: 0 | AC52: 0 | AD52: 0 | AE52: 0 | AF52: 0 | AG52: 0 | AH52: 0 | AI52: 0 | AL52: 0 | AM52: 0
B53: TOTAL | P53: 0 | Q53: 0 | R53: 0 | S53: 0 | T53: 0 | U53: 0 | V53: 0 | W53: 0 | X53: 0 | Y53: 0 | Z53: 0 | AA53: 0 | AB53: 0 | AC53: 0 | AD53: 0 | AE53: 0 | AF53: 0 | AG53: 0 | AH53: 0 | AI53: 0 | AJ53: {=_xlfn.LET(_xlpm.StartRow,MATCH(2,1/(F$6:F52="Start")),SUM(OFFSET($P$6,_xlpm.StartRow+1,0,ROW(F52)-_xlpm.StartRow-7,10)))} -> -66 | AK53: {=_xlfn.LET(_xlpm.StartRow,MATCH(2,1/(F$6:F52="Start")),SUM(OFFSET($Z$6,_xlpm.StartRow+1,0,ROW(F52)-_xlpm.StartRow-7,10)))} -> -792 | AL53: -66 | AM53: -792
P54: 0 | Q54: 0 | R54: 0 | S54: 0 | T54: 0 | U54: 0 | V54: 0 | W54: 0 | X54: 0 | Y54: 0 | Z54: 0 | AA54: 0 | AB54: 0 | AC54: 0 | AD54: 0 | AE54: 0 | AF54: 0 | AG54: 0 | AH54: 0 | AI54: 0 | AL54: 0 | AM54: 0
B55: Expenses | F55: Start | G55: Start | H55: Start | I55: Start | J55: Start | K55: Start | L55: Start | M55: Start | N55: Start | O55: Start | P55: 0 | Q55: 0 | R55: 0 | S55: 0 | T55: 0 | U55: 0 | V55: 0 | W55: 0 | X55: 0 | Y55: 0 | Z55: 0 | AA55: 0 | AB55: 0 | AC55: 0 | AD55: 0 | AE55: 0 | AF55: 0 | AG55: 0 | AH55: 0 | AI55: 0 | AL55: 0 | AM55: 0
P56: 0 | Q56: 0 | R56: 0 | S56: 0 | T56: 0 | U56: 0 | V56: 0 | W56: 0 | X56: 0 | Y56: 0 | Z56: 0 | AA56: 0 | AB56: 0 | AC56: 0 | AD56: 0 | AE56: 0 | AF56: 0 | AG56: 0 | AH56: 0 | AI56: 0 | AL56: 0 | AM56: 0
B57: 1 | C57: month(s) | D57: 45809 | E57: Rent | F57: -1277.97 | P57: -1277.97 | Q57: 0 | R57: 0 | S57: 0 | T57: 0 | U57: 0 | V57: 0 | W57: 0 | X57: 0 | Y57: 0 | Z57: -15335.64 | AA57: 0 | AB57: 0 | AC57: 0 | AD57: 0 | AE57: 0 | AF57: 0 | AG57: 0 | AH57: 0 | AI57: 0 | AL57: -1277.97 | AM57: -15335.64
B58: 2 | C58: week(s) | D58: 45703 | E58: Groceries | G58: -200 | P58: 0 | Q58: -441.66667 | R58: 0 | S58: 0 | T58: 0 | U58: 0 | V58: 0 | W58: 0 | X58: 0 | Y58: 0 | Z58: 0 | AA58: -5300 | AB58: 0 | AC58: 0 | AD58: 0 | AE58: 0 | AF58: 0 | AG58: 0 | AH58: 0 | AI58: 0 | AL58: -441.66667 | AM58: -5300
B59: 2 | C59: week(s) | D59: 45703 | E59: Food & Drinks | G59: -200 | P59: 0 | Q59: -441.66667 | R59: 0 | S59: 0 | T59: 0 | U59: 0 | V59: 0 | W59: 0 | X59: 0 | Y59: 0 | Z59: 0 | AA59: -5300 | AB59: 0 | AC59: 0 | AD59: 0 | AE59: 0 | AF59: 0 | AG59: 0 | AH59: 0 | AI59: 0 | AL59: -441.66667 | AM59: -5300
B60: 1 | C60: month(s) | D60: 45798 | E60: Renters | F60: -10.92 | P60: -10.92 | Q60: 0 | R60: 0 | S60: 0 | T60: 0 | U60: 0 | V60: 0 | W60: 0 | X60: 0 | Y60: 0 | Z60: -131.04 | AA60: 0 | AB60: 0 | AC60: 0 | AD60: 0 | AE60: 0 | AF60: 0 | AG60: 0 | AH60: 0 | AI60: 0 | AL60: -10.92 | AM60: -131.04
B61: 1 | C61: month(s) | D61: 45724 | E61: Sony | F61: -17.99 | P61: -17.99 | Q61: 0 | R61: 0 | S61: 0 | T61: 0 | U61: 0 | V61: 0 | W61: 0 | X61: 0 | Y61: 0 | Z61: -215.88 | AA61: 0 | AB61: 0 | AC61: 0 | AD61: 0 | AE61: 0 | AF61: 0 | AG61: 0 | AH61: 0 | AI61: 0 | AL61: -17.99 | AM61: -215.88
B62: 1 | C62: month(s) | D62: 45631 | E62: Phone | F62: -150.67 | P62: -150.67 | Q62: 0 | R62: 0 | S62: 0 | T62: 0 | U62: 0 | V62: 0 | W62: 0 | X62: 0 | Y62: 0 | Z62: -1808.04 | AA62: 0 | AB62: 0 | AC62: 0 | AD62: 0 | AE62: 0 | AF62: 0 | AG62: 0 | AH62: 0 | AI62: 0 | AL62: -150.67 | AM62: -1808.04
B63: 1 | C63: month(s) | D63: 45635 | E63: Amazon | F63: -16.15 | P63: -16.15 | Q63: 0 | R63: 0 | S63: 0 | T63: 0 | U63: 0 | V63: 0 | W63: 0 | X63: 0 | Y63: 0 | Z63: -193.8 | AA63: 0 | AB63: 0 | AC63: 0 | AD63: 0 | AE63: 0 | AF63: 0 | AG63: 0 | AH63: 0 | AI63: 0 | AL63: -16.15 | AM63: -193.8
B64: 1 | C64: month(s) | D64: 45642 | E64: Motorcycle | F64: -150.38 | P64: -150.38 | Q64: 0 | R64: 0 | S64: 0 | T64: 0 | U64: 0 | V64: 0 | W64: 0 | X64: 0 | Y64: 0 | Z64: -1804.56 | AA64: 0 | AB64: 0 | AC64: 0 | AD64: 0 | AE64: 0 | AF64: 0 | AG64: 0 | AH64: 0 | AI64: 0 | AL64: -150.38 | AM64: -1804.56
B65: 1 | C65: year(s) | D65: 45604 | E65: Bike Insurance | F65: -324.05 | P65: -27.004167 | Q65: 0 | R65: 0 | S65: 0 | T65: 0 | U65: 0 | V65: 0 | W65: 0 | X65: 0 | Y65: 0 | Z65: -324.05 | AA65: 0 | AB65: 0 | AC65: 0 | AD65: 0 | AE65: 0 | AF65: 0 | AG65: 0 | AH65: 0 | AI65: 0 | AL65: -27.004167 | AM65: -324.05
B66: 1 | C66: month(s) | D66: 45866 | E66: SDGE | F66: -84 | P66: -84 | Q66: 0 | R66: 0 | S66: 0 | T66: 0 | U66: 0 | V66: 0 | W66: 0 | X66: 0 | Y66: 0 | Z66: -1008 | AA66: 0 | AB66: 0 | AC66: 0 | AD66: 0 | AE66: 0 | AF66: 0 | AG66: 0 | AH66: 0 | AI66: 0 | AL66: -84 | AM66: -1008
B67: 1 | C67: month(s) | D67: 45652 | E67: Internet | F67: 0 | P67: 0 | Q67: 0 | R67: 0 | S67: 0 | T67: 0 | U67: 0 | V67: 0 | W67: 0 | X67: 0 | Y67: 0 | Z67: 0 | AA67: 0 | AB67: 0 | AC67: 0 | AD67: 0 | AE67: 0 | AF67: 0 | AG67: 0 | AH67: 0 | AI67: 0 | AL67: 0 | AM67: 0
B68: 1 | C68: month(s) | D68: 45828 | E68: Netflix | F68: -24.99 | P68: -24.99 | Q68: 0 | R68: 0 | S68: 0 | T68: 0 | U68: 0 | V68: 0 | W68: 0 | X68: 0 | Y68: 0 | Z68: -299.88 | AA68: 0 | AB68: 0 | AC68: 0 | AD68: 0 | AE68: 0 | AF68: 0 | AG68: 0 | AH68: 0 | AI68: 0 | AL68: -24.99 | AM68: -299.88
B69: 1 | C69: month(s) | D69: 45656 | E69: Prime Ad-Free | F69: -2.99 | P69: -2.99 | Q69: 0 | R69: 0 | S69: 0 | T69: 0 | U69: 0 | V69: 0 | W69: 0 | X69: 0 | Y69: 0 | Z69: -35.88 | AA69: 0 | AB69: 0 | AC69: 0 | AD69: 0 | AE69: 0 | AF69: 0 | AG69: 0 | AH69: 0 | AI69: 0 | AL69: -2.99 | AM69: -35.88
B70: 1 | C70: year(s) | D70: 45690 | E70: Down Dog | K70: -14.99 | P70: 0 | Q70: 0 | R70: 0 | S70: 0 | T70: 0 | U70: -1.2491667 | V70: 0 | W70: 0 | X70: 0 | Y70: 0 | Z70: 0 | AA70: 0 | AB70: 0 | AC70: 0 | AD70: 0 | AE70: -14.99 | AF70: 0 | AG70: 0 | AH70: 0 | AI70: 0 | AL70: -1.2491667 | AM70: -14.99
B71: 1 | C71: year(s) | D71: 45715 | E71: Google+ | F71: -29.99 | P71: -2.4991667 | Q71: 0 | R71: 0 | S71: 0 | T71: 0 | U71: 0 | V71: 0 | W71: 0 | X71: 0 | Y71: 0 | Z71: -29.99 | AA71: 0 | AB71: 0 | AC71: 0 | AD71: 0 | AE71: 0 | AF71: 0 | AG71: 0 | AH71: 0 | AI71: 0 | AL71: -2.4991667 | AM71: -29.99
B72: 1 | C72: month(s) | D72: 45634 | E72: Phone Insurance | F72: -8 | P72: -8 | Q72: 0 | R72: 0 | S72: 0 | T72: 0 | U72: 0 | V72: 0 | W72: 0 | X72: 0 | Y72: 0 | Z72: -96 | AA72: 0 | AB72: 0 | AC72: 0 | AD72: 0 | AE72: 0 | AF72: 0 | AG72: 0 | AH72: 0 | AI72: 0 | AL72: -8 | AM72: -96
B73: 6 | C73: month(s) | D73: 45464 | E73: Sniffies | F73: -59.94 | P73: -9.99 | Q73: 0 | R73: 0 | S73: 0 | T73: 0 | U73: 0 | V73: 0 | W73: 0 | X73: 0 | Y73: 0 | Z73: -119.88 | AA73: 0 | AB73: 0 | AC73: 0 | AD73: 0 | AE73: 0 | AF73: 0 | AG73: 0 | AH73: 0 | AI73: 0 | AL73: -9.99 | AM73: -119.88
B74: 1 | C74: month(s) | D74: 46049 | E74: Tidal | F74: -10.99 | P74: -10.99 | Q74: 0 | R74: 0 | S74: 0 | T74: 0 | U74: 0 | V74: 0 | W74: 0 | X74: 0 | Y74: 0 | Z74: -131.88 | AA74: 0 | AB74: 0 | AC74: 0 | AD74: 0 | AE74: 0 | AF74: 0 | AG74: 0 | AH74: 0 | AI74: 0 | AL74: -10.99 | AM74: -131.88
B75: 1 | C75: month(s) | D75: 46048 | E75: Windsurf | F75: -15 | P75: -15 | Q75: 0 | R75: 0 | S75: 0 | T75: 0 | U75: 0 | V75: 0 | W75: 0 | X75: 0 | Y75: 0 | Z75: -180 | AA75: 0 | AB75: 0 | AC75: 0 | AD75: 0 | AE75: 0 | AF75: 0 | AG75: 0 | AH75: 0 | AI75: 0 | AL75: -15 | AM75: -180
P76: 0 | Q76: 0 | R76: 0 | S76: 0 | T76: 0 | U76: 0 | V76: 0 | W76: 0 | X76: 0 | Y76: 0 | Z76: 0 | AA76: 0 | AB76: 0 | AC76: 0 | AD76: 0 | AE76: 0 | AF76: 0 | AG76: 0 | AH76: 0 | AI76: 0 | AL76: 0 | AM76: 0
P77: 0 | Q77: 0 | R77: 0 | S77: 0 | T77: 0 | U77: 0 | V77: 0 | W77: 0 | X77: 0 | Y77: 0 | Z77: 0 | AA77: 0 | AB77: 0 | AC77: 0 | AD77: 0 | AE77: 0 | AF77: 0 | AG77: 0 | AH77: 0 | AI77: 0 | AL77: 0 | AM77: 0
P78: 0 | Q78: 0 | R78: 0 | S78: 0 | T78: 0 | U78: 0 | V78: 0 | W78: 0 | X78: 0 | Y78: 0 | Z78: 0 | AA78: 0 | AB78: 0 | AC78: 0 | AD78: 0 | AE78: 0 | AF78: 0 | AG78: 0 | AH78: 0 | AI78: 0 | AL78: 0 | AM78: 0
P79: 0 | Q79: 0 | R79: 0 | S79: 0 | T79: 0 | U79: 0 | V79: 0 | W79: 0 | X79: 0 | Y79: 0 | Z79: 0 | AA79: 0 | AB79: 0 | AC79: 0 | AD79: 0 | AE79: 0 | AF79: 0 | AG79: 0 | AH79: 0 | AI79: 0 | AL79: 0 | AM79: 0
P80: 0 | Q80: 0 | R80: 0 | S80: 0 | T80: 0 | U80: 0 | V80: 0 | W80: 0 | X80: 0 | Y80: 0 | Z80: 0 | AA80: 0 | AB80: 0 | AC80: 0 | AD80: 0 | AE80: 0 | AF80: 0 | AG80: 0 | AH80: 0 | AI80: 0 | AL80: 0 | AM80: 0
P81: 0 | Q81: 0 | R81: 0 | S81: 0 | T81: 0 | U81: 0 | V81: 0 | W81: 0 | X81: 0 | Y81: 0 | Z81: 0 | AA81: 0 | AB81: 0 | AC81: 0 | AD81: 0 | AE81: 0 | AF81: 0 | AG81: 0 | AH81: 0 | AI81: 0 | AL81: 0 | AM81: 0
P82: 0 | Q82: 0 | R82: 0 | S82: 0 | T82: 0 | U82: 0 | V82: 0 | W82: 0 | X82: 0 | Y82: 0 | Z82: 0 | AA82: 0 | AB82: 0 | AC82: 0 | AD82: 0 | AE82: 0 | AF82: 0 | AG82: 0 | AH82: 0 | AI82: 0 | AL82: 0 | AM82: 0
P83: 0 | Q83: 0 | R83: 0 | S83: 0 | T83: 0 | U83: 0 | V83: 0 | W83: 0 | X83: 0 | Y83: 0 | Z83: 0 | AA83: 0 | AB83: 0 | AC83: 0 | AD83: 0 | AE83: 0 | AF83: 0 | AG83: 0 | AH83: 0 | AI83: 0 | AL83: 0 | AM83: 0
P84: 0 | Q84: 0 | R84: 0 | S84: 0 | T84: 0 | U84: 0 | V84: 0 | W84: 0 | X84: 0 | Y84: 0 | Z84: 0 | AA84: 0 | AB84: 0 | AC84: 0 | AD84: 0 | AE84: 0 | AF84: 0 | AG84: 0 | AH84: 0 | AI84: 0 | AL84: 0 | AM84: 0
P85: 0 | Q85: 0 | R85: 0 | S85: 0 | T85: 0 | U85: 0 | V85: 0 | W85: 0 | X85: 0 | Y85: 0 | Z85: 0 | AA85: 0 | AB85: 0 | AC85: 0 | AD85: 0 | AE85: 0 | AF85: 0 | AG85: 0 | AH85: 0 | AI85: 0 | AL85: 0 | AM85: 0
P86: 0 | Q86: 0 | R86: 0 | S86: 0 | T86: 0 | U86: 0 | V86: 0 | W86: 0 | X86: 0 | Y86: 0 | Z86: 0 | AA86: 0 | AB86: 0 | AC86: 0 | AD86: 0 | AE86: 0 | AF86: 0 | AG86: 0 | AH86: 0 | AI86: 0 | AL86: 0 | AM86: 0
B87: TOTAL | P87: 0 | Q87: 0 | R87: 0 | S87: 0 | T87: 0 | U87: 0 | V87: 0 | W87: 0 | X87: 0 | Y87: 0 | Z87: 0 | AA87: 0 | AB87: 0 | AC87: 0 | AD87: 0 | AE87: 0 | AF87: 0 | AG87: 0 | AH87: 0 | AI87: 0 | AJ87: {=_xlfn.LET(_xlpm.StartRow,MATCH(2,1/(F$6:F86="Start")),SUM(OFFSET($P$6,_xlpm.StartRow+1,0,ROW(F86)-_xlpm.StartRow-7,10)))} -> -2694.1258 | AK87: {=_xlfn.LET(_xlpm.StartRow,MATCH(2,1/(F$6:F86="Start")),SUM(OFFSET($Z$6,_xlpm.StartRow+1,0,ROW(F86)-_xlpm.StartRow-7,10)))} -> -32329.51 | AL87: -2694.1258 | AM87: -32329.51
E89: Subtotal Deposits: | F89: =SUMIF(_xlfn.ANCHORARRAY(P10),">0") -> 3662 | G89: =SUMIF(_xlfn.ANCHORARRAY(Q10),">0") -> 1353.3267 | H89: =SUMIF(_xlfn.ANCHORARRAY(R10),">0") -> 242.66667 | I89: =SUMIF(_xlfn.ANCHORARRAY(S10),">0") -> 0 | J89: =SUMIF(_xlfn.ANCHORARRAY(T10),">0") -> 0 | K89: =SUMIF(_xlfn.ANCHORARRAY(U10),">0") -> 311 | L89: =SUMIF(_xlfn.ANCHORARRAY(V10),">0") -> 146 | M89: =SUMIF(_xlfn.ANCHORARRAY(W10),">0") -> 0 | ... O89: =SUMIF(_xlfn.ANCHORARRAY(Y10),">0") -> 140 | P89: =SUMIF(P8:P86,">0") -> 3662 | Q89: =SUMIF(Q8:Q86,">0") -> 1353.3267 | R89: =SUMIF(R8:R86,">0") -> 242.66667 | S89: =SUMIF(S8:S86,">0") -> 0 | T89: =SUMIF(T8:T86,">0") -> 0 | U89: =SUMIF(U8:U86,">0") -> 311 | V89: =SUMIF(V8:V86,">0") -> 146 | W89: =SUMIF(W8:W86,">0") -> 0 | ... AI89: =SUMIF(AI8:AI86,">0") -> 1680 | AL89: =SUMIF(AL8:AL86,">0") -> 9405.9867 | AM89: =SUMIF(AM8:AM86,">0") -> 112871.84
E90: Subtotal Debits: | F90: =SUMIF(_xlfn.ANCHORARRAY(P10),"<0") -> -3664.5433 | G90: =SUMIF(_xlfn.ANCHORARRAY(Q10),"<0") -> -883.33333 | H90: =SUMIF(_xlfn.ANCHORARRAY(R10),"<0") -> 0 | I90: =SUMIF(_xlfn.ANCHORARRAY(S10),"<0") -> 0 | J90: =SUMIF(_xlfn.ANCHORARRAY(T10),"<0") -> 0 | K90: =SUMIF(_xlfn.ANCHORARRAY(U10),"<0") -> -1.2491667 | L90: =SUMIF(_xlfn.ANCHORARRAY(V10),"<0") -> 0 | M90: =SUMIF(_xlfn.ANCHORARRAY(W10),"<0") -> 0 | ... O90: =SUMIF(_xlfn.ANCHORARRAY(Y10),"<0") -> 0 | P90: =SUMIF(P8:P86,"<0") -> -3664.5433 | Q90: =SUMIF(Q8:Q86,"<0") -> -883.33333 | R90: =SUMIF(R8:R86,"<0") -> 0 | S90: =SUMIF(S8:S86,"<0") -> 0 | T90: =SUMIF(T8:T86,"<0") -> 0 | U90: =SUMIF(U8:U86,"<0") -> -1.2491667 | V90: =SUMIF(V8:V86,"<0") -> 0 | W90: =SUMIF(W8:W86,"<0") -> 0 | ... AI90: =SUMIF(AI8:AI86,"<0") -> 0 | AL90: =SUMIF(AL8:AL86,"<0") -> -4100.1258 | AM90: =SUMIF(AM8:AM86,"<0") -> -49201.51
E91: Total: | F91: =SUM(_xlfn.ANCHORARRAY(P10)) -> -2.5433333 | G91: =SUM(_xlfn.ANCHORARRAY(Q10)) -> 469.99333 | H91: =SUM(_xlfn.ANCHORARRAY(R10)) -> 242.66667 | I91: =SUM(_xlfn.ANCHORARRAY(S10)) -> 0 | J91: =SUM(_xlfn.ANCHORARRAY(T10)) -> 0 | K91: =SUM(_xlfn.ANCHORARRAY(U10)) -> 309.75083 | L91: =SUM(_xlfn.ANCHORARRAY(V10)) -> 146 | M91: =SUM(_xlfn.ANCHORARRAY(W10)) -> 0 | ... O91: =SUM(_xlfn.ANCHORARRAY(Y10)) -> 140 | P91: =SUM(P8:P86) -> -2.5433333 | Q91: =SUM(Q8:Q86) -> 469.99333 | R91: =SUM(R8:R86) -> 242.66667 | S91: =SUM(S8:S86) -> 0 | T91: =SUM(T8:T86) -> 0 | U91: =SUM(U8:U86) -> 309.75083 | V91: =SUM(V8:V86) -> 146 | W91: =SUM(W8:W86) -> 0 | ... AI91: =SUM(AI8:AI86) -> 1680 | AL91: =SUM(AL8:AL86) -> 5305.8608 | AM91: =SUM(AM8:AM86) -> 63670.33

Sheet Forecast
B1: TRANSACTION FORECAST
B2: x | C2: Use this sheet to balance your checkbook. The forecast is calculated off the starting date and balances at the top. (All transactions before the starting date will be ommitted) If you need to adjust the date or dollar amount of a transaction, add it to the Manual Adjustments section and make sure to skip the corresponding transaction by selecting the checkmark in the Calculated Forecast section. Once all calculated transactions before a given date have been processed, you can adjust the starting date - when you change the start date, the transactions will re-calculate so you will have to clear the manual adjustments and skipped transactions as needed.
B3: x
B4: x
B5: x
B6: Skip | C6: Description | D6: Date | E6: =IF('Monthly budget'!F6<>"",'Monthly budget'!F6,"") -> US Bank | F6: =IF('Monthly budget'!G6<>"",'Monthly budget'!G6,"") -> Wells Fargo | G6: =IF('Monthly budget'!H6<>"",'Monthly budget'!H6,"") -> ADP | H6: =IF('Monthly budget'!I6<>"",'Monthly budget'!I6,"") -> Marcus | I6: =IF('Monthly budget'!J6<>"",'Monthly budget'!J6,"") -> T.Rowe Price | J6: =IF('Monthly budget'!K6<>"",'Monthly budget'!K6,"") -> Platinum | K6: =IF('Monthly budget'!L6<>"",'Monthly budget'!L6,"") -> Visa Go | L6: Costco | N6: =IF('Monthly budget'!O6<>"",'Monthly budget'!O6,"") | O6: DateHelper | P6: =E6&"Helper" -> US BankHelper | Q6: =F6&"Helper" -> Wells FargoHelper | R6: =G6&"Helper" -> ADPHelper | S6: =H6&"Helper" -> MarcusHelper | T6: =I6&"Helper" -> T.Rowe PriceHelper | U6: =J6&"Helper" -> PlatinumHelper | V6: =K6&"Helper" -> Visa GoHelper | W6: =L6&"Helper" -> CostcoHelper | ... Y6: =N6&"Helper" -> Helper
B7: FALSE | C7: Starting balance | D7: 46081 | E7: 3775.81 | F7: 6067.9 | G7: 23232.39 | H7: 114.43 | I7: 12062.04 | J7: -6311.05 | K7: -8503.82 | L7: -4271.75 | O7: {=IFERROR(VLOOKUP(DescList,$C$29:$D$1011,2,FALSE),"")} | P7: {=IFERROR(VLOOKUP(DescList,$C$29:$N$1011,COLUMN(P6)-12,FALSE),"")} | Q7: {=IFERROR(VLOOKUP(DescList,$C$29:$N$1011,COLUMN(Q6)-12,FALSE),"")} | R7: {=IFERROR(VLOOKUP(DescList,$C$29:$N$1011,COLUMN(R6)-12,FALSE),"")} | S7: {=IFERROR(VLOOKUP(DescList,$C$29:$N$1011,COLUMN(S6)-12,FALSE),"")} | T7: {=IFERROR(VLOOKUP(DescList,$C$29:$N$1011,COLUMN(T6)-12,FALSE),"")} | U7: {=IFERROR(VLOOKUP(DescList,$C$29:$N$1011,COLUMN(U6)-12,FALSE),"")} | V7: {=IFERROR(VLOOKUP(DescList,$C$29:$N$1011,COLUMN(V6)-12,FALSE),"")} | W7: {=IFERROR(VLOOKUP(DescList,$C$29:$N$1011,COLUMN(W6)-12,FALSE),"")} | ... Y7: {=IFERROR(VLOOKUP(DescList,$C$29:$N$1011,COLUMN(Y6)-12,FALSE),"")}
B9: Manual Adjustments
B11: FALSE
B12: FALSE
B13: FALSE
B14: FALSE
B15: FALSE
B16: FALSE
B17: FALSE
B18: FALSE
B19: FALSE
B20: FALSE
B21: FALSE
B22: FALSE
... B25: FALSE
B26: Calculated Forecast
B27: Skip
B29: FALSE | C29: {=_xlfn.LET(_xlpm.data,_xlfn._xlws.SORT(_xlfn.HSTACK(_xlfn.TOCOL(_xlfn.ANCHORARRAY('Helper - All dates'!B2)&IF(_xlfn.HSTACK(_xlfn.ANCHORARRAY('Helper - All dates'!E2),_xlfn.ANCHORARRAY('Helper - All dates'!F2))=FALSE,"","")),_xlfn.TOCOL(_xlfn.HSTACK(_xlfn.ANCHORARRAY('Helper - All dates'!E2),_xlfn.ANCHORARRAY('Helper - All dates'!F2)))),2),_xlfn._xlws.FILTER(_xlpm.data,_xlfn.CHOOSECOLS(_xlpm.data,2)<EDATE('Helper - All dates'!$A$2,24)))} -> Costco Citi | D29: 46081 | E29: =IF($C29<>"",VLOOKUP($C29,'Monthly budget'!$E$8:$O$86,COLUMN()-3,FALSE),0) -> -140 | F29: =IF($C29<>"",VLOOKUP($C29,'Monthly budget'!$E$8:$O$86,COLUMN()-3,FALSE),0) -> 0 | G29: =IF($C29<>"",VLOOKUP($C29,'Monthly budget'!$E$8:$O$86,COLUMN()-3,FALSE),0) -> 0 | H29: =IF($C29<>"",VLOOKUP($C29,'Monthly budget'!$E$8:$O$86,COLUMN()-3,FALSE),0) -> 0 | I29: =IF($C29<>"",VLOOKUP($C29,'Monthly budget'!$E$8:$O$86,COLUMN()-3,FALSE),0) -> 0 | J29: =IF($C29<>"",VLOOKUP($C29,'Monthly budget'!$E$8:$O$86,COLUMN()-3,FALSE),0) -> 0 | K29: =IF($C29<>"",VLOOKUP($C29,'Monthly budget'!$E$8:$O$86,COLUMN()-3,FALSE),0) -> 0 | L29: =IF($C29<>"",VLOOKUP($C29,'Monthly budget'!$E$8:$O$86,COLUMN()-3,FALSE),0) -> 0 | ... N29: =IF($C29<>"",VLOOKUP($C29,'Monthly budget'!$E$8:$O$86,COLUMN()-3,FALSE),0) -> 140
B30: TRUE | C30: Kulo Transfer | D30: 46081 | E30: =IF($C30<>"",VLOOKUP($C30,'Monthly budget'!$E$8:$O$86,COLUMN()-3,FALSE),0) -> 1050 | F30: =IF($C30<>"",VLOOKUP($C30,'Monthly budget'!$E$8:$O$86,COLUMN()-3,FALSE),0) -> 0 | G30: =IF($C30<>"",VLOOKUP($C30,'Monthly budget'!$E$8:$O$86,COLUMN()-3,FALSE),0) -> 0 | H30: =IF($C30<>"",VLOOKUP($C30,'Monthly budget'!$E$8:$O$86,COLUMN()-3,FALSE),0) -> 0 | I30: =IF($C30<>"",VLOOKUP($C30,'Monthly budget'!$E$8:$O$86,COLUMN()-3,FALSE),0) -> 0 | J30: =IF($C30<>"",VLOOKUP($C30,'Monthly budget'!$E$8:$O$86,COLUMN()-3,FALSE),0) -> 0 | K30: =IF($C30<>"",VLOOKUP($C30,'Monthly budget'!$E$8:$O$86,COLUMN()-3,FALSE),0) -> 0 | L30: =IF($C30<>"",VLOOKUP($C30,'Monthly budget'!$E$8:$O$86,COLUMN()-3,FALSE),0) -> 0 | ... N30: =IF($C30<>"",VLOOKUP($C30,'Monthly budget'!$E$8:$O$86,COLUMN()-3,FALSE),0) -> 0
B31: FALSE | C31: Kulo SDGE | D31: 46081 | E31: =IF($C31<>"",VLOOKUP($C31,'Monthly budget'!$E$8:$O$86,COLUMN()-3,FALSE),0) -> -82 | F31: =IF($C31<>"",VLOOKUP($C31,'Monthly budget'!$E$8:$O$86,COLUMN()-3,FALSE),0) -> 0 | G31: =IF($C31<>"",VLOOKUP($C31,'Monthly budget'!$E$8:$O$86,COLUMN()-3,FALSE),0) -> 0 | H31: =IF($C31<>"",VLOOKUP($C31,'Monthly budget'!$E$8:$O$86,COLUMN()-3,FALSE),0) -> 0 | I31: =IF($C31<>"",VLOOKUP($C31,'Monthly budget'!$E$8:$O$86,COLUMN()-3,FALSE),0) -> 0 | J31: =IF($C31<>"",VLOOKUP($C31,'Monthly budget'!$E$8:$O$86,COLUMN()-3,FALSE),0) -> 0 | K31: =IF($C31<>"",VLOOKUP($C31,'Monthly budget'!$E$8:$O$86,COLUMN()-3,FALSE),0) -> 0 | L31: =IF($C31<>"",VLOOKUP($C31,'Monthly budget'!$E$8:$O$86,COLUMN()-3,FALSE),0) -> 0 | ... N31: =IF($C31<>"",VLOOKUP($C31,'Monthly budget'!$E$8:$O$86,COLUMN()-3,FALSE),0) -> 0
B32: FALSE | C32: Groceries | D32: 46081 | E32: =IF($C32<>"",VLOOKUP($C32,'Monthly budget'!$E$8:$O$86,COLUMN()-3,FALSE),0) -> 0 | F32: =IF($C32<>"",VLOOKUP($C32,'Monthly budget'!$E$8:$O$86,COLUMN()-3,FALSE),0) -> -200 | G32: =IF($C32<>"",VLOOKUP($C32,'Monthly budget'!$E$8:$O$86,COLUMN()-3,FALSE),0) -> 0 | H32: =IF($C32<>"",VLOOKUP($C32,'Monthly budget'!$E$8:$O$86,COLUMN()-3,FALSE),0) -> 0 | I32: =IF($C32<>"",VLOOKUP($C32,'Monthly budget'!$E$8:$O$86,COLUMN()-3,FALSE),0) -> 0 | J32: =IF($C32<>"",VLOOKUP($C32,'Monthly budget'!$E$8:$O$86,COLUMN()-3,FALSE),0) -> 0 | K32: =IF($C32<>"",VLOOKUP($C32,'Monthly budget'!$E$8:$O$86,COLUMN()-3,FALSE),0) -> 0 | L32: =IF($C32<>"",VLOOKUP($C32,'Monthly budget'!$E$8:$O$86,COLUMN()-3,FALSE),0) -> 0 | ... N32: =IF($C32<>"",VLOOKUP($C32,'Monthly budget'!$E$8:$O$86,COLUMN()-3,FALSE),0) -> 0
B33: FALSE | C33: Food & Drinks | D33: 46081 | E33: =IF($C33<>"",VLOOKUP($C33,'Monthly budget'!$E$8:$O$86,COLUMN()-3,FALSE),0) -> 0 | F33: =IF($C33<>"",VLOOKUP($C33,'Monthly budget'!$E$8:$O$86,COLUMN()-3,FALSE),0) -> -200 | G33: =IF($C33<>"",VLOOKUP($C33,'Monthly budget'!$E$8:$O$86,COLUMN()-3,FALSE),0) -> 0 | H33: =IF($C33<>"",VLOOKUP($C33,'Monthly budget'!$E$8:$O$86,COLUMN()-3,FALSE),0) -> 0 | I33: =IF($C33<>"",VLOOKUP($C33,'Monthly budget'!$E$8:$O$86,COLUMN()-3,FALSE),0) -> 0 | J33: =IF($C33<>"",VLOOKUP($C33,'Monthly budget'!$E$8:$O$86,COLUMN()-3,FALSE),0) -> 0 | K33: =IF($C33<>"",VLOOKUP($C33,'Monthly budget'!$E$8:$O$86,COLUMN()-3,FALSE),0) -> 0 | L33: =IF($C33<>"",VLOOKUP($C33,'Monthly budget'!$E$8:$O$86,COLUMN()-3,FALSE),0) -> 0 | ... N33: =IF($C33<>"",VLOOKUP($C33,'Monthly budget'!$E$8:$O$86,COLUMN()-3,FALSE),0) -> 0
B34: FALSE | C34: SDGE | D34: 46081 | E34: =IF($C34<>"",VLOOKUP($C34,'Monthly budget'!$E$8:$O$86,COLUMN()-3,FALSE),0) -> -84 | F34: =IF($C34<>"",VLOOKUP($C34,'Monthly budget'!$E$8:$O$86,COLUMN()-3,FALSE),0) -> 0 | G34: =IF($C34<>"",VLOOKUP($C34,'Monthly budget'!$E$8:$O$86,COLUMN()-3,FALSE),0) -> 0 | H34: =IF($C34<>"",VLOOKUP($C34,'Monthly budget'!$E$8:$O$86,COLUMN()-3,FALSE),0) -> 0 | I34: =IF($C34<>"",VLOOKUP($C34,'Monthly budget'!$E$8:$O$86,COLUMN()-3,FALSE),0) -> 0 | J34: =IF($C34<>"",VLOOKUP($C34,'Monthly budget'!$E$8:$O$86,COLUMN()-3,FALSE),0) -> 0 | K34: =IF($C34<>"",VLOOKUP($C34,'Monthly budget'!$E$8:$O$86,COLUMN()-3,FALSE),0) -> 0 | L34: =IF($C34<>"",VLOOKUP($C34,'Monthly budget'!$E$8:$O$86,COLUMN()-3,FALSE),0) -> 0 | ... N34: =IF($C34<>"",VLOOKUP($C34,'Monthly budget'!$E$8:$O$86,COLUMN()-3,FALSE),0) -> 0
B35: FALSE | C35: Prime Ad-Free | D35: 46081 | E35: =IF($C35<>"",VLOOKUP($C35,'Monthly budget'!$E$8:$O$86,COLUMN()-3,FALSE),0) -> -2.99 | F35: =IF($C35<>"",VLOOKUP($C35,'Monthly budget'!$E$8:$O$86,COLUMN()-3,FALSE),0) -> 0 | G35: =IF($C35<>"",VLOOKUP($C35,'Monthly budget'!$E$8:$O$86,COLUMN()-3,FALSE),0) -> 0 | H35: =IF($C35<>"",VLOOKUP($C35,'Monthly budget'!$E$8:$O$86,COLUMN()-3,FALSE),0) -> 0 | I35: =IF($C35<>"",VLOOKUP($C35,'Monthly budget'!$E$8:$O$86,COLUMN()-3,FALSE),0) -> 0 | J35: =IF($C35<>"",VLOOKUP($C35,'Monthly budget'!$E$8:$O$86,COLUMN()-3,FALSE),0) -> 0 | K35: =IF($C35<>"",VLOOKUP($C35,'Monthly budget'!$E$8:$O$86,COLUMN()-3,FALSE),0) -> 0 | L35: =IF($C35<>"",VLOOKUP($C35,'Monthly budget'!$E$8:$O$86,COLUMN()-3,FALSE),0) -> 0 | ... N35: =IF($C35<>"",VLOOKUP($C35,'Monthly budget'!$E$8:$O$86,COLUMN()-3,FALSE),0) -> 0
B36: FALSE | C36: Disability | D36: 46082 | E36: =IF($C36<>"",VLOOKUP($C36,'Monthly budget'!$E$8:$O$86,COLUMN()-3,FALSE),0) -> 0 | F36: =IF($C36<>"",VLOOKUP($C36,'Monthly budget'!$E$8:$O$86,COLUMN()-3,FALSE),0) -> 356.66 | G36: =IF($C36<>"",VLOOKUP($C36,'Monthly budget'!$E$8:$O$86,COLUMN()-3,FALSE),0) -> 0 | H36: =IF($C36<>"",VLOOKUP($C36,'Monthly budget'!$E$8:$O$86,COLUMN()-3,FALSE),0) -> 0 | I36: =IF($C36<>"",VLOOKUP($C36,'Monthly budget'!$E$8:$O$86,COLUMN()-3,FALSE),0) -> 0 | J36: =IF($C36<>"",VLOOKUP($C36,'Monthly budget'!$E$8:$O$86,COLUMN()-3,FALSE),0) -> 0 | K36: =IF($C36<>"",VLOOKUP($C36,'Monthly budget'!$E$8:$O$86,COLUMN()-3,FALSE),0) -> 0 | L36: =IF($C36<>"",VLOOKUP($C36,'Monthly budget'!$E$8:$O$86,COLUMN()-3,FALSE),0) -> 0 | ... N36: =IF($C36<>"",VLOOKUP($C36,'Monthly budget'!$E$8:$O$86,COLUMN()-3,FALSE),0) -> 0
B37: FALSE | C37: Kulo Rent | D37: 46082 | E37: =IF($C37<>"",VLOOKUP($C37,'Monthly budget'!$E$8:$O$86,COLUMN()-3,FALSE),0) -> -959 | F37: =IF($C37<>"",VLOOKUP($C37,'Monthly budget'!$E$8:$O$86,COLUMN()-3,FALSE),0) -> 0 | G37: =IF($C37<>"",VLOOKUP($C37,'Monthly budget'!$E$8:$O$86,COLUMN()-3,FALSE),0) -> 0 | H37: =IF($C37<>"",VLOOKUP($C37,'Monthly budget'!$E$8:$O$86,COLUMN()-3,FALSE),0) -> 0 | I37: =IF($C37<>"",VLOOKUP($C37,'Monthly budget'!$E$8:$O$86,COLUMN()-3,FALSE),0) -> 0 | J37: =IF($C37<>"",VLOOKUP($C37,'Monthly budget'!$E$8:$O$86,COLUMN()-3,FALSE),0) -> 0 | K37: =IF($C37<>"",VLOOKUP($C37,'Monthly budget'!$E$8:$O$86,COLUMN()-3,FALSE),0) -> 0 | L37: =IF($C37<>"",VLOOKUP($C37,'Monthly budget'!$E$8:$O$86,COLUMN()-3,FALSE),0) -> 0 | ... N37: =IF($C37<>"",VLOOKUP($C37,'Monthly budget'!$E$8:$O$86,COLUMN()-3,FALSE),0) -> 0
B38: FALSE | C38: Rent | D38: 46082 | E38: =IF($C38<>"",VLOOKUP($C38,'Monthly budget'!$E$8:$O$86,COLUMN()-3,FALSE),0) -> -1277.97 | F38: =IF($C38<>"",VLOOKUP($C38,'Monthly budget'!$E$8:$O$86,COLUMN()-3,FALSE),0) -> 0 | G38: =IF($C38<>"",VLOOKUP($C38,'Monthly budget'!$E$8:$O$86,COLUMN()-3,FALSE),0) -> 0 | H38: =IF($C38<>"",VLOOKUP($C38,'Monthly budget'!$E$8:$O$86,COLUMN()-3,FALSE),0) -> 0 | I38: =IF($C38<>"",VLOOKUP($C38,'Monthly budget'!$E$8:$O$86,COLUMN()-3,FALSE),0) -> 0 | J38: =IF($C38<>"",VLOOKUP($C38,'Monthly budget'!$E$8:$O$86,COLUMN()-3,FALSE),0) -> 0 | K38: =IF($C38<>"",VLOOKUP($C38,'Monthly budget'!$E$8:$O$86,COLUMN()-3,FALSE),0) -> 0 | L38: =IF($C38<>"",VLOOKUP($C38,'Monthly budget'!$E$8:$O$86,COLUMN()-3,FALSE),0) -> 0 | ... N38: =IF($C38<>"",VLOOKUP($C38,'Monthly budget'!$E$8:$O$86,COLUMN()-3,FALSE),0) -> 0
B39: FALSE | C39: Visa Platinum | D39: 46084 | E39: =IF($C39<>"",VLOOKUP($C39,'Monthly budget'!$E$8:$O$86,COLUMN()-3,FALSE),0) -> -229 | F39: =IF($C39<>"",VLOOKUP($C39,'Monthly budget'!$E$8:$O$86,COLUMN()-3,FALSE),0) -> 0 | G39: =IF($C39<>"",VLOOKUP($C39,'Monthly budget'!$E$8:$O$86,COLUMN()-3,FALSE),0) -> 0 | H39: =IF($C39<>"",VLOOKUP($C39,'Monthly budget'!$E$8:$O$86,COLUMN()-3,FALSE),0) -> 0 | I39: =IF($C39<>"",VLOOKUP($C39,'Monthly budget'!$E$8:$O$86,COLUMN()-3,FALSE),0) -> 0 | J39: =IF($C39<>"",VLOOKUP($C39,'Monthly budget'!$E$8:$O$86,COLUMN()-3,FALSE),0) -> 311 | K39: =IF($C39<>"",VLOOKUP($C39,'Monthly budget'!$E$8:$O$86,COLUMN()-3,FALSE),0) -> 0 | L39: =IF($C39<>"",VLOOKUP($C39,'Monthly budget'!$E$8:$O$86,COLUMN()-3,FALSE),0) -> 0 | ... N39: =IF($C39<>"",VLOOKUP($C39,'Monthly budget'!$E$8:$O$86,COLUMN()-3,FALSE),0) -> 0
B40: FALSE | C40: Kulo Internet | D40: 46086 | E40: =IF($C40<>"",VLOOKUP($C40,'Monthly budget'!$E$8:$O$86,COLUMN()-3,FALSE),0) -> -28 | F40: =IF($C40<>"",VLOOKUP($C40,'Monthly budget'!$E$8:$O$86,COLUMN()-3,FALSE),0) -> 0 | G40: =IF($C40<>"",VLOOKUP($C40,'Monthly budget'!$E$8:$O$86,COLUMN()-3,FALSE),0) -> 0 | H40: =IF($C40<>"",VLOOKUP($C40,'Monthly budget'!$E$8:$O$86,COLUMN()-3,FALSE),0) -> 0 | I40: =IF($C40<>"",VLOOKUP($C40,'Monthly budget'!$E$8:$O$86,COLUMN()-3,FALSE),0) -> 0 | J40: =IF($C40<>"",VLOOKUP($C40,'Monthly budget'!$E$8:$O$86,COLUMN()-3,FALSE),0) -> 0 | K40: =IF($C40<>"",VLOOKUP($C40,'Monthly budget'!$E$8:$O$86,COLUMN()-3,FALSE),0) -> 0 | L40: =IF($C40<>"",VLOOKUP($C40,'Monthly budget'!$E$8:$O$86,COLUMN()-3,FALSE),0) -> 0 | ... N40: =IF($C40<>"",VLOOKUP($C40,'Monthly budget'!$E$8:$O$86,COLUMN()-3,FALSE),0) -> 0
B41: FALSE | C41: Cese Phone | D41: 46086 | E41: =IF($C41<>"",VLOOKUP($C41,'Monthly budget'!$E$8:$O$86,COLUMN()-3,FALSE),0) -> -142 | F41: =IF($C41<>"",VLOOKUP($C41,'Monthly budget'!$E$8:$O$86,COLUMN()-3,FALSE),0) -> 0 | G41: =IF($C41<>"",VLOOKUP($C41,'Monthly budget'!$E$8:$O$86,COLUMN()-3,FALSE),0) -> 0 | H41: =IF($C41<>"",VLOOKUP($C41,'Monthly budget'!$E$8:$O$86,COLUMN()-3,FALSE),0) -> 0 | I41: =IF($C41<>"",VLOOKUP($C41,'Monthly budget'!$E$8:$O$86,COLUMN()-3,FALSE),0) -> 0 | J41: =IF($C41<>"",VLOOKUP($C41,'Monthly budget'!$E$8:$O$86,COLUMN()-3,FALSE),0) -> 0 | K41: =IF($C41<>"",VLOOKUP($C41,'Monthly budget'!$E$8:$O$86,COLUMN()-3,FALSE),0) -> 0 | L41: =IF($C41<>"",VLOOKUP($C41,'Monthly budget'!$E$8:$O$86,COLUMN()-3,FALSE),0) -> 0 | ... N41: =IF($C41<>"",VLOOKUP($C41,'Monthly budget'!$E$8:$O$86,COLUMN()-3,FALSE),0) -> 0
... B800: FALSE | C800: Tidal | D800: 46810 | E800: =IF($C800<>"",VLOOKUP($C800,'Monthly budget'!$E$8:$O$86,COLUMN()-3,FALSE),0) -> -10.99 | F800: =IF($C800<>"",VLOOKUP($C800,'Monthly budget'!$E$8:$O$86,COLUMN()-3,FALSE),0) -> 0 | G800: =IF($C800<>"",VLOOKUP($C800,'Monthly budget'!$E$8:$O$86,COLUMN()-3,FALSE),0) -> 0 | H800: =IF($C800<>"",VLOOKUP($C800,'Monthly budget'!$E$8:$O$86,COLUMN()-3,FALSE),0) -> 0 | I800: =IF($C800<>"",VLOOKUP($C800,'Monthly budget'!$E$8:$O$86,COLUMN()-3,FALSE),0) -> 0 | J800: =IF($C800<>"",VLOOKUP($C800,'Monthly budget'!$E$8:$O$86,COLUMN()-3,FALSE),0) -> 0 | K800: =IF($C800<>"",VLOOKUP($C800,'Monthly budget'!$E$8:$O$86,COLUMN()-3,FALSE),0) -> 0 | L800: =IF($C800<>"",VLOOKUP($C800,'Monthly budget'!$E$8:$O$86,COLUMN()-3,FALSE),0) -> 0 | ... N800: =IF($C800<>"",VLOOKUP($C800,'Monthly budget'!$E$8:$O$86,COLUMN()-3,FALSE),0) -> 0
B801: FALSE | E801: =IF($C801<>"",VLOOKUP($C801,'Monthly budget'!$E$8:$O$86,COLUMN()-3,FALSE),0) -> 0 | F801: =IF($C801<>"",VLOOKUP($C801,'Monthly budget'!$E$8:$O$86,COLUMN()-3,FALSE),0) -> 0 | G801: =IF($C801<>"",VLOOKUP($C801,'Monthly budget'!$E$8:$O$86,COLUMN()-3,FALSE),0) -> 0 | H801: =IF($C801<>"",VLOOKUP($C801,'Monthly budget'!$E$8:$O$86,COLUMN()-3,FALSE),0) -> 0 | I801: =IF($C801<>"",VLOOKUP($C801,'Monthly budget'!$E$8:$O$86,COLUMN()-3,FALSE),0) -> 0 | J801: =IF($C801<>"",VLOOKUP($C801,'Monthly budget'!$E$8:$O$86,COLUMN()-3,FALSE),0) -> 0 | K801: =IF($C801<>"",VLOOKUP($C801,'Monthly budget'!$E$8:$O$86,COLUMN()-3,FALSE),0) -> 0 | L801: =IF($C801<>"",VLOOKUP($C801,'Monthly budget'!$E$8:$O$86,COLUMN()-3,FALSE),0) -> 0 | ... N801: =IF($C801<>"",VLOOKUP($C801,'Monthly budget'!$E$8:$O$86,COLUMN()-3,FALSE),0) -> 0
B802: FALSE | E802: =IF($C802<>"",VLOOKUP($C802,'Monthly budget'!$E$8:$O$86,COLUMN()-3,FALSE),0) -> 0 | F802: =IF($C802<>"",VLOOKUP($C802,'Monthly budget'!$E$8:$O$86,COLUMN()-3,FALSE),0) -> 0 | G802: =IF($C802<>"",VLOOKUP($C802,'Monthly budget'!$E$8:$O$86,COLUMN()-3,FALSE),0) -> 0 | H802: =IF($C802<>"",VLOOKUP($C802,'Monthly budget'!$E$8:$O$86,COLUMN()-3,FALSE),0) -> 0 | I802: =IF($C802<>"",VLOOKUP($C802,'Monthly budget'!$E$8:$O$86,COLUMN()-3,FALSE),0) -> 0 | J802: =IF($C802<>"",VLOOKUP($C802,'Monthly budget'!$E$8:$O$86,COLUMN()-3,FALSE),0) -> 0 | K802: =IF($C802<>"",VLOOKUP($C802,'Monthly budget'!$E$8:$O$86,COLUMN()-3,FALSE),0) -> 0 | L802: =IF($C802<>"",VLOOKUP($C802,'Monthly budget'!$E$8:$O$86,COLUMN()-3,FALSE),0) -> 0 | ... N802: =IF($C802<>"",VLOOKUP($C802,'Monthly budget'!$E$8:$O$86,COLUMN()-3,FALSE),0) -> 0
B803: FALSE | E803: =IF($C803<>"",VLOOKUP($C803,'Monthly budget'!$E$8:$O$86,COLUMN()-3,FALSE),0) -> 0 | F803: =IF($C803<>"",VLOOKUP($C803,'Monthly budget'!$E$8:$O$86,COLUMN()-3,FALSE),0) -> 0 | G803: =IF($C803<>"",VLOOKUP($C803,'Monthly budget'!$E$8:$O$86,COLUMN()-3,FALSE),0) -> 0 | H803: =IF($C803<>"",VLOOKUP($C803,'Monthly budget'!$E$8:$O$86,COLUMN()-3,FALSE),0) -> 0 | I803: =IF($C803<>"",VLOOKUP($C803,'Monthly budget'!$E$8:$O$86,COLUMN()-3,FALSE),0) -> 0 | J803: =IF($C803<>"",VLOOKUP($C803,'Monthly budget'!$E$8:$O$86,COLUMN()-3,FALSE),0) -> 0 | K803: =IF($C803<>"",VLOOKUP($C803,'Monthly budget'!$E$8:$O$86,COLUMN()-3,FALSE),0) -> 0 | L803: =IF($C803<>"",VLOOKUP($C803,'Monthly budget'!$E$8:$O$86,COLUMN()-3,FALSE),0) -> 0 | ... N803: =IF($C803<>"",VLOOKUP($C803,'Monthly budget'!$E$8:$O$86,COLUMN()-3,FALSE),0) -> 0
B804: FALSE | E804: =IF($C804<>"",VLOOKUP($C804,'Monthly budget'!$E$8:$O$86,COLUMN()-3,FALSE),0) -> 0 | F804: =IF($C804<>"",VLOOKUP($C804,'Monthly budget'!$E$8:$O$86,COLUMN()-3,FALSE),0) -> 0 | G804: =IF($C804<>"",VLOOKUP($C804,'Monthly budget'!$E$8:$O$86,COLUMN()-3,FALSE),0) -> 0 | H804: =IF($C804<>"",VLOOKUP($C804,'Monthly budget'!$E$8:$O$86,COLUMN()-3,FALSE),0) -> 0 | I804: =IF($C804<>"",VLOOKUP($C804,'Monthly budget'!$E$8:$O$86,COLUMN()-3,FALSE),0) -> 0 | J804: =IF($C804<>"",VLOOKUP($C804,'Monthly budget'!$E$8:$O$86,COLUMN()-3,FALSE),0) -> 0 | K804: =IF($C804<>"",VLOOKUP($C804,'Monthly budget'!$E$8:$O$86,COLUMN()-3,FALSE),0) -> 0 | L804: =IF($C804<>"",VLOOKUP($C804,'Monthly budget'!$E$8:$O$86,COLUMN()-3,FALSE),0) -> 0 | ... N804: =IF($C804<>"",VLOOKUP($C804,'Monthly budget'!$E$8:$O$86,COLUMN()-3,FALSE),0) -> 0
B805: FALSE | E805: =IF($C805<>"",VLOOKUP($C805,'Monthly budget'!$E$8:$O$86,COLUMN()-3,FALSE),0) -> 0 | F805: =IF($C805<>"",VLOOKUP($C805,'Monthly budget'!$E$8:$O$86,COLUMN()-3,FALSE),0) -> 0 | G805: =IF($C805<>"",VLOOKUP($C805,'Monthly budget'!$E$8:$O$86,COLUMN()-3,FALSE),0) -> 0 | H805: =IF($C805<>"",VLOOKUP($C805,'Monthly budget'!$E$8:$O$86,COLUMN()-3,FALSE),0) -> 0 | I805: =IF($C805<>"",VLOOKUP($C805,'Monthly budget'!$E$8:$O$86,COLUMN()-3,FALSE),0) -> 0 | J805: =IF($C805<>"",VLOOKUP($C805,'Monthly budget'!$E$8:$O$86,COLUMN()-3,FALSE),0) -> 0 | K805: =IF($C805<>"",VLOOKUP($C805,'Monthly budget'!$E$8:$O$86,COLUMN()-3,FALSE),0) -> 0 | L805: =IF($C805<>"",VLOOKUP($C805,'Monthly budget'!$E$8:$O$86,COLUMN()-3,FALSE),0) -> 0 | ... N805: =IF($C805<>"",VLOOKUP($C805,'Monthly budget'!$E$8:$O$86,COLUMN()-3,FALSE),0) -> 0
B806: FALSE | E806: =IF($C806<>"",VLOOKUP($C806,'Monthly budget'!$E$8:$O$86,COLUMN()-3,FALSE),0) -> 0 | F806: =IF($C806<>"",VLOOKUP($C806,'Monthly budget'!$E$8:$O$86,COLUMN()-3,FALSE),0) -> 0 | G806: =IF($C806<>"",VLOOKUP($C806,'Monthly budget'!$E$8:$O$86,COLUMN()-3,FALSE),0) -> 0 | H806: =IF($C806<>"",VLOOKUP($C806,'Monthly budget'!$E$8:$O$86,COLUMN()-3,FALSE),0) -> 0 | I806: =IF($C806<>"",VLOOKUP($C806,'Monthly budget'!$E$8:$O$86,COLUMN()-3,FALSE),0) -> 0 | J806: =IF($C806<>"",VLOOKUP($C806,'Monthly budget'!$E$8:$O$86,COLUMN()-3,FALSE),0) -> 0 | K806: =IF($C806<>"",VLOOKUP($C806,'Monthly budget'!$E$8:$O$86,COLUMN()-3,FALSE),0) -> 0 | L806: =IF($C806<>"",VLOOKUP($C806,'Monthly budget'!$E$8:$O$86,COLUMN()-3,FALSE),0) -> 0 | ... N806: =IF($C806<>"",VLOOKUP($C806,'Monthly budget'!$E$8:$O$86,COLUMN()-3,FALSE),0) -> 0
B807: FALSE | E807: =IF($C807<>"",VLOOKUP($C807,'Monthly budget'!$E$8:$O$86,COLUMN()-3,FALSE),0) -> 0 | F807: =IF($C807<>"",VLOOKUP($C807,'Monthly budget'!$E$8:$O$86,COLUMN()-3,FALSE),0) -> 0 | G807: =IF($C807<>"",VLOOKUP($C807,'Monthly budget'!$E$8:$O$86,COLUMN()-3,FALSE),0) -> 0 | H807: =IF($C807<>"",VLOOKUP($C807,'Monthly budget'!$E$8:$O$86,COLUMN()-3,FALSE),0) -> 0 | I807: =IF($C807<>"",VLOOKUP($C807,'Monthly budget'!$E$8:$O$86,COLUMN()-3,FALSE),0) -> 0 | J807: =IF($C807<>"",VLOOKUP($C807,'Monthly budget'!$E$8:$O$86,COLUMN()-3,FALSE),0) -> 0 | K807: =IF($C807<>"",VLOOKUP($C807,'Monthly budget'!$E$8:$O$86,COLUMN()-3,FALSE),0) -> 0 | L807: =IF($C807<>"",VLOOKUP($C807,'Monthly budget'!$E$8:$O$86,COLUMN()-3,FALSE),0) -> 0 | ... N807: =IF($C807<>"",VLOOKUP($C807,'Monthly budget'!$E$8:$O$86,COLUMN()-3,FALSE),0) -> 0
B808: FALSE | E808: =IF($C808<>"",VLOOKUP($C808,'Monthly budget'!$E$8:$O$86,COLUMN()-3,FALSE),0) -> 0 | F808: =IF($C808<>"",VLOOKUP($C808,'Monthly budget'!$E$8:$O$86,COLUMN()-3,FALSE),0) -> 0 | G808: =IF($C808<>"",VLOOKUP($C808,'Monthly budget'!$E$8:$O$86,COLUMN()-3,FALSE),0) -> 0 | H808: =IF($C808<>"",VLOOKUP($C808,'Monthly budget'!$E$8:$O$86,COLUMN()-3,FALSE),0) -> 0 | I808: =IF($C808<>"",VLOOKUP($C808,'Monthly budget'!$E$8:$O$86,COLUMN()-3,FALSE),0) -> 0 | J808: =IF($C808<>"",VLOOKUP($C808,'Monthly budget'!$E$8:$O$86,COLUMN()-3,FALSE),0) -> 0 | K808: =IF($C808<>"",VLOOKUP($C808,'Monthly budget'!$E$8:$O$86,COLUMN()-3,FALSE),0) -> 0 | L808: =IF($C808<>"",VLOOKUP($C808,'Monthly budget'!$E$8:$O$86,COLUMN()-3,FALSE),0) -> 0 | ... N808: =IF($C808<>"",VLOOKUP($C808,'Monthly budget'!$E$8:$O$86,COLUMN()-3,FALSE),0) -> 0
B809: FALSE | E809: =IF($C809<>"",VLOOKUP($C809,'Monthly budget'!$E$8:$O$86,COLUMN()-3,FALSE),0) -> 0 | F809: =IF($C809<>"",VLOOKUP($C809,'Monthly budget'!$E$8:$O$86,COLUMN()-3,FALSE),0) -> 0 | G809: =IF($C809<>"",VLOOKUP($C809,'Monthly budget'!$E$8:$O$86,COLUMN()-3,FALSE),0) -> 0 | H809: =IF($C809<>"",VLOOKUP($C809,'Monthly budget'!$E$8:$O$86,COLUMN()-3,FALSE),0) -> 0 | I809: =IF($C809<>"",VLOOKUP($C809,'Monthly budget'!$E$8:$O$86,COLUMN()-3,FALSE),0) -> 0 | J809: =IF($C809<>"",VLOOKUP($C809,'Monthly budget'!$E$8:$O$86,COLUMN()-3,FALSE),0) -> 0 | K809: =IF($C809<>"",VLOOKUP($C809,'Monthly budget'!$E$8:$O$86,COLUMN()-3,FALSE),0) -> 0 | L809: =IF($C809<>"",VLOOKUP($C809,'Monthly budget'!$E$8:$O$86,COLUMN()-3,FALSE),0) -> 0 | ... N809: =IF($C809<>"",VLOOKUP($C809,'Monthly budget'!$E$8:$O$86,COLUMN()-3,FALSE),0) -> 0
B810: FALSE | E810: =IF($C810<>"",VLOOKUP($C810,'Monthly budget'!$E$8:$O$86,COLUMN()-3,FALSE),0) -> 0 | F810: =IF($C810<>"",VLOOKUP($C810,'Monthly budget'!$E$8:$O$86,COLUMN()-3,FALSE),0) -> 0 | G810: =IF($C810<>"",VLOOKUP($C810,'Monthly budget'!$E$8:$O$86,COLUMN()-3,FALSE),0) -> 0 | H810: =IF($C810<>"",VLOOKUP($C810,'Monthly budget'!$E$8:$O$86,COLUMN()-3,FALSE),0) -> 0 | I810: =IF($C810<>"",VLOOKUP($C810,'Monthly budget'!$E$8:$O$86,COLUMN()-3,FALSE),0) -> 0 | J810: =IF($C810<>"",VLOOKUP($C810,'Monthly budget'!$E$8:$O$86,COLUMN()-3,FALSE),0) -> 0 | K810: =IF($C810<>"",VLOOKUP($C810,'Monthly budget'!$E$8:$O$86,COLUMN()-3,FALSE),0) -> 0 | L810: =IF($C810<>"",VLOOKUP($C810,'Monthly budget'!$E$8:$O$86,COLUMN()-3,FALSE),0) -> 0 | ... N810: =IF($C810<>"",VLOOKUP($C810,'Monthly budget'!$E$8:$O$86,COLUMN()-3,FALSE),0) -> 0
B811: FALSE | E811: =IF($C811<>"",VLOOKUP($C811,'Monthly budget'!$E$8:$O$86,COLUMN()-3,FALSE),0) -> 0 | F811: =IF($C811<>"",VLOOKUP($C811,'Monthly budget'!$E$8:$O$86,COLUMN()-3,FALSE),0) -> 0 | G811: =IF($C811<>"",VLOOKUP($C811,'Monthly budget'!$E$8:$O$86,COLUMN()-3,FALSE),0) -> 0 | H811: =IF($C811<>"",VLOOKUP($C811,'Monthly budget'!$E$8:$O$86,COLUMN()-3,FALSE),0) -> 0 | I811: =IF($C811<>"",VLOOKUP($C811,'Monthly budget'!$E$8:$O$86,COLUMN()-3,FALSE),0) -> 0 | J811: =IF($C811<>"",VLOOKUP($C811,'Monthly budget'!$E$8:$O$86,COLUMN()-3,FALSE),0) -> 0 | K811: =IF($C811<>"",VLOOKUP($C811,'Monthly budget'!$E$8:$O$86,COLUMN()-3,FALSE),0) -> 0 | L811: =IF($C811<>"",VLOOKUP($C811,'Monthly budget'!$E$8:$O$86,COLUMN()-3,FALSE),0) -> 0 | ... N811: =IF($C811<>"",VLOOKUP($C811,'Monthly budget'!$E$8:$O$86,COLUMN()-3,FALSE),0) -> 0
B812: FALSE | E812: =IF($C812<>"",VLOOKUP($C812,'Monthly budget'!$E$8:$O$86,COLUMN()-3,FALSE),0) -> 0 | F812: =IF($C812<>"",VLOOKUP($C812,'Monthly budget'!$E$8:$O$86,COLUMN()-3,FALSE),0) -> 0 | G812: =IF($C812<>"",VLOOKUP($C812,'Monthly budget'!$E$8:$O$86,COLUMN()-3,FALSE),0) -> 0 | H812: =IF($C812<>"",VLOOKUP($C812,'Monthly budget'!$E$8:$O$86,COLUMN()-3,FALSE),0) -> 0 | I812: =IF($C812<>"",VLOOKUP($C812,'Monthly budget'!$E$8:$O$86,COLUMN()-3,FALSE),0) -> 0 | J812: =IF($C812<>"",VLOOKUP($C812,'Monthly budget'!$E$8:$O$86,COLUMN()-3,FALSE),0) -> 0 | K812: =IF($C812<>"",VLOOKUP($C812,'Monthly budget'!$E$8:$O$86,COLUMN()-3,FALSE),0) -> 0 | L812: =IF($C812<>"",VLOOKUP($C812,'Monthly budget'!$E$8:$O$86,COLUMN()-3,FALSE),0) -> 0 | ... N812: =IF($C812<>"",VLOOKUP($C812,'Monthly budget'!$E$8:$O$86,COLUMN()-3,FALSE),0) -> 0
... B2004: FALSE | E2004: =IF($C2004<>"",VLOOKUP($C2004,'Monthly budget'!$E$8:$O$86,COLUMN()-3,FALSE),0) -> 0 | F2004: =IF($C2004<>"",VLOOKUP($C2004,'Monthly budget'!$E$8:$O$86,COLUMN()-3,FALSE),0) -> 0 | G2004: =IF($C2004<>"",VLOOKUP($C2004,'Monthly budget'!$E$8:$O$86,COLUMN()-3,FALSE),0) -> 0 | H2004: =IF($C2004<>"",VLOOKUP($C2004,'Monthly budget'!$E$8:$O$86,COLUMN()-3,FALSE),0) -> 0 | I2004: =IF($C2004<>"",VLOOKUP($C2004,'Monthly budget'!$E$8:$O$86,COLUMN()-3,FALSE),0) -> 0 | J2004: =IF($C2004<>"",VLOOKUP($C2004,'Monthly budget'!$E$8:$O$86,COLUMN()-3,FALSE),0) -> 0 | K2004: =IF($C2004<>"",VLOOKUP($C2004,'Monthly budget'!$E$8:$O$86,COLUMN()-3,FALSE),0) -> 0 | L2004: =IF($C2004<>"",VLOOKUP($C2004,'Monthly budget'!$E$8:$O$86,COLUMN()-3,FALSE),0) -> 0 | ... N2004: =IF($C2004<>"",VLOOKUP($C2004,'Monthly budget'!$E$8:$O$86,COLUMN()-3,FALSE),0) -> 0

Sheet Dashboard
B1: Dashboard
B2: x | C2: Use this sheet to identify trends and trouble spots in your forecasted budget. The chart at the top shows each account over time. You can select which accounts to display using the slicer on the right and the date range using the timeline below the chart. Please note, the chart uses the average for each acocunt when summarizining the values so the chart will not show the effect of each transaction when multiple occur on the same day. The table below the chart will identify negative checking and savings balances, the bottom 10 balances for each account, and the lowest single balance for each account. Click on the chart and go to PivotChart Analyze > Refresh > Refresh All to update the accounts and balances in the chart.
B3: x
B4: x
B5: x
B34: Transactions | C34: Dates | D34: Checking | E34: Credit | F34: Savings | G34: Net Worth | H34: ="Account 1 "&'Monthly budget'!F6 -> Account 1 US Bank | I34: ="Account 2 "&'Monthly budget'!G6 -> Account 2 Wells Fargo | J34: ="Account 3 "&'Monthly budget'!H6 -> Account 3 ADP | K34: ="Account 4 "&'Monthly budget'!I6 -> Account 4 Marcus | L34: ="Account 5 "&'Monthly budget'!J6 -> Account 5 T.Rowe Price | M34: ="Account 6 "&'Monthly budget'!K6 -> Account 6 Platinum | N34: ="Account 7 "&'Monthly budget'!L6 -> Account 7 Visa Go | O34: ="Account 8 "&'Monthly budget'!M6 -> Account 8 CareCredit | P34: ="Account 9 "&'Monthly budget'!N6 -> Account 9 Costco | Q34: ="Account 10 "&'Monthly budget'!O6 -> Account 10
B35: {=_xlfn.CHOOSECOLS(_xlfn._xlws.SORT(_xlfn._xlws.FILTER(Forecast!B:O,(Forecast!B:B=FALSE)*(Forecast!C:C<>"")),3),2)} -> Starting balance | C35: {=_xlfn.CHOOSECOLS(_xlfn._xlws.SORT(_xlfn._xlws.FILTER(Forecast!B:O,(Forecast!B:B=FALSE)*(Forecast!C:C<>"")),3),3)} -> 46081 | D35: {=_xlfn.BYROW(_xlfn.HSTACK(_xlfn.ANCHORARRAY(H35):_xlfn.ANCHORARRAY(Q35)),_xlfn.LAMBDA(_xlpm.a,SUMPRODUCT(--('Monthly budget'!$F$7:$O$7="Checking"),_xlpm.a)))} -> 9843.71 | E35: {=_xlfn.BYROW(_xlfn.HSTACK(_xlfn.ANCHORARRAY(H35):_xlfn.ANCHORARRAY(Q35)),_xlfn.LAMBDA(_xlpm.a,SUMPRODUCT(--('Monthly budget'!$F$7:$O$7="Credit"),_xlpm.a)))} -> -19086.62 | F35: {=_xlfn.BYROW(_xlfn.HSTACK(_xlfn.ANCHORARRAY(H35):_xlfn.ANCHORARRAY(Q35)),_xlfn.LAMBDA(_xlpm.a,SUMPRODUCT(--('Monthly budget'!$F$7:$O$7="Savings"),_xlpm.a)))} -> 35408.86 | G35: {=_xlfn.BYROW(_xlfn.HSTACK(_xlfn.ANCHORARRAY(H35):_xlfn.ANCHORARRAY(Q35)),_xlfn.LAMBDA(_xlpm.a,SUM(_xlpm.a)))} -> 26165.95 | H35: {=_xlfn.SCAN(0,_xlfn.CHOOSECOLS(_xlfn._xlws.SORT(_xlfn._xlws.FILTER(Forecast!B:O,(Forecast!B:B=FALSE)*(Forecast!C:C<>"")),3),4),_xlfn.LAMBDA(_xlpm.a,_xlpm.v,_xlpm.a+_xlpm.v))} -> 3775.81 | I35: {=_xlfn.SCAN(0,_xlfn.CHOOSECOLS(_xlfn._xlws.SORT(_xlfn._xlws.FILTER(Forecast!B:O,(Forecast!B:B=FALSE)*(Forecast!C:C<>"")),3),5),_xlfn.LAMBDA(_xlpm.a,_xlpm.v,_xlpm.a+_xlpm.v))} -> 6067.9 | J35: {=_xlfn.SCAN(0,_xlfn.CHOOSECOLS(_xlfn._xlws.SORT(_xlfn._xlws.FILTER(Forecast!B:O,(Forecast!B:B=FALSE)*(Forecast!C:C<>"")),3),6),_xlfn.LAMBDA(_xlpm.a,_xlpm.v,_xlpm.a+_xlpm.v))} -> 23232.39 | K35: {=_xlfn.SCAN(0,_xlfn.CHOOSECOLS(_xlfn._xlws.SORT(_xlfn._xlws.FILTER(Forecast!B:O,(Forecast!B:B=FALSE)*(Forecast!C:C<>"")),3),7),_xlfn.LAMBDA(_xlpm.a,_xlpm.v,_xlpm.a+_xlpm.v))} -> 114.43 | L35: {=_xlfn.SCAN(0,_xlfn.CHOOSECOLS(_xlfn._xlws.SORT(_xlfn._xlws.FILTER(Forecast!B:O,(Forecast!B:B=FALSE)*(Forecast!C:C<>"")),3),8),_xlfn.LAMBDA(_xlpm.a,_xlpm.v,_xlpm.a+_xlpm.v))} -> 12062.04 | M35: {=_xlfn.SCAN(0,_xlfn.CHOOSECOLS(_xlfn._xlws.SORT(_xlfn._xlws.FILTER(Forecast!B:O,(Forecast!B:B=FALSE)*(Forecast!C:C<>"")),3),9),_xlfn.LAMBDA(_xlpm.a,_xlpm.v,_xlpm.a+_xlpm.v))} -> -6311.05 | N35: {=_xlfn.SCAN(0,_xlfn.CHOOSECOLS(_xlfn._xlws.SORT(_xlfn._xlws.FILTER(Forecast!B:O,(Forecast!B:B=FALSE)*(Forecast!C:C<>"")),3),10),_xlfn.LAMBDA(_xlpm.a,_xlpm.v,_xlpm.a+_xlpm.v))} -> -8503.82 | O35: {=_xlfn.SCAN(0,_xlfn.CHOOSECOLS(_xlfn._xlws.SORT(_xlfn._xlws.FILTER(Forecast!B:O,(Forecast!B:B=FALSE)*(Forecast!C:C<>"")),3),11),_xlfn.LAMBDA(_xlpm.a,_xlpm.v,_xlpm.a+_xlpm.v))} -> -4271.75 | P35: {=_xlfn.SCAN(0,_xlfn.CHOOSECOLS(_xlfn._xlws.SORT(_xlfn._xlws.FILTER(Forecast!B:O,(Forecast!B:B=FALSE)*(Forecast!C:C<>"")),3),12),_xlfn.LAMBDA(_xlpm.a,_xlpm.v,_xlpm.a+_xlpm.v))} -> 0 | Q35: {=_xlfn.SCAN(0,_xlfn.CHOOSECOLS(_xlfn._xlws.SORT(_xlfn._xlws.FILTER(Forecast!B:O,(Forecast!B:B=FALSE)*(Forecast!C:C<>"")),3),13),_xlfn.LAMBDA(_xlpm.a,_xlpm.v,_xlpm.a+_xlpm.v))} -> 0
B36: Costco Citi | C36: 46081 | D36: 9703.71 | E36: -19086.62 | F36: 35408.86 | G36: 26165.95 | H36: 3635.81 | I36: 6067.9 | J36: 23232.39 | K36: 114.43 | L36: 12062.04 | M36: -6311.05 | N36: -8503.82 | O36: -4271.75 | P36: 0 | Q36: 140
B37: Kulo SDGE | C37: 46081 | D37: 9621.71 | E37: -19086.62 | F37: 35408.86 | G37: 26083.95 | H37: 3553.81 | I37: 6067.9 | J37: 23232.39 | K37: 114.43 | L37: 12062.04 | M37: -6311.05 | N37: -8503.82 | O37: -4271.75 | P37: 0 | Q37: 140
B38: Groceries | C38: 46081 | D38: 9421.71 | E38: -19086.62 | F38: 35408.86 | G38: 25883.95 | H38: 3553.81 | I38: 5867.9 | J38: 23232.39 | K38: 114.43 | L38: 12062.04 | M38: -6311.05 | N38: -8503.82 | O38: -4271.75 | P38: 0 | Q38: 140
B39: Food & Drinks | C39: 46081 | D39: 9221.71 | E39: -19086.62 | F39: 35408.86 | G39: 25683.95 | H39: 3553.81 | I39: 5667.9 | J39: 23232.39 | K39: 114.43 | L39: 12062.04 | M39: -6311.05 | N39: -8503.82 | O39: -4271.75 | P39: 0 | Q39: 140
B40: SDGE | C40: 46081 | D40: 9137.71 | E40: -19086.62 | F40: 35408.86 | G40: 25599.95 | H40: 3469.81 | I40: 5667.9 | J40: 23232.39 | K40: 114.43 | L40: 12062.04 | M40: -6311.05 | N40: -8503.82 | O40: -4271.75 | P40: 0 | Q40: 140
B41: Prime Ad-Free | C41: 46081 | D41: 9134.72 | E41: -19086.62 | F41: 35408.86 | G41: 25596.96 | H41: 3466.82 | I41: 5667.9 | J41: 23232.39 | K41: 114.43 | L41: 12062.04 | M41: -6311.05 | N41: -8503.82 | O41: -4271.75 | P41: 0 | Q41: 140
B42: Disability | C42: 46082 | D42: 9491.38 | E42: -19086.62 | F42: 35408.86 | G42: 25953.62 | H42: 3466.82 | I42: 6024.56 | J42: 23232.39 | K42: 114.43 | L42: 12062.04 | M42: -6311.05 | N42: -8503.82 | O42: -4271.75 | P42: 0 | Q42: 140
B43: Kulo Rent | C43: 46082 | D43: 8532.38 | E43: -19086.62 | F43: 35408.86 | G43: 24994.62 | H43: 2507.82 | I43: 6024.56 | J43: 23232.39 | K43: 114.43 | L43: 12062.04 | M43: -6311.05 | N43: -8503.82 | O43: -4271.75 | P43: 0 | Q43: 140
B44: Rent | C44: 46082 | D44: 7254.41 | E44: -19086.62 | F44: 35408.86 | G44: 23716.65 | H44: 1229.85 | I44: 6024.56 | J44: 23232.39 | K44: 114.43 | L44: 12062.04 | M44: -6311.05 | N44: -8503.82 | O44: -4271.75 | P44: 0 | Q44: 140
B45: Visa Platinum | C45: 46084 | D45: 7025.41 | E45: -18775.62 | F45: 35408.86 | G45: 23798.65 | H45: 1000.85 | I45: 6024.56 | J45: 23232.39 | K45: 114.43 | L45: 12062.04 | M45: -6000.05 | N45: -8503.82 | O45: -4271.75 | P45: 0 | Q45: 140
B46: Kulo Internet | C46: 46086 | D46: 6997.41 | E46: -18775.62 | F46: 35408.86 | G46: 23770.65 | H46: 972.85 | I46: 6024.56 | J46: 23232.39 | K46: 114.43 | L46: 12062.04 | M46: -6000.05 | N46: -8503.82 | O46: -4271.75 | P46: 0 | Q46: 140
B47: Cese Phone | C47: 46086 | D47: 6855.41 | E47: -18775.62 | F47: 35408.86 | G47: 23628.65 | H47: 830.85 | I47: 6024.56 | J47: 23232.39 | K47: 114.43 | L47: 12062.04 | M47: -6000.05 | N47: -8503.82 | O47: -4271.75 | P47: 0 | Q47: 140
... B806: Tidal | C806: 46810 | D806: 20012.51 | E806: -8148.6 | F806: 41232.86 | G806: 56456.77 | H806: 2664.77 | I806: 17347.74 | J806: 29056.39 | K806: 114.43 | L806: 12062.04 | M806: 1122.97 | N806: -4999.82 | O806: -4271.75 | P806: 0 | Q806: 3360

Sheet Notes
B1: Rent +Utilities | C1: Rent | D1: Utilities | E1: SDGE | F1: T-Mobile
A2: TOTAL | B2: 2244.11 | C2: 2195 | D2: =B2-C2 -> 49.11 | E2: 175 | F2: 54.99 | G2: =SUM(C2:F2) -> 2474.1
A3: Kulo | B3: =ROUNDUP(B$2/2-160,0) -> 963 | C3: =ROUNDUP(C$2/2-160,0) -> 938 | D3: =B3-C3 -> 25 | E3: =ROUNDUP(E$2/2,0) -> 88 | F3: =ROUNDUP(F$2/2,0) -> 28 | G3: =SUM(C3:F3) -> 1079
A4: Me | B4: =B2-B3 -> 1281.11 | C4: =C2-C3 -> 1257 | D4: =B4-C4 -> 24.11 | E4: =E2-E3 -> 87 | F4: =F2-F3 -> 26.99 | G4: =SUM(C4:F4) -> 1395.1 | H4: =1050-425 -> 625 | J4: =C4-C3 -> 319
G5: =G3+G4 -> 2474.1
B6: Limit | C6: 0.3 | D6: Balance | E6: Difference
A7: Platinum | B7: -16000 | C7: =B7*0.3 -> -4800 | D7: -6564.28 | E7: =D7-C7 -> -1764.28
A8: Go | B8: -9600 | C8: =B8*0.3 -> -2880 | D8: -9380.48 | E8: =D8-C8 -> -6500.48
A9: Line of Credit | B9: -8000 | C9: =B9*0.3 -> -2400 | D9: =Forecast!K8 -> 0 | E9: =D9-C9 -> 2400 | J9: Kulo owes for deposit on 4110
A10: Costco | B10: -8200 | C10: =B10*0.3 -> -2460 | D10: -3646 | E10: =D10-C10 -> -1186 | J10: 962
A11: CareCredit | B11: -5500 | C11: =B11*0.3 -> -1650 | D11: =Forecast!L7 -> -4271.75 | E11: =D11-C11 -> -2621.75 | J11: Kulo owes for January
B12: =SUM(B7:B11) -> -47300 | C12: =SUM(C7:C11) -> -14190 | D12: =SUM(D7:D11) -> -23862.51 | E12: =SUM(E7:E11) -> -9672.51 | J12: =1142-795 -> 347
C15: Total
A16: Plan | B16: 135
A17: Raymond phone | B17: =5+7+4.17 -> 16.17 | C17: =B17+$B$16/3 -> 61.17
A18: Internet | B18: 55 | C18: =B18 -> 55
A19: Cese phone | B19: 33.75 | C19: =B19+$B$16/3 -> 78.75
A20: Corey phone | B20: 17.92 | C20: =B20+$B$16/3 -> 62.92
C21: =SUM(C17:C20) -> 257.84
A23: Cese total | C23: 142
A24: Me total | C24: =C21-C23 -> 115.84
A27: =Forecast!J6 -> Platinum | B27: =Forecast!K6 -> Visa Go | C27: =Forecast!L6 -> Costco
A28: =Forecast!J7 -> -6311.05 | B28: =Forecast!K7 -> -8503.82 | C28: =Forecast!L7 -> -4271.75 | D28: =SUM(A28:C28) -> -19086.62
A29: 0.2499 | B29: 0.2449 | C29: 0.2674

Sheet Helper - Dashboard
A1: Transactions | B1: Dates | C1: Balance | D1: Account | F1: Transactions | G1: Dates | H1: Checking | I1: Credit | J1: Savings | K1: Net Worth | L1: ="Acct 1 - "&'Monthly budget'!F6 -> Acct 1 - US Bank | M1: ="Acct 2 - "&'Monthly budget'!G6 -> Acct 2 - Wells Fargo | N1: ="Acct 3 - "&'Monthly budget'!H6 -> Acct 3 - ADP | O1: ="Acct 4 - "&'Monthly budget'!I6 -> Acct 4 - Marcus | P1: ="Acct 5 - "&'Monthly budget'!J6 -> Acct 5 - T.Rowe Price | Q1: ="Acct 6 - "&'Monthly budget'!K6 -> Acct 6 - Platinum | R1: ="Acct 7 - "&'Monthly budget'!L6 -> Acct 7 - Visa Go | S1: ="Acct 8 - "&'Monthly budget'!M6 -> Acct 8 - CareCredit | T1: ="Acct 9 - "&'Monthly budget'!N6 -> Acct 9 - Costco | U1: ="Acct 10 - "&'Monthly budget'!O6 -> Acct 10 -
A2: {=_xlfn.VSTACK({"Transactions","Dates","Balance","Account"},_xlfn.ANCHORARRAY(W2),_xlfn.ANCHORARRAY(AA2),_xlfn.ANCHORARRAY(AE2),_xlfn.ANCHORARRAY(AI2),_xlfn.ANCHORARRAY(AM2),_xlfn.ANCHORARRAY(AQ2),_xlfn.ANCHORARRAY(AU2),_xlfn.ANCHORARRAY(AY2),_xlfn.ANCHORARRAY(BC2),_xlfn.ANCHORARRAY(BG2),_xlfn.ANCHORARRAY(BK2),_xlfn.ANCHORARRAY(BO2),_xlfn.ANCHORARRAY(BS2),_xlfn.ANCHORARRAY(BW2))} -> Transactions | B2: Dates | C2: Balance | D2: Account | F2: {=_xlfn.CHOOSECOLS(_xlfn._xlws.SORT(_xlfn._xlws.FILTER(Forecast!B:O,(Forecast!B:B=FALSE)*(Forecast!C:C<>"")),3),2)} -> Starting balance | G2: {=_xlfn.CHOOSECOLS(_xlfn._xlws.SORT(_xlfn._xlws.FILTER(Forecast!B:O,(Forecast!B:B=FALSE)*(Forecast!C:C<>"")),3),3)} -> 46081 | H2: {=_xlfn.BYROW(_xlfn.HSTACK(_xlfn.ANCHORARRAY(L2):_xlfn.ANCHORARRAY(U2)),_xlfn.LAMBDA(_xlpm.a,SUMPRODUCT(--('Monthly budget'!$F$7:$O$7="Checking"),_xlpm.a)))} -> 9843.71 | I2: {=_xlfn.BYROW(_xlfn.HSTACK(_xlfn.ANCHORARRAY(L2):_xlfn.ANCHORARRAY(U2)),_xlfn.LAMBDA(_xlpm.a,SUMPRODUCT(--('Monthly budget'!$F$7:$O$7="Credit"),_xlpm.a)))} -> -19086.62 | J2: {=_xlfn.BYROW(_xlfn.HSTACK(_xlfn.ANCHORARRAY(L2):_xlfn.ANCHORARRAY(U2)),_xlfn.LAMBDA(_xlpm.a,SUMPRODUCT(--('Monthly budget'!$F$7:$O$7="Savings"),_xlpm.a)))} -> 35408.86 | K2: {=_xlfn.BYROW(_xlfn.HSTACK(_xlfn.ANCHORARRAY(L2):_xlfn.ANCHORARRAY(U2)),_xlfn.LAMBDA(_xlpm.a,SUM(_xlpm.a)))} -> 26165.95 | L2: {=_xlfn.SCAN(0,_xlfn.CHOOSECOLS(_xlfn._xlws.SORT(_xlfn._xlws.FILTER(Forecast!B:O,(Forecast!B:B=FALSE)*(Forecast!C:C<>"")),3),4),_xlfn.LAMBDA(_xlpm.a,_xlpm.v,_xlpm.a+_xlpm.v))} -> 3775.81 | M2: {=_xlfn.SCAN(0,_xlfn.CHOOSECOLS(_xlfn._xlws.SORT(_xlfn._xlws.FILTER(Forecast!B:O,(Forecast!B:B=FALSE)*(Forecast!C:C<>"")),3),5),_xlfn.LAMBDA(_xlpm.a,_xlpm.v,_xlpm.a+_xlpm.v))} -> 6067.9 | N2: {=_xlfn.SCAN(0,_xlfn.CHOOSECOLS(_xlfn._xlws.SORT(_xlfn._xlws.FILTER(Forecast!B:O,(Forecast!B:B=FALSE)*(Forecast!C:C<>"")),3),6),_xlfn.LAMBDA(_xlpm.a,_xlpm.v,_xlpm.a+_xlpm.v))} -> 23232.39 | O2: {=_xlfn.SCAN(0,_xlfn.CHOOSECOLS(_xlfn._xlws.SORT(_xlfn._xlws.FILTER(Forecast!B:O,(Forecast!B:B=FALSE)*(Forecast!C:C<>"")),3),7),_xlfn.LAMBDA(_xlpm.a,_xlpm.v,_xlpm.a+_xlpm.v))} -> 114.43 | P2: {=_xlfn.SCAN(0,_xlfn.CHOOSECOLS(_xlfn._xlws.SORT(_xlfn._xlws.FILTER(Forecast!B:O,(Forecast!B:B=FALSE)*(Forecast!C:C<>"")),3),8),_xlfn.LAMBDA(_xlpm.a,_xlpm.v,_xlpm.a+_xlpm.v))} -> 12062.04 | Q2: {=_xlfn.SCAN(0,_xlfn.CHOOSECOLS(_xlfn._xlws.SORT(_xlfn._xlws.FILTER(Forecast!B:O,(Forecast!B:B=FALSE)*(Forecast!C:C<>"")),3),9),_xlfn.LAMBDA(_xlpm.a,_xlpm.v,_xlpm.a+_xlpm.v))} -> -6311.05 | R2: {=_xlfn.SCAN(0,_xlfn.CHOOSECOLS(_xlfn._xlws.SORT(_xlfn._xlws.FILTER(Forecast!B:O,(Forecast!B:B=FALSE)*(Forecast!C:C<>"")),3),10),_xlfn.LAMBDA(_xlpm.a,_xlpm.v,_xlpm.a+_xlpm.v))} -> -8503.82 | S2: {=_xlfn.SCAN(0,_xlfn.CHOOSECOLS(_xlfn._xlws.SORT(_xlfn._xlws.FILTER(Forecast!B:O,(Forecast!B:B=FALSE)*(Forecast!C:C<>"")),3),11),_xlfn.LAMBDA(_xlpm.a,_xlpm.v,_xlpm.a+_xlpm.v))} -> -4271.75 | T2: {=_xlfn.SCAN(0,_xlfn.CHOOSECOLS(_xlfn._xlws.SORT(_xlfn._xlws.FILTER(Forecast!B:O,(Forecast!B:B=FALSE)*(Forecast!C:C<>"")),3),12),_xlfn.LAMBDA(_xlpm.a,_xlpm.v,_xlpm.a+_xlpm.v))} -> 0 | U2: {=_xlfn.SCAN(0,_xlfn.CHOOSECOLS(_xlfn._xlws.SORT(_xlfn._xlws.FILTER(Forecast!B:O,(Forecast!B:B=FALSE)*(Forecast!C:C<>"")),3),13),_xlfn.LAMBDA(_xlpm.a,_xlpm.v,_xlpm.a+_xlpm.v))} -> 0 | W2: {=_xlfn.HSTACK(_xlfn.ANCHORARRAY($F$2):_xlfn.ANCHORARRAY($G$2),_xlfn.ANCHORARRAY(L2),IF(_xlfn.SEQUENCE(ROWS(_xlfn.ANCHORARRAY($F$2)),,1,0)=1,L1,""))} -> Starting balance | X2: 46081 | Y2: 3775.81 | Z2: Acct 1 - US Bank | AA2: {=_xlfn.HSTACK(_xlfn.ANCHORARRAY($F$2):_xlfn.ANCHORARRAY($G$2),_xlfn.ANCHORARRAY(M2),IF(_xlfn.SEQUENCE(ROWS(_xlfn.ANCHORARRAY($F$2)),,1,0)=1,M1,""))} -> Starting balance | AB2: 46081 | AC2: 6067.9 | AD2: Acct 2 - Wells Fargo | AE2: {=_xlfn.HSTACK(_xlfn.ANCHORARRAY($F$2):_xlfn.ANCHORARRAY($G$2),_xlfn.ANCHORARRAY(N2),IF(_xlfn.SEQUENCE(ROWS(_xlfn.ANCHORARRAY($F$2)),,1,0)=1,N1,""))} -> Starting balance | AF2: 46081 | AG2: 23232.39 | AH2: Acct 3 - ADP | AI2: {=_xlfn.HSTACK(_xlfn.ANCHORARRAY($F$2):_xlfn.ANCHORARRAY($G$2),_xlfn.ANCHORARRAY(O2),IF(_xlfn.SEQUENCE(ROWS(_xlfn.ANCHORARRAY($F$2)),,1,0)=1,O1,""))} -> Starting balance | AJ2: 46081 | AK2: 114.43 | AL2: Acct 4 - Marcus | AM2: {=_xlfn.HSTACK(_xlfn.ANCHORARRAY($F$2):_xlfn.ANCHORARRAY($G$2),_xlfn.ANCHORARRAY(P2),IF(_xlfn.SEQUENCE(ROWS(_xlfn.ANCHORARRAY($F$2)),,1,0)=1,P1,""))} -> Starting balance | AN2: 46081 | AO2: 12062.04 | AP2: Acct 5 - T.Rowe Price | AQ2: {=_xlfn.HSTACK(_xlfn.ANCHORARRAY($F$2):_xlfn.ANCHORARRAY($G$2),_xlfn.ANCHORARRAY(Q2),IF(_xlfn.SEQUENCE(ROWS(_xlfn.ANCHORARRAY($F$2)),,1,0)=1,Q1,""))} -> Starting balance | AR2: 46081 | AS2: -6311.05 | AT2: Acct 6 - Platinum | AU2: {=_xlfn.HSTACK(_xlfn.ANCHORARRAY($F$2):_xlfn.ANCHORARRAY($G$2),_xlfn.ANCHORARRAY(R2),IF(_xlfn.SEQUENCE(ROWS(_xlfn.ANCHORARRAY($F$2)),,1,0)=1,R1,""))} -> Starting balance | AV2: 46081 | AW2: -8503.82 | AX2: Acct 7 - Visa Go | AY2: {=_xlfn.HSTACK(_xlfn.ANCHORARRAY($F$2):_xlfn.ANCHORARRAY($G$2),_xlfn.ANCHORARRAY(S2),IF(_xlfn.SEQUENCE(ROWS(_xlfn.ANCHORARRAY($F$2)),,1,0)=1,S1,""))} -> Starting balance | AZ2: 46081 | BA2: -4271.75 | BB2: Acct 8 - CareCredit | BC2: {=_xlfn.HSTACK(_xlfn.ANCHORARRAY($F$2):_xlfn.ANCHORARRAY($G$2),_xlfn.ANCHORARRAY(T2),IF(_xlfn.SEQUENCE(ROWS(_xlfn.ANCHORARRAY($F$2)),,1,0)=1,T1,""))} -> Starting balance | BD2: 46081 | BE2: 0 | BF2: Acct 9 - Costco | BG2: {=_xlfn.HSTACK(_xlfn.ANCHORARRAY($F$2):_xlfn.ANCHORARRAY($G$2),_xlfn.ANCHORARRAY(U2),IF(_xlfn.SEQUENCE(ROWS(_xlfn.ANCHORARRAY($F$2)),,1,0)=1,U1,""))} -> Starting balance | BH2: 46081 | BI2: 0 | BJ2: Acct 10 - | BK2: {=_xlfn.HSTACK(_xlfn.ANCHORARRAY($F$2):_xlfn.ANCHORARRAY($G$2),_xlfn.ANCHORARRAY(H2),IF(_xlfn.SEQUENCE(ROWS(_xlfn.ANCHORARRAY($F$2)),,1,0)=1,H1,""))} -> Starting balance | BL2: 46081 | BM2: 9843.71 | BN2: Checking | BO2: {=_xlfn.HSTACK(_xlfn.ANCHORARRAY($F$2):_xlfn.ANCHORARRAY($G$2),_xlfn.ANCHORARRAY(I2),IF(_xlfn.SEQUENCE(ROWS(_xlfn.ANCHORARRAY($F$2)),,1,0)=1,I1,""))} -> Starting balance | BP2: 46081 | BQ2: -19086.62 | BR2: Credit | BS2: {=_xlfn.HSTACK(_xlfn.ANCHORARRAY($F$2):_xlfn.ANCHORARRAY($G$2),_xlfn.ANCHORARRAY(J2),IF(_xlfn.SEQUENCE(ROWS(_xlfn.ANCHORARRAY($F$2)),,1,0)=1,J1,""))} -> Starting balance | BT2: 46081 | BU2: 35408.86 | BV2: Savings | BW2: {=_xlfn.HSTACK(_xlfn.ANCHORARRAY($F$2):_xlfn.ANCHORARRAY($G$2),_xlfn.ANCHORARRAY(K2),IF(_xlfn.SEQUENCE(ROWS(_xlfn.ANCHORARRAY($F$2)),,1,0)=1,K1,""))} -> Starting balance | BX2: 46081 | BY2: 26165.95 | BZ2: Net Worth
A3: Starting balance | B3: 46081 | C3: 3775.81 | D3: Acct 1 - US Bank | F3: Costco Citi | G3: 46081 | H3: 9703.71 | I3: -19086.62 | J3: 35408.86 | K3: 26165.95 | L3: 3635.81 | M3: 6067.9 | N3: 23232.39 | O3: 114.43 | P3: 12062.04 | Q3: -6311.05 | R3: -8503.82 | S3: -4271.75 | T3: 0 | U3: 140 | W3: Costco Citi | X3: 46081 | Y3: 3635.81 | Z3: Acct 1 - US Bank | AA3: Costco Citi | AB3: 46081 | AC3: 6067.9 | AD3: Acct 2 - Wells Fargo | AE3: Costco Citi | AF3: 46081 | AG3: 23232.39 | AH3: Acct 3 - ADP | AI3: Costco Citi | AJ3: 46081 | AK3: 114.43 | AL3: Acct 4 - Marcus | AM3: Costco Citi | AN3: 46081 | AO3: 12062.04 | AP3: Acct 5 - T.Rowe Price | AQ3: Costco Citi | AR3: 46081 | AS3: -6311.05 | AT3: Acct 6 - Platinum | AU3: Costco Citi | AV3: 46081 | AW3: -8503.82 | AX3: Acct 7 - Visa Go | AY3: Costco Citi | AZ3: 46081 | BA3: -4271.75 | BB3: Acct 8 - CareCredit | BC3: Costco Citi | BD3: 46081 | BE3: 0 | BF3: Acct 9 - Costco | BG3: Costco Citi | BH3: 46081 | BI3: 140 | BJ3: Acct 10 - | BK3: Costco Citi | BL3: 46081 | BM3: 9703.71 | BN3: Checking | BO3: Costco Citi | BP3: 46081 | BQ3: -19086.62 | BR3: Credit | BS3: Costco Citi | BT3: 46081 | BU3: 35408.86 | BV3: Savings | BW3: Costco Citi | BX3: 46081 | BY3: 26165.95 | BZ3: Net Worth
A4: Costco Citi | B4: 46081 | C4: 3635.81 | D4: Acct 1 - US Bank | F4: Kulo SDGE | G4: 46081 | H4: 9621.71 | I4: -19086.62 | J4: 35408.86 | K4: 26083.95 | L4: 3553.81 | M4: 6067.9 | N4: 23232.39 | O4: 114.43 | P4: 12062.04 | Q4: -6311.05 | R4: -8503.82 | S4: -4271.75 | T4: 0 | U4: 140 | W4: Kulo SDGE | X4: 46081 | Y4: 3553.81 | Z4: Acct 1 - US Bank | AA4: Kulo SDGE | AB4: 46081 | AC4: 6067.9 | AD4: Acct 2 - Wells Fargo | AE4: Kulo SDGE | AF4: 46081 | AG4: 23232.39 | AH4: Acct 3 - ADP | AI4: Kulo SDGE | AJ4: 46081 | AK4: 114.43 | AL4: Acct 4 - Marcus | AM4: Kulo SDGE | AN4: 46081 | AO4: 12062.04 | AP4: Acct 5 - T.Rowe Price | AQ4: Kulo SDGE | AR4: 46081 | AS4: -6311.05 | AT4: Acct 6 - Platinum | AU4: Kulo SDGE | AV4: 46081 | AW4: -8503.82 | AX4: Acct 7 - Visa Go | AY4: Kulo SDGE | AZ4: 46081 | BA4: -4271.75 | BB4: Acct 8 - CareCredit | BC4: Kulo SDGE | BD4: 46081 | BE4: 0 | BF4: Acct 9 - Costco | BG4: Kulo SDGE | BH4: 46081 | BI4: 140 | BJ4: Acct 10 - | BK4: Kulo SDGE | BL4: 46081 | BM4: 9621.71 | BN4: Checking | BO4: Kulo SDGE | BP4: 46081 | BQ4: -19086.62 | BR4: Credit | BS4: Kulo SDGE | BT4: 46081 | BU4: 35408.86 | BV4: Savings | BW4: Kulo SDGE | BX4: 46081 | BY4: 26083.95 | BZ4: Net Worth
A5: Kulo SDGE | B5: 46081 | C5: 3553.81 | D5: Acct 1 - US Bank | F5: Groceries | G5: 46081 | H5: 9421.71 | I5: -19086.62 | J5: 35408.86 | K5: 25883.95 | L5: 3553.81 | M5: 5867.9 | N5: 23232.39 | O5: 114.43 | P5: 12062.04 | Q5: -6311.05 | R5: -8503.82 | S5: -4271.75 | T5: 0 | U5: 140 | W5: Groceries | X5: 46081 | Y5: 3553.81 | Z5: Acct 1 - US Bank | AA5: Groceries | AB5: 46081 | AC5: 5867.9 | AD5: Acct 2 - Wells Fargo | AE5: Groceries | AF5: 46081 | AG5: 23232.39 | AH5: Acct 3 - ADP | AI5: Groceries | AJ5: 46081 | AK5: 114.43 | AL5: Acct 4 - Marcus | AM5: Groceries | AN5: 46081 | AO5: 12062.04 | AP5: Acct 5 - T.Rowe Price | AQ5: Groceries | AR5: 46081 | AS5: -6311.05 | AT5: Acct 6 - Platinum | AU5: Groceries | AV5: 46081 | AW5: -8503.82 | AX5: Acct 7 - Visa Go | AY5: Groceries | AZ5: 46081 | BA5: -4271.75 | BB5: Acct 8 - CareCredit | BC5: Groceries | BD5: 46081 | BE5: 0 | BF5: Acct 9 - Costco | BG5: Groceries | BH5: 46081 | BI5: 140 | BJ5: Acct 10 - | BK5: Groceries | BL5: 46081 | BM5: 9421.71 | BN5: Checking | BO5: Groceries | BP5: 46081 | BQ5: -19086.62 | BR5: Credit | BS5: Groceries | BT5: 46081 | BU5: 35408.86 | BV5: Savings | BW5: Groceries | BX5: 46081 | BY5: 25883.95 | BZ5: Net Worth
A6: Groceries | B6: 46081 | C6: 3553.81 | D6: Acct 1 - US Bank | F6: Food & Drinks | G6: 46081 | H6: 9221.71 | I6: -19086.62 | J6: 35408.86 | K6: 25683.95 | L6: 3553.81 | M6: 5667.9 | N6: 23232.39 | O6: 114.43 | P6: 12062.04 | Q6: -6311.05 | R6: -8503.82 | S6: -4271.75 | T6: 0 | U6: 140 | W6: Food & Drinks | X6: 46081 | Y6: 3553.81 | Z6: Acct 1 - US Bank | AA6: Food & Drinks | AB6: 46081 | AC6: 5667.9 | AD6: Acct 2 - Wells Fargo | AE6: Food & Drinks | AF6: 46081 | AG6: 23232.39 | AH6: Acct 3 - ADP | AI6: Food & Drinks | AJ6: 46081 | AK6: 114.43 | AL6: Acct 4 - Marcus | AM6: Food & Drinks | AN6: 46081 | AO6: 12062.04 | AP6: Acct 5 - T.Rowe Price | AQ6: Food & Drinks | AR6: 46081 | AS6: -6311.05 | AT6: Acct 6 - Platinum | AU6: Food & Drinks | AV6: 46081 | AW6: -8503.82 | AX6: Acct 7 - Visa Go | AY6: Food & Drinks | AZ6: 46081 | BA6: -4271.75 | BB6: Acct 8 - CareCredit | BC6: Food & Drinks | BD6: 46081 | BE6: 0 | BF6: Acct 9 - Costco | BG6: Food & Drinks | BH6: 46081 | BI6: 140 | BJ6: Acct 10 - | BK6: Food & Drinks | BL6: 46081 | BM6: 9221.71 | BN6: Checking | BO6: Food & Drinks | BP6: 46081 | BQ6: -19086.62 | BR6: Credit | BS6: Food & Drinks | BT6: 46081 | BU6: 35408.86 | BV6: Savings | BW6: Food & Drinks | BX6: 46081 | BY6: 25683.95 | BZ6: Net Worth
A7: Food & Drinks | B7: 46081 | C7: 3553.81 | D7: Acct 1 - US Bank | F7: SDGE | G7: 46081 | H7: 9137.71 | I7: -19086.62 | J7: 35408.86 | K7: 25599.95 | L7: 3469.81 | M7: 5667.9 | N7: 23232.39 | O7: 114.43 | P7: 12062.04 | Q7: -6311.05 | R7: -8503.82 | S7: -4271.75 | T7: 0 | U7: 140 | W7: SDGE | X7: 46081 | Y7: 3469.81 | Z7: Acct 1 - US Bank | AA7: SDGE | AB7: 46081 | AC7: 5667.9 | AD7: Acct 2 - Wells Fargo | AE7: SDGE | AF7: 46081 | AG7: 23232.39 | AH7: Acct 3 - ADP | AI7: SDGE | AJ7: 46081 | AK7: 114.43 | AL7: Acct 4 - Marcus | AM7: SDGE | AN7: 46081 | AO7: 12062.04 | AP7: Acct 5 - T.Rowe Price | AQ7: SDGE | AR7: 46081 | AS7: -6311.05 | AT7: Acct 6 - Platinum | AU7: SDGE | AV7: 46081 | AW7: -8503.82 | AX7: Acct 7 - Visa Go | AY7: SDGE | AZ7: 46081 | BA7: -4271.75 | BB7: Acct 8 - CareCredit | BC7: SDGE | BD7: 46081 | BE7: 0 | BF7: Acct 9 - Costco | BG7: SDGE | BH7: 46081 | BI7: 140 | BJ7: Acct 10 - | BK7: SDGE | BL7: 46081 | BM7: 9137.71 | BN7: Checking | BO7: SDGE | BP7: 46081 | BQ7: -19086.62 | BR7: Credit | BS7: SDGE | BT7: 46081 | BU7: 35408.86 | BV7: Savings | BW7: SDGE | BX7: 46081 | BY7: 25599.95 | BZ7: Net Worth
A8: SDGE | B8: 46081 | C8: 3469.81 | D8: Acct 1 - US Bank | F8: Prime Ad-Free | G8: 46081 | H8: 9134.72 | I8: -19086.62 | J8: 35408.86 | K8: 25596.96 | L8: 3466.82 | M8: 5667.9 | N8: 23232.39 | O8: 114.43 | P8: 12062.04 | Q8: -6311.05 | R8: -8503.82 | S8: -4271.75 | T8: 0 | U8: 140 | W8: Prime Ad-Free | X8: 46081 | Y8: 3466.82 | Z8: Acct 1 - US Bank | AA8: Prime Ad-Free | AB8: 46081 | AC8: 5667.9 | AD8: Acct 2 - Wells Fargo | AE8: Prime Ad-Free | AF8: 46081 | AG8: 23232.39 | AH8: Acct 3 - ADP | AI8: Prime Ad-Free | AJ8: 46081 | AK8: 114.43 | AL8: Acct 4 - Marcus | AM8: Prime Ad-Free | AN8: 46081 | AO8: 12062.04 | AP8: Acct 5 - T.Rowe Price | AQ8: Prime Ad-Free | AR8: 46081 | AS8: -6311.05 | AT8: Acct 6 - Platinum | AU8: Prime Ad-Free | AV8: 46081 | AW8: -8503.82 | AX8: Acct 7 - Visa Go | AY8: Prime Ad-Free | AZ8: 46081 | BA8: -4271.75 | BB8: Acct 8 - CareCredit | BC8: Prime Ad-Free | BD8: 46081 | BE8: 0 | BF8: Acct 9 - Costco | BG8: Prime Ad-Free | BH8: 46081 | BI8: 140 | BJ8: Acct 10 - | BK8: Prime Ad-Free | BL8: 46081 | BM8: 9134.72 | BN8: Checking | BO8: Prime Ad-Free | BP8: 46081 | BQ8: -19086.62 | BR8: Credit | BS8: Prime Ad-Free | BT8: 46081 | BU8: 35408.86 | BV8: Savings | BW8: Prime Ad-Free | BX8: 46081 | BY8: 25596.96 | BZ8: Net Worth
A9: Prime Ad-Free | B9: 46081 | C9: 3466.82 | D9: Acct 1 - US Bank | F9: Disability | G9: 46082 | H9: 9491.38 | I9: -19086.62 | J9: 35408.86 | K9: 25953.62 | L9: 3466.82 | M9: 6024.56 | N9: 23232.39 | O9: 114.43 | P9: 12062.04 | Q9: -6311.05 | R9: -8503.82 | S9: -4271.75 | T9: 0 | U9: 140 | W9: Disability | X9: 46082 | Y9: 3466.82 | Z9: Acct 1 - US Bank | AA9: Disability | AB9: 46082 | AC9: 6024.56 | AD9: Acct 2 - Wells Fargo | AE9: Disability | AF9: 46082 | AG9: 23232.39 | AH9: Acct 3 - ADP | AI9: Disability | AJ9: 46082 | AK9: 114.43 | AL9: Acct 4 - Marcus | AM9: Disability | AN9: 46082 | AO9: 12062.04 | AP9: Acct 5 - T.Rowe Price | AQ9: Disability | AR9: 46082 | AS9: -6311.05 | AT9: Acct 6 - Platinum | AU9: Disability | AV9: 46082 | AW9: -8503.82 | AX9: Acct 7 - Visa Go | AY9: Disability | AZ9: 46082 | BA9: -4271.75 | BB9: Acct 8 - CareCredit | BC9: Disability | BD9: 46082 | BE9: 0 | BF9: Acct 9 - Costco | BG9: Disability | BH9: 46082 | BI9: 140 | BJ9: Acct 10 - | BK9: Disability | BL9: 46082 | BM9: 9491.38 | BN9: Checking | BO9: Disability | BP9: 46082 | BQ9: -19086.62 | BR9: Credit | BS9: Disability | BT9: 46082 | BU9: 35408.86 | BV9: Savings | BW9: Disability | BX9: 46082 | BY9: 25953.62 | BZ9: Net Worth
A10: Disability | B10: 46082 | C10: 3466.82 | D10: Acct 1 - US Bank | F10: Kulo Rent | G10: 46082 | H10: 8532.38 | I10: -19086.62 | J10: 35408.86 | K10: 24994.62 | L10: 2507.82 | M10: 6024.56 | N10: 23232.39 | O10: 114.43 | P10: 12062.04 | Q10: -6311.05 | R10: -8503.82 | S10: -4271.75 | T10: 0 | U10: 140 | W10: Kulo Rent | X10: 46082 | Y10: 2507.82 | Z10: Acct 1 - US Bank | AA10: Kulo Rent | AB10: 46082 | AC10: 6024.56 | AD10: Acct 2 - Wells Fargo | AE10: Kulo Rent | AF10: 46082 | AG10: 23232.39 | AH10: Acct 3 - ADP | AI10: Kulo Rent | AJ10: 46082 | AK10: 114.43 | AL10: Acct 4 - Marcus | AM10: Kulo Rent | AN10: 46082 | AO10: 12062.04 | AP10: Acct 5 - T.Rowe Price | AQ10: Kulo Rent | AR10: 46082 | AS10: -6311.05 | AT10: Acct 6 - Platinum | AU10: Kulo Rent | AV10: 46082 | AW10: -8503.82 | AX10: Acct 7 - Visa Go | AY10: Kulo Rent | AZ10: 46082 | BA10: -4271.75 | BB10: Acct 8 - CareCredit | BC10: Kulo Rent | BD10: 46082 | BE10: 0 | BF10: Acct 9 - Costco | BG10: Kulo Rent | BH10: 46082 | BI10: 140 | BJ10: Acct 10 - | BK10: Kulo Rent | BL10: 46082 | BM10: 8532.38 | BN10: Checking | BO10: Kulo Rent | BP10: 46082 | BQ10: -19086.62 | BR10: Credit | BS10: Kulo Rent | BT10: 46082 | BU10: 35408.86 | BV10: Savings | BW10: Kulo Rent | BX10: 46082 | BY10: 24994.62 | BZ10: Net Worth
A11: Kulo Rent | B11: 46082 | C11: 2507.82 | D11: Acct 1 - US Bank | F11: Rent | G11: 46082 | H11: 7254.41 | I11: -19086.62 | J11: 35408.86 | K11: 23716.65 | L11: 1229.85 | M11: 6024.56 | N11: 23232.39 | O11: 114.43 | P11: 12062.04 | Q11: -6311.05 | R11: -8503.82 | S11: -4271.75 | T11: 0 | U11: 140 | W11: Rent | X11: 46082 | Y11: 1229.85 | Z11: Acct 1 - US Bank | AA11: Rent | AB11: 46082 | AC11: 6024.56 | AD11: Acct 2 - Wells Fargo | AE11: Rent | AF11: 46082 | AG11: 23232.39 | AH11: Acct 3 - ADP | AI11: Rent | AJ11: 46082 | AK11: 114.43 | AL11: Acct 4 - Marcus | AM11: Rent | AN11: 46082 | AO11: 12062.04 | AP11: Acct 5 - T.Rowe Price | AQ11: Rent | AR11: 46082 | AS11: -6311.05 | AT11: Acct 6 - Platinum | AU11: Rent | AV11: 46082 | AW11: -8503.82 | AX11: Acct 7 - Visa Go | AY11: Rent | AZ11: 46082 | BA11: -4271.75 | BB11: Acct 8 - CareCredit | BC11: Rent | BD11: 46082 | BE11: 0 | BF11: Acct 9 - Costco | BG11: Rent | BH11: 46082 | BI11: 140 | BJ11: Acct 10 - | BK11: Rent | BL11: 46082 | BM11: 7254.41 | BN11: Checking | BO11: Rent | BP11: 46082 | BQ11: -19086.62 | BR11: Credit | BS11: Rent | BT11: 46082 | BU11: 35408.86 | BV11: Savings | BW11: Rent | BX11: 46082 | BY11: 23716.65 | BZ11: Net Worth
A12: Rent | B12: 46082 | C12: 1229.85 | D12: Acct 1 - US Bank | F12: Visa Platinum | G12: 46084 | H12: 7025.41 | I12: -18775.62 | J12: 35408.86 | K12: 23798.65 | L12: 1000.85 | M12: 6024.56 | N12: 23232.39 | O12: 114.43 | P12: 12062.04 | Q12: -6000.05 | R12: -8503.82 | S12: -4271.75 | T12: 0 | U12: 140 | W12: Visa Platinum | X12: 46084 | Y12: 1000.85 | Z12: Acct 1 - US Bank | AA12: Visa Platinum | AB12: 46084 | AC12: 6024.56 | AD12: Acct 2 - Wells Fargo | AE12: Visa Platinum | AF12: 46084 | AG12: 23232.39 | AH12: Acct 3 - ADP | AI12: Visa Platinum | AJ12: 46084 | AK12: 114.43 | AL12: Acct 4 - Marcus | AM12: Visa Platinum | AN12: 46084 | AO12: 12062.04 | AP12: Acct 5 - T.Rowe Price | AQ12: Visa Platinum | AR12: 46084 | AS12: -6000.05 | AT12: Acct 6 - Platinum | AU12: Visa Platinum | AV12: 46084 | AW12: -8503.82 | AX12: Acct 7 - Visa Go | AY12: Visa Platinum | AZ12: 46084 | BA12: -4271.75 | BB12: Acct 8 - CareCredit | BC12: Visa Platinum | BD12: 46084 | BE12: 0 | BF12: Acct 9 - Costco | BG12: Visa Platinum | BH12: 46084 | BI12: 140 | BJ12: Acct 10 - | BK12: Visa Platinum | BL12: 46084 | BM12: 7025.41 | BN12: Checking | BO12: Visa Platinum | BP12: 46084 | BQ12: -18775.62 | BR12: Credit | BS12: Visa Platinum | BT12: 46084 | BU12: 35408.86 | BV12: Savings | BW12: Visa Platinum | BX12: 46084 | BY12: 23798.65 | BZ12: Net Worth
A13: Visa Platinum | B13: 46084 | C13: 1000.85 | D13: Acct 1 - US Bank | F13: Kulo Internet | G13: 46086 | H13: 6997.41 | I13: -18775.62 | J13: 35408.86 | K13: 23770.65 | L13: 972.85 | M13: 6024.56 | N13: 23232.39 | O13: 114.43 | P13: 12062.04 | Q13: -6000.05 | R13: -8503.82 | S13: -4271.75 | T13: 0 | U13: 140 | W13: Kulo Internet | X13: 46086 | Y13: 972.85 | Z13: Acct 1 - US Bank | AA13: Kulo Internet | AB13: 46086 | AC13: 6024.56 | AD13: Acct 2 - Wells Fargo | AE13: Kulo Internet | AF13: 46086 | AG13: 23232.39 | AH13: Acct 3 - ADP | AI13: Kulo Internet | AJ13: 46086 | AK13: 114.43 | AL13: Acct 4 - Marcus | AM13: Kulo Internet | AN13: 46086 | AO13: 12062.04 | AP13: Acct 5 - T.Rowe Price | AQ13: Kulo Internet | AR13: 46086 | AS13: -6000.05 | AT13: Acct 6 - Platinum | AU13: Kulo Internet | AV13: 46086 | AW13: -8503.82 | AX13: Acct 7 - Visa Go | AY13: Kulo Internet | AZ13: 46086 | BA13: -4271.75 | BB13: Acct 8 - CareCredit | BC13: Kulo Internet | BD13: 46086 | BE13: 0 | BF13: Acct 9 - Costco | BG13: Kulo Internet | BH13: 46086 | BI13: 140 | BJ13: Acct 10 - | BK13: Kulo Internet | BL13: 46086 | BM13: 6997.41 | BN13: Checking | BO13: Kulo Internet | BP13: 46086 | BQ13: -18775.62 | BR13: Credit | BS13: Kulo Internet | BT13: 46086 | BU13: 35408.86 | BV13: Savings | BW13: Kulo Internet | BX13: 46086 | BY13: 23770.65 | BZ13: Net Worth
A14: Kulo Internet | B14: 46086 | C14: 972.85 | D14: Acct 1 - US Bank | F14: Cese Phone | G14: 46086 | H14: 6855.41 | I14: -18775.62 | J14: 35408.86 | K14: 23628.65 | L14: 830.85 | M14: 6024.56 | N14: 23232.39 | O14: 114.43 | P14: 12062.04 | Q14: -6000.05 | R14: -8503.82 | S14: -4271.75 | T14: 0 | U14: 140 | W14: Cese Phone | X14: 46086 | Y14: 830.85 | Z14: Acct 1 - US Bank | AA14: Cese Phone | AB14: 46086 | AC14: 6024.56 | AD14: Acct 2 - Wells Fargo | AE14: Cese Phone | AF14: 46086 | AG14: 23232.39 | AH14: Acct 3 - ADP | AI14: Cese Phone | AJ14: 46086 | AK14: 114.43 | AL14: Acct 4 - Marcus | AM14: Cese Phone | AN14: 46086 | AO14: 12062.04 | AP14: Acct 5 - T.Rowe Price | AQ14: Cese Phone | AR14: 46086 | AS14: -6000.05 | AT14: Acct 6 - Platinum | AU14: Cese Phone | AV14: 46086 | AW14: -8503.82 | AX14: Acct 7 - Visa Go | AY14: Cese Phone | AZ14: 46086 | BA14: -4271.75 | BB14: Acct 8 - CareCredit | BC14: Cese Phone | BD14: 46086 | BE14: 0 | BF14: Acct 9 - Costco | BG14: Cese Phone | BH14: 46086 | BI14: 140 | BJ14: Acct 10 - | BK14: Cese Phone | BL14: 46086 | BM14: 6855.41 | BN14: Checking | BO14: Cese Phone | BP14: 46086 | BQ14: -18775.62 | BR14: Credit | BS14: Cese Phone | BT14: 46086 | BU14: 35408.86 | BV14: Savings | BW14: Cese Phone | BX14: 46086 | BY14: 23628.65 | BZ14: Net Worth
... A773: Google+ | B773: 46810 | C773: 2675.76 | D773: Acct 1 - US Bank | F773: Tidal | G773: 46810 | H773: 20012.51 | I773: -8148.6 | J773: 41232.86 | K773: 56456.77 | L773: 2664.77 | M773: 17347.74 | N773: 29056.39 | O773: 114.43 | P773: 12062.04 | Q773: 1122.97 | R773: -4999.82 | S773: -4271.75 | T773: 0 | U773: 3360 | W773: Tidal | X773: 46810 | Y773: 2664.77 | Z773: Acct 1 - US Bank | AA773: Tidal | AB773: 46810 | AC773: 17347.74 | AD773: Acct 2 - Wells Fargo | AE773: Tidal | AF773: 46810 | AG773: 29056.39 | AH773: Acct 3 - ADP | AI773: Tidal | AJ773: 46810 | AK773: 114.43 | AL773: Acct 4 - Marcus | AM773: Tidal | AN773: 46810 | AO773: 12062.04 | AP773: Acct 5 - T.Rowe Price | AQ773: Tidal | AR773: 46810 | AS773: 1122.97 | AT773: Acct 6 - Platinum | AU773: Tidal | AV773: 46810 | AW773: -4999.82 | AX773: Acct 7 - Visa Go | AY773: Tidal | AZ773: 46810 | BA773: -4271.75 | BB773: Acct 8 - CareCredit | BC773: Tidal | BD773: 46810 | BE773: 0 | BF773: Acct 9 - Costco | BG773: Tidal | BH773: 46810 | BI773: 3360 | BJ773: Acct 10 - | BK773: Tidal | BL773: 46810 | BM773: 20012.51 | BN773: Checking | BO773: Tidal | BP773: 46810 | BQ773: -8148.6 | BR773: Credit | BS773: Tidal | BT773: 46810 | BU773: 41232.86 | BV773: Savings | BW773: Tidal | BX773: 46810 | BY773: 56456.77 | BZ773: Net Worth
A774: Tidal | B774: 46810 | C774: 2664.77 | D774: Acct 1 - US Bank
A775: Starting balance | B775: 46081 | C775: 6067.9 | D775: Acct 2 - Wells Fargo
A776: Costco Citi | B776: 46081 | C776: 6067.9 | D776: Acct 2 - Wells Fargo
A777: Kulo SDGE | B777: 46081 | C777: 6067.9 | D777: Acct 2 - Wells Fargo
A778: Groceries | B778: 46081 | C778: 5867.9 | D778: Acct 2 - Wells Fargo
A779: Food & Drinks | B779: 46081 | C779: 5667.9 | D779: Acct 2 - Wells Fargo
A780: SDGE | B780: 46081 | C780: 5667.9 | D780: Acct 2 - Wells Fargo
A781: Prime Ad-Free | B781: 46081 | C781: 5667.9 | D781: Acct 2 - Wells Fargo
A782: Disability | B782: 46082 | C782: 6024.56 | D782: Acct 2 - Wells Fargo
A783: Kulo Rent | B783: 46082 | C783: 6024.56 | D783: Acct 2 - Wells Fargo
A784: Rent | B784: 46082 | C784: 6024.56 | D784: Acct 2 - Wells Fargo
A785: Visa Platinum | B785: 46084 | C785: 6024.56 | D785: Acct 2 - Wells Fargo
... A10810: Tidal | B10810: 46810 | C10810: 56456.77 | D10810: Net Worth

Sheet Helper - All dates
A1: First Date | B1: Transactions | C1: Freq | D1: Unit | E1: Start Date | F1: Dates
A2: =Forecast!$D$7 -> 46081 | B2: {=_xlfn._xlws.FILTER(OFFSET('Monthly budget'!$E$11,0,0,ROW('Monthly budget'!TotalRow)-ROW('Monthly budget'!IncomeRow)-4,1),OFFSET('Monthly budget'!$E$11,0,0,ROW('Monthly budget'!TotalRow)-ROW('Monthly budget'!IncomeRow)-4,1)<>"")} -> Paycheck | C2: {=_xlfn.XLOOKUP(_xlfn.ANCHORARRAY($B$2),'Monthly budget'!$E$8:$E$89,'Monthly budget'!$B$8:$B$89,"",0)} -> 2 | D2: {=_xlfn.XLOOKUP(_xlfn.ANCHORARRAY($B$2),'Monthly budget'!$E$8:$E$89,'Monthly budget'!$C$8:$C$89,"",0)} -> week(s) | E2: {=OFFSET('Helper - Start date'!$E$2,0,0,ROWS(_xlfn.ANCHORARRAY('Helper - All dates'!$B$2)),1)} -> 46094 | F2: {=_xlfn.LET(_xlpm.strFreq,INDEX(_xlfn.ANCHORARRAY(C2),_xlfn.SEQUENCE(ROWS(_xlfn.ANCHORARRAY(C2)),1,1,1)), _xlfn.IFS(_xlfn.ANCHORARRAY(D2)="year(s)", _xlfn.LET(_xlpm.yrTest,EDATE(INDEX(_xlfn.ANCHORARRAY(E2),ROW(_xlfn.ANCHORARRAY(E2))-1),_xlfn.SEQUENCE(1,100,1,1)*12*_xlpm.strFreq), IF(_xlpm.yrTest<EDATE(A2,24), _xlpm.yrTest, "" ) ),_xlfn.ANCHORARRAY( D2)="month(s)", _xlfn.LET(_xlpm.mnthTest,EDATE(INDEX(_xlfn.ANCHORARRAY(E2),ROW(_xlfn.ANCHORARRAY(E2))-1),_xlfn.SEQUENCE(1,100,1,1)*_xlpm.strFreq), IF(_xlpm.mnthTest<EDATE(A2,24), _xlpm.mnthTest, "" ) ),_xlfn.ANCHORARRAY( D2)="week(s)", _xlfn.LET(_xlpm.wkTest,INDEX(_xlfn.ANCHORARRAY(E2),ROW(_xlfn.ANCHORARRAY(E2))-1)+_xlfn.SEQUENCE(1,100,7,7)*_xlpm.strFreq, IF(_xlpm.wkTest<EDATE(A2,24), _xlpm.wkTest, "" ) ),_xlfn.ANCHORARRAY( D2)="day(s)", _xlfn.LET(_xlpm.dyTest,INDEX(_xlfn.ANCHORARRAY(E2),ROW(_xlfn.ANCHORARRAY(E2))-1)+_xlfn.SEQUENCE(1,100,1,1)*_xlpm.strFreq, IF(_xlpm.dyTest<EDATE(A2,24), _xlpm.dyTest, "" ) ), TRUE, "" ) )} -> 46108 | G2: 46122 | H2: 46136 | I2: 46150 | J2: 46164 | K2: 46178 | L2: 46192 | M2: 46206 | N2: 46220 | O2: 46234 | P2: 46248 | Q2: 46262 | R2: 46276 | S2: 46290 | T2: 46304 | U2: 46318 | V2: 46332 | W2: 46346 | X2: 46360 | Y2: 46374 | Z2: 46388 | AA2: 46402 | AB2: 46416 | AC2: 46430 | AD2: 46444 | AE2: 46458 | AF2: 46472 | AG2: 46486 | AH2: 46500 | AI2: 46514 | AJ2: 46528 | AK2: 46542 | AL2: 46556 | AM2: 46570 | AN2: 46584 | AO2: 46598 | AP2: 46612 | AQ2: 46626 | AR2: 46640 | AS2: 46654 | AT2: 46668 | AU2: 46682 | AV2: 46696 | AW2: 46710 | AX2: 46724 | AY2: 46738 | AZ2: 46752 | BA2: 46766 | BB2: 46780 | BC2: 46794 | BD2: 46808
A3: First full month start date | B3: Disability | C3: 1 | D3: month(s) | E3: 46082 | F3: 46113 | G3: 46143 | H3: 46174 | I3: 46204 | J3: 46235 | K3: 46266 | L3: 46296 | M3: 46327 | N3: 46357 | O3: 46388 | P3: 46419 | Q3: 46447 | R3: 46478 | S3: 46508 | T3: 46539 | U3: 46569 | V3: 46600 | W3: 46631 | X3: 46661 | Y3: 46692 | Z3: 46722 | AA3: 46753 | AB3: 46784
A4: {=_xlfn.LET(_xlpm.TransDate,_xlfn.CHOOSECOLS(_xlfn.ANCHORARRAY(Forecast!C29),2),INDEX(_xlpm.TransDate,MATCH(EOMONTH(A2,0),_xlfn.CHOOSECOLS(_xlfn.ANCHORARRAY(Forecast!C29),2),1)+1))} -> 46082 | B4: Ameritas | C4: 2 | D4: week(s) | E4: 46094 | F4: 46108 | G4: 46122 | H4: 46136 | I4: 46150 | J4: 46164 | K4: 46178 | L4: 46192 | M4: 46206 | N4: 46220 | O4: 46234 | P4: 46248 | Q4: 46262 | R4: 46276 | S4: 46290 | T4: 46304 | U4: 46318 | V4: 46332 | W4: 46346 | X4: 46360 | Y4: 46374 | Z4: 46388 | AA4: 46402 | AB4: 46416 | AC4: 46430 | AD4: 46444 | AE4: 46458 | AF4: 46472 | AG4: 46486 | AH4: 46500 | AI4: 46514 | AJ4: 46528 | AK4: 46542 | AL4: 46556 | AM4: 46570 | AN4: 46584 | AO4: 46598 | AP4: 46612 | AQ4: 46626 | AR4: 46640 | AS4: 46654 | AT4: 46668 | AU4: 46682 | AV4: 46696 | AW4: 46710 | AX4: 46724 | AY4: 46738 | AZ4: 46752 | BA4: 46766 | BB4: 46780 | BC4: 46794 | BD4: 46808
A5: First full month start row | B5: Visa Platinum | C5: 1 | D5: month(s) | E5: 46084 | F5: 46115 | G5: 46145 | H5: 46176 | I5: 46206 | J5: 46237 | K5: 46268 | L5: 46298 | M5: 46329 | N5: 46359 | O5: 46390 | P5: 46421 | Q5: 46449 | R5: 46480 | S5: 46510 | T5: 46541 | U5: 46571 | V5: 46602 | W5: 46633 | X5: 46663 | Y5: 46694 | Z5: 46724 | AA5: 46755 | AB5: 46786
A6: =MATCH(A4,_xlfn.CHOOSECOLS(_xlfn.ANCHORARRAY(Forecast!C29),2),0)+1 -> 9 | B6: Viso Go | C6: 1 | D6: month(s) | E6: 46092 | F6: 46123 | G6: 46153 | H6: 46184 | I6: 46214 | J6: 46245 | K6: 46276 | L6: 46306 | M6: 46337 | N6: 46367 | O6: 46398 | P6: 46429 | Q6: 46457 | R6: 46488 | S6: 46518 | T6: 46549 | U6: 46579 | V6: 46610 | W6: 46641 | X6: 46671 | Y6: 46702 | Z6: 46732 | AA6: 46763 | AB6: 46794
A7: Last Date | B7: Costco Citi | C7: 1 | D7: month(s) | E7: 46081 | F7: 46109 | G7: 46140 | H7: 46170 | I7: 46201 | J7: 46231 | K7: 46262 | L7: 46293 | M7: 46323 | N7: 46354 | O7: 46384 | P7: 46415 | Q7: 46446 | R7: 46474 | S7: 46505 | T7: 46535 | U7: 46566 | V7: 46596 | W7: 46627 | X7: 46658 | Y7: 46688 | Z7: 46719 | AA7: 46749 | AB7: 46780
A8: =_xlfn.LET(_xlpm.TransDate,_xlfn.CHOOSECOLS(_xlfn.ANCHORARRAY(Forecast!C29),2),DATE(YEAR(MAX(_xlpm.TransDate)),MONTH(MAX(_xlpm.TransDate))+1,1)) -> 46813 | B8: Kulo Transfer | C8: 1 | D8: month(s) | E8: 46081 | F8: 46109 | G8: 46140 | H8: 46170 | I8: 46201 | J8: 46231 | K8: 46262 | L8: 46293 | M8: 46323 | N8: 46354 | O8: 46384 | P8: 46415 | Q8: 46446 | R8: 46474 | S8: 46505 | T8: 46535 | U8: 46566 | V8: 46596 | W8: 46627 | X8: 46658 | Y8: 46688 | Z8: 46719 | AA8: 46749 | AB8: 46780
A9: Number of Months | B9: Kulo Rent | C9: 1 | D9: month(s) | E9: 46082 | F9: 46113 | G9: 46143 | H9: 46174 | I9: 46204 | J9: 46235 | K9: 46266 | L9: 46296 | M9: 46327 | N9: 46357 | O9: 46388 | P9: 46419 | Q9: 46447 | R9: 46478 | S9: 46508 | T9: 46539 | U9: 46569 | V9: 46600 | W9: 46631 | X9: 46661 | Y9: 46692 | Z9: 46722 | AA9: 46753 | AB9: 46784
A10: =DATEDIF(EOMONTH(A2,0)+1,A8,"m") -> 24 | B10: Kulo SDGE | C10: 1 | D10: month(s) | E10: 46081 | F10: 46109 | G10: 46140 | H10: 46170 | I10: 46201 | J10: 46231 | K10: 46262 | L10: 46293 | M10: 46323 | N10: 46354 | O10: 46384 | P10: 46415 | Q10: 46446 | R10: 46474 | S10: 46505 | T10: 46535 | U10: 46566 | V10: 46596 | W10: 46627 | X10: 46658 | Y10: 46688 | Z10: 46719 | AA10: 46749 | AB10: 46780
B11: Kulo Internet | C11: 1 | D11: month(s) | E11: 46086 | F11: 46117 | G11: 46147 | H11: 46178 | I11: 46208 | J11: 46239 | K11: 46270 | L11: 46300 | M11: 46331 | N11: 46361 | O11: 46392 | P11: 46423 | Q11: 46451 | R11: 46482 | S11: 46512 | T11: 46543 | U11: 46573 | V11: 46604 | W11: 46635 | X11: 46665 | Y11: 46696 | Z11: 46726 | AA11: 46757 | AB11: 46788
B12: Cese Transfer | C12: 1 | D12: month(s) | E12: 46106 | F12: 46137 | G12: 46167 | H12: 46198 | I12: 46228 | J12: 46259 | K12: 46290 | L12: 46320 | M12: 46351 | N12: 46381 | O12: 46412 | P12: 46443 | Q12: 46471 | R12: 46502 | S12: 46532 | T12: 46563 | U12: 46593 | V12: 46624 | W12: 46655 | X12: 46685 | Y12: 46716 | Z12: 46746 | AA12: 46777 | AB12: 46808
B13: Cese Phone | C13: 1 | D13: month(s) | E13: 46086 | F13: 46117 | G13: 46147 | H13: 46178 | I13: 46208 | J13: 46239 | K13: 46270 | L13: 46300 | M13: 46331 | N13: 46361 | O13: 46392 | P13: 46423 | Q13: 46451 | R13: 46482 | S13: 46512 | T13: 46543 | U13: 46573 | V13: 46604 | W13: 46635 | X13: 46665 | Y13: 46696 | Z13: 46726 | AA13: 46757 | AB13: 46788
B14: Rent | C14: 1 | D14: month(s) | E14: 46082 | F14: 46113 | G14: 46143 | H14: 46174 | I14: 46204 | J14: 46235 | K14: 46266 | L14: 46296 | M14: 46327 | N14: 46357 | O14: 46388 | P14: 46419 | Q14: 46447 | R14: 46478 | S14: 46508 | T14: 46539 | U14: 46569 | V14: 46600 | W14: 46631 | X14: 46661 | Y14: 46692 | Z14: 46722 | AA14: 46753 | AB14: 46784
B15: Groceries | C15: 2 | D15: week(s) | E15: 46081 | F15: 46095 | G15: 46109 | H15: 46123 | I15: 46137 | J15: 46151 | K15: 46165 | L15: 46179 | M15: 46193 | N15: 46207 | O15: 46221 | P15: 46235 | Q15: 46249 | R15: 46263 | S15: 46277 | T15: 46291 | U15: 46305 | V15: 46319 | W15: 46333 | X15: 46347 | Y15: 46361 | Z15: 46375 | AA15: 46389 | AB15: 46403 | AC15: 46417 | AD15: 46431 | AE15: 46445 | AF15: 46459 | AG15: 46473 | AH15: 46487 | AI15: 46501 | AJ15: 46515 | AK15: 46529 | AL15: 46543 | AM15: 46557 | AN15: 46571 | AO15: 46585 | AP15: 46599 | AQ15: 46613 | AR15: 46627 | AS15: 46641 | AT15: 46655 | AU15: 46669 | AV15: 46683 | AW15: 46697 | AX15: 46711 | AY15: 46725 | AZ15: 46739 | BA15: 46753 | BB15: 46767 | BC15: 46781 | BD15: 46795 | BE15: 46809
B16: Food & Drinks | C16: 2 | D16: week(s) | E16: 46081 | F16: 46095 | G16: 46109 | H16: 46123 | I16: 46137 | J16: 46151 | K16: 46165 | L16: 46179 | M16: 46193 | N16: 46207 | O16: 46221 | P16: 46235 | Q16: 46249 | R16: 46263 | S16: 46277 | T16: 46291 | U16: 46305 | V16: 46319 | W16: 46333 | X16: 46347 | Y16: 46361 | Z16: 46375 | AA16: 46389 | AB16: 46403 | AC16: 46417 | AD16: 46431 | AE16: 46445 | AF16: 46459 | AG16: 46473 | AH16: 46487 | AI16: 46501 | AJ16: 46515 | AK16: 46529 | AL16: 46543 | AM16: 46557 | AN16: 46571 | AO16: 46585 | AP16: 46599 | AQ16: 46613 | AR16: 46627 | AS16: 46641 | AT16: 46655 | AU16: 46669 | AV16: 46683 | AW16: 46697 | AX16: 46711 | AY16: 46725 | AZ16: 46739 | BA16: 46753 | BB16: 46767 | BC16: 46781 | BD16: 46795 | BE16: 46809
B17: Renters | C17: 1 | D17: month(s) | E17: 46102 | F17: 46133 | G17: 46163 | H17: 46194 | I17: 46224 | J17: 46255 | K17: 46286 | L17: 46316 | M17: 46347 | N17: 46377 | O17: 46408 | P17: 46439 | Q17: 46467 | R17: 46498 | S17: 46528 | T17: 46559 | U17: 46589 | V17: 46620 | W17: 46651 | X17: 46681 | Y17: 46712 | Z17: 46742 | AA17: 46773 | AB17: 46804
B18: Sony | C18: 1 | D18: month(s) | E18: 46089 | F18: 46120 | G18: 46150 | H18: 46181 | I18: 46211 | J18: 46242 | K18: 46273 | L18: 46303 | M18: 46334 | N18: 46364 | O18: 46395 | P18: 46426 | Q18: 46454 | R18: 46485 | S18: 46515 | T18: 46546 | U18: 46576 | V18: 46607 | W18: 46638 | X18: 46668 | Y18: 46699 | Z18: 46729 | AA18: 46760 | AB18: 46791
B19: Phone | C19: 1 | D19: month(s) | E19: 46086 | F19: 46117 | G19: 46147 | H19: 46178 | I19: 46208 | J19: 46239 | K19: 46270 | L19: 46300 | M19: 46331 | N19: 46361 | O19: 46392 | P19: 46423 | Q19: 46451 | R19: 46482 | S19: 46512 | T19: 46543 | U19: 46573 | V19: 46604 | W19: 46635 | X19: 46665 | Y19: 46696 | Z19: 46726 | AA19: 46757 | AB19: 46788
B20: Amazon | C20: 1 | D20: month(s) | E20: 46090 | F20: 46121 | G20: 46151 | H20: 46182 | I20: 46212 | J20: 46243 | K20: 46274 | L20: 46304 | M20: 46335 | N20: 46365 | O20: 46396 | P20: 46427 | Q20: 46455 | R20: 46486 | S20: 46516 | T20: 46547 | U20: 46577 | V20: 46608 | W20: 46639 | X20: 46669 | Y20: 46700 | Z20: 46730 | AA20: 46761 | AB20: 46792
B21: Motorcycle | C21: 1 | D21: month(s) | E21: 46097 | F21: 46128 | G21: 46158 | H21: 46189 | I21: 46219 | J21: 46250 | K21: 46281 | L21: 46311 | M21: 46342 | N21: 46372 | O21: 46403 | P21: 46434 | Q21: 46462 | R21: 46493 | S21: 46523 | T21: 46554 | U21: 46584 | V21: 46615 | W21: 46646 | X21: 46676 | Y21: 46707 | Z21: 46737 | AA21: 46768 | AB21: 46799
B22: Bike Insurance | C22: 1 | D22: year(s) | E22: 46334 | F22: 46699
B23: SDGE | C23: 1 | D23: month(s) | E23: 46081 | F23: 46109 | G23: 46140 | H23: 46170 | I23: 46201 | J23: 46231 | K23: 46262 | L23: 46293 | M23: 46323 | N23: 46354 | O23: 46384 | P23: 46415 | Q23: 46446 | R23: 46474 | S23: 46505 | T23: 46535 | U23: 46566 | V23: 46596 | W23: 46627 | X23: 46658 | Y23: 46688 | Z23: 46719 | AA23: 46749 | AB23: 46780
B24: Internet | C24: 1 | D24: month(s) | E24: 46107 | F24: 46138 | G24: 46168 | H24: 46199 | I24: 46229 | J24: 46260 | K24: 46291 | L24: 46321 | M24: 46352 | N24: 46382 | O24: 46413 | P24: 46444 | Q24: 46472 | R24: 46503 | S24: 46533 | T24: 46564 | U24: 46594 | V24: 46625 | W24: 46656 | X24: 46686 | Y24: 46717 | Z24: 46747 | AA24: 46778 | AB24: 46809
B25: Netflix | C25: 1 | D25: month(s) | E25: 46101 | F25: 46132 | G25: 46162 | H25: 46193 | I25: 46223 | J25: 46254 | K25: 46285 | L25: 46315 | M25: 46346 | N25: 46376 | O25: 46407 | P25: 46438 | Q25: 46466 | R25: 46497 | S25: 46527 | T25: 46558 | U25: 46588 | V25: 46619 | W25: 46650 | X25: 46680 | Y25: 46711 | Z25: 46741 | AA25: 46772 | AB25: 46803
B26: Prime Ad-Free | C26: 1 | D26: month(s) | E26: 46081 | F26: 46109 | G26: 46140 | H26: 46170 | I26: 46201 | J26: 46231 | K26: 46262 | L26: 46293 | M26: 46323 | N26: 46354 | O26: 46384 | P26: 46415 | Q26: 46446 | R26: 46474 | S26: 46505 | T26: 46535 | U26: 46566 | V26: 46596 | W26: 46627 | X26: 46658 | Y26: 46688 | Z26: 46719 | AA26: 46749 | AB26: 46780
B27: Down Dog | C27: 1 | D27: year(s) | E27: 46420 | F27: 46785
B28: Google+ | C28: 1 | D28: year(s) | E28: 46445 | F28: 46810
B29: Phone Insurance | C29: 1 | D29: month(s) | E29: 46089 | F29: 46120 | G29: 46150 | H29: 46181 | I29: 46211 | J29: 46242 | K29: 46273 | L29: 46303 | M29: 46334 | N29: 46364 | O29: 46395 | P29: 46426 | Q29: 46454 | R29: 46485 | S29: 46515 | T29: 46546 | U29: 46576 | V29: 46607 | W29: 46638 | X29: 46668 | Y29: 46699 | Z29: 46729 | AA29: 46760 | AB29: 46791
B30: Sniffies | C30: 6 | D30: month(s) | E30: 46194 | F30: 46377 | G30: 46559 | H30: 46742
B31: Tidal | C31: 1 | D31: month(s) | E31: 46108 | F31: 46139 | G31: 46169 | H31: 46200 | I31: 46230 | J31: 46261 | K31: 46292 | L31: 46322 | M31: 46353 | N31: 46383 | O31: 46414 | P31: 46445 | Q31: 46473 | R31: 46504 | S31: 46534 | T31: 46565 | U31: 46595 | V31: 46626 | W31: 46657 | X31: 46687 | Y31: 46718 | Z31: 46748 | AA31: 46779 | AB31: 46810
B32: Windsurf | C32: 1 | D32: month(s) | E32: 46107 | F32: 46138 | G32: 46168 | H32: 46199 | I32: 46229 | J32: 46260 | K32: 46291 | L32: 46321 | M32: 46352 | N32: 46382 | O32: 46413 | P32: 46444 | Q32: 46472 | R32: 46503 | S32: 46533 | T32: 46564 | U32: 46594 | V32: 46625 | W32: 46656 | X32: 46686 | Y32: 46717 | Z32: 46747 | AA32: 46778 | AB32: 46809

Sheet Helper - Start date
A1: First Date | B1: Transactions | C1: Freq | D1: Unit | E1: Start Date | F1: Entry Date | G1: Dates
A2: =Forecast!$D$7 -> 46081 | B2: {=_xlfn._xlws.FILTER(OFFSET('Monthly budget'!$E$11,0,0,ROW('Monthly budget'!TotalRow)-ROW('Monthly budget'!IncomeRow)-4,1),OFFSET('Monthly budget'!$E$11,0,0,ROW('Monthly budget'!TotalRow)-ROW('Monthly budget'!IncomeRow)-4,1)<>"")} -> Paycheck | C2: {=_xlfn.XLOOKUP(_xlfn.ANCHORARRAY($B$2),'Monthly budget'!$E$8:$E$89,'Monthly budget'!$B$8:$B$89,"",0)} -> 2 | D2: {=_xlfn.XLOOKUP(_xlfn.ANCHORARRAY($B$2),'Monthly budget'!$E$8:$E$89,'Monthly budget'!$C$8:$C$89,"",0)} -> week(s) | E2: {=_xlfn.XLOOKUP($A$2,_xlfn.CHOOSEROWS(_xlfn.HSTACK(_xlfn.ANCHORARRAY($F$2),_xlfn.ANCHORARRAY($G$2)),ROW()-1),_xlfn.CHOOSEROWS(_xlfn.HSTACK(_xlfn.ANCHORARRAY($F$2),_xlfn.ANCHORARRAY($G$2)),ROW()-1),"",1)} -> 46094 | F2: {=IF(B2="","",_xlfn.XLOOKUP(_xlfn.ANCHORARRAY(B2),'Monthly budget'!$E$8:$E$86,'Monthly budget'!$D$8:$D$86,"",0))} -> 45702 | G2: {=_xlfn.LET(_xlpm.strFreq,INDEX(_xlfn.ANCHORARRAY(C2),_xlfn.SEQUENCE(ROWS(_xlfn.ANCHORARRAY(C2)),1,1,1)), _xlfn.IFS(_xlfn.ANCHORARRAY(D2)="year(s)", _xlfn.LET(_xlpm.yrTest,EDATE(INDEX(_xlfn.ANCHORARRAY(F2),ROW(_xlfn.ANCHORARRAY(F2))-1),_xlfn.SEQUENCE(1,100,1,1)*12*_xlpm.strFreq), IF(_xlpm.yrTest<EDATE(A2,24), _xlpm.yrTest, "" ) ),_xlfn.ANCHORARRAY( D2)="month(s)", _xlfn.LET(_xlpm.mnthTest,EDATE(INDEX(_xlfn.ANCHORARRAY(F2),ROW(_xlfn.ANCHORARRAY(F2))-1),_xlfn.SEQUENCE(1,100,1,1)*_xlpm.strFreq), IF(_xlpm.mnthTest<EDATE(A2,24), _xlpm.mnthTest, "" ) ),_xlfn.ANCHORARRAY( D2)="week(s)", _xlfn.LET(_xlpm.wkTest,INDEX(_xlfn.ANCHORARRAY(F2),ROW(_xlfn.ANCHORARRAY(F2))-1)+_xlfn.SEQUENCE(1,100,7,7)*_xlpm.strFreq, IF(_xlpm.wkTest<EDATE(A2,24), _xlpm.wkTest, "" ) ),_xlfn.ANCHORARRAY( D2)="day(s)", _xlfn.LET(_xlpm.dyTest,INDEX(_xlfn.ANCHORARRAY(F2),ROW(_xlfn.ANCHORARRAY(F2))-1)+_xlfn.SEQUENCE(1,100,1,1)*_xlpm.strFreq, IF(_xlpm.dyTest<EDATE(A2,24), _xlpm.dyTest, "" ) ), TRUE, "" ) )} -> 45716 | H2: 45730 | I2: 45744 | J2: 45758 | K2: 45772 | L2: 45786 | M2: 45800 | N2: 45814 | O2: 45828 | P2: 45842 | Q2: 45856 | R2: 45870 | S2: 45884 | T2: 45898 | U2: 45912 | V2: 45926 | W2: 45940 | X2: 45954 | Y2: 45968 | Z2: 45982 | AA2: 45996 | AB2: 46010 | AC2: 46024 | AD2: 46038 | AE2: 46052 | AF2: 46066 | AG2: 46080 | AH2: 46094 | AI2: 46108 | AJ2: 46122 | AK2: 46136 | AL2: 46150 | AM2: 46164 | AN2: 46178 | AO2: 46192 | AP2: 46206 | AQ2: 46220 | AR2: 46234 | AS2: 46248 | AT2: 46262 | AU2: 46276 | AV2: 46290 | AW2: 46304 | AX2: 46318 | AY2: 46332 | AZ2: 46346 | BA2: 46360 | BB2: 46374 | BC2: 46388 | BD2: 46402 | BE2: 46416 | BF2: 46430 | BG2: 46444 | BH2: 46458 | BI2: 46472 | BJ2: 46486 | BK2: 46500 | BL2: 46514 | BM2: 46528 | BN2: 46542 | BO2: 46556 | BP2: 46570 | BQ2: 46584 | BR2: 46598 | BS2: 46612 | BT2: 46626 | BU2: 46640 | BV2: 46654 | BW2: 46668 | BX2: 46682 | BY2: 46696 | BZ2: 46710 | CA2: 46724 | CB2: 46738 | CC2: 46752 | CD2: 46766 | CE2: 46780 | CF2: 46794 | CG2: 46808
B3: Disability | C3: 1 | D3: month(s) | E3: {=_xlfn.XLOOKUP($A$2,_xlfn.CHOOSEROWS(_xlfn.HSTACK(_xlfn.ANCHORARRAY($F$2),_xlfn.ANCHORARRAY($G$2)),ROW()-1),_xlfn.CHOOSEROWS(_xlfn.HSTACK(_xlfn.ANCHORARRAY($F$2),_xlfn.ANCHORARRAY($G$2)),ROW()-1),"",1)} -> 46082 | F3: 45627 | G3: 45658 | H3: 45689 | I3: 45717 | J3: 45748 | K3: 45778 | L3: 45809 | M3: 45839 | N3: 45870 | O3: 45901 | P3: 45931 | Q3: 45962 | R3: 45992 | S3: 46023 | T3: 46054 | U3: 46082 | V3: 46113 | W3: 46143 | X3: 46174 | Y3: 46204 | Z3: 46235 | AA3: 46266 | AB3: 46296 | AC3: 46327 | AD3: 46357 | AE3: 46388 | AF3: 46419 | AG3: 46447 | AH3: 46478 | AI3: 46508 | AJ3: 46539 | AK3: 46569 | AL3: 46600 | AM3: 46631 | AN3: 46661 | AO3: 46692 | AP3: 46722 | AQ3: 46753 | AR3: 46784
B4: Ameritas | C4: 2 | D4: week(s) | E4: {=_xlfn.XLOOKUP($A$2,_xlfn.CHOOSEROWS(_xlfn.HSTACK(_xlfn.ANCHORARRAY($F$2),_xlfn.ANCHORARRAY($G$2)),ROW()-1),_xlfn.CHOOSEROWS(_xlfn.HSTACK(_xlfn.ANCHORARRAY($F$2),_xlfn.ANCHORARRAY($G$2)),ROW()-1),"",1)} -> 46094 | F4: 45702 | G4: 45716 | H4: 45730 | I4: 45744 | J4: 45758 | K4: 45772 | L4: 45786 | M4: 45800 | N4: 45814 | O4: 45828 | P4: 45842 | Q4: 45856 | R4: 45870 | S4: 45884 | T4: 45898 | U4: 45912 | V4: 45926 | W4: 45940 | X4: 45954 | Y4: 45968 | Z4: 45982 | AA4: 45996 | AB4: 46010 | AC4: 46024 | AD4: 46038 | AE4: 46052 | AF4: 46066 | AG4: 46080 | AH4: 46094 | AI4: 46108 | AJ4: 46122 | AK4: 46136 | AL4: 46150 | AM4: 46164 | AN4: 46178 | AO4: 46192 | AP4: 46206 | AQ4: 46220 | AR4: 46234 | AS4: 46248 | AT4: 46262 | AU4: 46276 | AV4: 46290 | AW4: 46304 | AX4: 46318 | AY4: 46332 | AZ4: 46346 | BA4: 46360 | BB4: 46374 | BC4: 46388 | BD4: 46402 | BE4: 46416 | BF4: 46430 | BG4: 46444 | BH4: 46458 | BI4: 46472 | BJ4: 46486 | BK4: 46500 | BL4: 46514 | BM4: 46528 | BN4: 46542 | BO4: 46556 | BP4: 46570 | BQ4: 46584 | BR4: 46598 | BS4: 46612 | BT4: 46626 | BU4: 46640 | BV4: 46654 | BW4: 46668 | BX4: 46682 | BY4: 46696 | BZ4: 46710 | CA4: 46724 | CB4: 46738 | CC4: 46752 | CD4: 46766 | CE4: 46780 | CF4: 46794 | CG4: 46808
B5: Visa Platinum | C5: 1 | D5: month(s) | E5: {=_xlfn.XLOOKUP($A$2,_xlfn.CHOOSEROWS(_xlfn.HSTACK(_xlfn.ANCHORARRAY($F$2),_xlfn.ANCHORARRAY($G$2)),ROW()-1),_xlfn.CHOOSEROWS(_xlfn.HSTACK(_xlfn.ANCHORARRAY($F$2),_xlfn.ANCHORARRAY($G$2)),ROW()-1),"",1)} -> 46084 | F5: 45629 | G5: 45660 | H5: 45691 | I5: 45719 | J5: 45750 | K5: 45780 | L5: 45811 | M5: 45841 | N5: 45872 | O5: 45903 | P5: 45933 | Q5: 45964 | R5: 45994 | S5: 46025 | T5: 46056 | U5: 46084 | V5: 46115 | W5: 46145 | X5: 46176 | Y5: 46206 | Z5: 46237 | AA5: 46268 | AB5: 46298 | AC5: 46329 | AD5: 46359 | AE5: 46390 | AF5: 46421 | AG5: 46449 | AH5: 46480 | AI5: 46510 | AJ5: 46541 | AK5: 46571 | AL5: 46602 | AM5: 46633 | AN5: 46663 | AO5: 46694 | AP5: 46724 | AQ5: 46755 | AR5: 46786
B6: Viso Go | C6: 1 | D6: month(s) | E6: {=_xlfn.XLOOKUP($A$2,_xlfn.CHOOSEROWS(_xlfn.HSTACK(_xlfn.ANCHORARRAY($F$2),_xlfn.ANCHORARRAY($G$2)),ROW()-1),_xlfn.CHOOSEROWS(_xlfn.HSTACK(_xlfn.ANCHORARRAY($F$2),_xlfn.ANCHORARRAY($G$2)),ROW()-1),"",1)} -> 46092 | F6: 45637 | G6: 45668 | H6: 45699 | I6: 45727 | J6: 45758 | K6: 45788 | L6: 45819 | M6: 45849 | N6: 45880 | O6: 45911 | P6: 45941 | Q6: 45972 | R6: 46002 | S6: 46033 | T6: 46064 | U6: 46092 | V6: 46123 | W6: 46153 | X6: 46184 | Y6: 46214 | Z6: 46245 | AA6: 46276 | AB6: 46306 | AC6: 46337 | AD6: 46367 | AE6: 46398 | AF6: 46429 | AG6: 46457 | AH6: 46488 | AI6: 46518 | AJ6: 46549 | AK6: 46579 | AL6: 46610 | AM6: 46641 | AN6: 46671 | AO6: 46702 | AP6: 46732 | AQ6: 46763 | AR6: 46794
B7: Costco Citi | C7: 1 | D7: month(s) | E7: {=_xlfn.XLOOKUP($A$2,_xlfn.CHOOSEROWS(_xlfn.HSTACK(_xlfn.ANCHORARRAY($F$2),_xlfn.ANCHORARRAY($G$2)),ROW()-1),_xlfn.CHOOSEROWS(_xlfn.HSTACK(_xlfn.ANCHORARRAY($F$2),_xlfn.ANCHORARRAY($G$2)),ROW()-1),"",1)} -> 46081 | F7: 46050 | G7: 46081 | H7: 46109 | I7: 46140 | J7: 46170 | K7: 46201 | L7: 46231 | M7: 46262 | N7: 46293 | O7: 46323 | P7: 46354 | Q7: 46384 | R7: 46415 | S7: 46446 | T7: 46474 | U7: 46505 | V7: 46535 | W7: 46566 | X7: 46596 | Y7: 46627 | Z7: 46658 | AA7: 46688 | AB7: 46719 | AC7: 46749 | AD7: 46780
B8: Kulo Transfer | C8: 1 | D8: month(s) | E8: {=_xlfn.XLOOKUP($A$2,_xlfn.CHOOSEROWS(_xlfn.HSTACK(_xlfn.ANCHORARRAY($F$2),_xlfn.ANCHORARRAY($G$2)),ROW()-1),_xlfn.CHOOSEROWS(_xlfn.HSTACK(_xlfn.ANCHORARRAY($F$2),_xlfn.ANCHORARRAY($G$2)),ROW()-1),"",1)} -> 46081 | F8: 45654 | G8: 45685 | H8: 45716 | I8: 45744 | J8: 45775 | K8: 45805 | L8: 45836 | M8: 45866 | N8: 45897 | O8: 45928 | P8: 45958 | Q8: 45989 | R8: 46019 | S8: 46050 | T8: 46081 | U8: 46109 | V8: 46140 | W8: 46170 | X8: 46201 | Y8: 46231 | Z8: 46262 | AA8: 46293 | AB8: 46323 | AC8: 46354 | AD8: 46384 | AE8: 46415 | AF8: 46446 | AG8: 46474 | AH8: 46505 | AI8: 46535 | AJ8: 46566 | AK8: 46596 | AL8: 46627 | AM8: 46658 | AN8: 46688 | AO8: 46719 | AP8: 46749 | AQ8: 46780
B9: Kulo Rent | C9: 1 | D9: month(s) | E9: {=_xlfn.XLOOKUP($A$2,_xlfn.CHOOSEROWS(_xlfn.HSTACK(_xlfn.ANCHORARRAY($F$2),_xlfn.ANCHORARRAY($G$2)),ROW()-1),_xlfn.CHOOSEROWS(_xlfn.HSTACK(_xlfn.ANCHORARRAY($F$2),_xlfn.ANCHORARRAY($G$2)),ROW()-1),"",1)} -> 46082 | F9: 45627 | G9: 45658 | H9: 45689 | I9: 45717 | J9: 45748 | K9: 45778 | L9: 45809 | M9: 45839 | N9: 45870 | O9: 45901 | P9: 45931 | Q9: 45962 | R9: 45992 | S9: 46023 | T9: 46054 | U9: 46082 | V9: 46113 | W9: 46143 | X9: 46174 | Y9: 46204 | Z9: 46235 | AA9: 46266 | AB9: 46296 | AC9: 46327 | AD9: 46357 | AE9: 46388 | AF9: 46419 | AG9: 46447 | AH9: 46478 | AI9: 46508 | AJ9: 46539 | AK9: 46569 | AL9: 46600 | AM9: 46631 | AN9: 46661 | AO9: 46692 | AP9: 46722 | AQ9: 46753 | AR9: 46784
B10: Kulo SDGE | C10: 1 | D10: month(s) | E10: {=_xlfn.XLOOKUP($A$2,_xlfn.CHOOSEROWS(_xlfn.HSTACK(_xlfn.ANCHORARRAY($F$2),_xlfn.ANCHORARRAY($G$2)),ROW()-1),_xlfn.CHOOSEROWS(_xlfn.HSTACK(_xlfn.ANCHORARRAY($F$2),_xlfn.ANCHORARRAY($G$2)),ROW()-1),"",1)} -> 46081 | F10: 45928 | G10: 45958 | H10: 45989 | I10: 46019 | J10: 46050 | K10: 46081 | L10: 46109 | M10: 46140 | N10: 46170 | O10: 46201 | P10: 46231 | Q10: 46262 | R10: 46293 | S10: 46323 | T10: 46354 | U10: 46384 | V10: 46415 | W10: 46446 | X10: 46474 | Y10: 46505 | Z10: 46535 | AA10: 46566 | AB10: 46596 | AC10: 46627 | AD10: 46658 | AE10: 46688 | AF10: 46719 | AG10: 46749 | AH10: 46780
B11: Kulo Internet | C11: 1 | D11: month(s) | E11: {=_xlfn.XLOOKUP($A$2,_xlfn.CHOOSEROWS(_xlfn.HSTACK(_xlfn.ANCHORARRAY($F$2),_xlfn.ANCHORARRAY($G$2)),ROW()-1),_xlfn.CHOOSEROWS(_xlfn.HSTACK(_xlfn.ANCHORARRAY($F$2),_xlfn.ANCHORARRAY($G$2)),ROW()-1),"",1)} -> 46086 | F11: 45935 | G11: 45966 | H11: 45996 | I11: 46027 | J11: 46058 | K11: 46086 | L11: 46117 | M11: 46147 | N11: 46178 | O11: 46208 | P11: 46239 | Q11: 46270 | R11: 46300 | S11: 46331 | T11: 46361 | U11: 46392 | V11: 46423 | W11: 46451 | X11: 46482 | Y11: 46512 | Z11: 46543 | AA11: 46573 | AB11: 46604 | AC11: 46635 | AD11: 46665 | AE11: 46696 | AF11: 46726 | AG11: 46757 | AH11: 46788
B12: Cese Transfer | C12: 1 | D12: month(s) | E12: {=_xlfn.XLOOKUP($A$2,_xlfn.CHOOSEROWS(_xlfn.HSTACK(_xlfn.ANCHORARRAY($F$2),_xlfn.ANCHORARRAY($G$2)),ROW()-1),_xlfn.CHOOSEROWS(_xlfn.HSTACK(_xlfn.ANCHORARRAY($F$2),_xlfn.ANCHORARRAY($G$2)),ROW()-1),"",1)} -> 46106 | F12: 45651 | G12: 45682 | H12: 45713 | I12: 45741 | J12: 45772 | K12: 45802 | L12: 45833 | M12: 45863 | N12: 45894 | O12: 45925 | P12: 45955 | Q12: 45986 | R12: 46016 | S12: 46047 | T12: 46078 | U12: 46106 | V12: 46137 | W12: 46167 | X12: 46198 | Y12: 46228 | Z12: 46259 | AA12: 46290 | AB12: 46320 | AC12: 46351 | AD12: 46381 | AE12: 46412 | AF12: 46443 | AG12: 46471 | AH12: 46502 | AI12: 46532 | AJ12: 46563 | AK12: 46593 | AL12: 46624 | AM12: 46655 | AN12: 46685 | AO12: 46716 | AP12: 46746 | AQ12: 46777 | AR12: 46808
B13: Cese Phone | C13: 1 | D13: month(s) | E13: {=_xlfn.XLOOKUP($A$2,_xlfn.CHOOSEROWS(_xlfn.HSTACK(_xlfn.ANCHORARRAY($F$2),_xlfn.ANCHORARRAY($G$2)),ROW()-1),_xlfn.CHOOSEROWS(_xlfn.HSTACK(_xlfn.ANCHORARRAY($F$2),_xlfn.ANCHORARRAY($G$2)),ROW()-1),"",1)} -> 46086 | F13: 45631 | G13: 45662 | H13: 45693 | I13: 45721 | J13: 45752 | K13: 45782 | L13: 45813 | M13: 45843 | N13: 45874 | O13: 45905 | P13: 45935 | Q13: 45966 | R13: 45996 | S13: 46027 | T13: 46058 | U13: 46086 | V13: 46117 | W13: 46147 | X13: 46178 | Y13: 46208 | Z13: 46239 | AA13: 46270 | AB13: 46300 | AC13: 46331 | AD13: 46361 | AE13: 46392 | AF13: 46423 | AG13: 46451 | AH13: 46482 | AI13: 46512 | AJ13: 46543 | AK13: 46573 | AL13: 46604 | AM13: 46635 | AN13: 46665 | AO13: 46696 | AP13: 46726 | AQ13: 46757 | AR13: 46788
B14: Rent | C14: 1 | D14: month(s) | E14: {=_xlfn.XLOOKUP($A$2,_xlfn.CHOOSEROWS(_xlfn.HSTACK(_xlfn.ANCHORARRAY($F$2),_xlfn.ANCHORARRAY($G$2)),ROW()-1),_xlfn.CHOOSEROWS(_xlfn.HSTACK(_xlfn.ANCHORARRAY($F$2),_xlfn.ANCHORARRAY($G$2)),ROW()-1),"",1)} -> 46082 | F14: 45809 | G14: 45839 | H14: 45870 | I14: 45901 | J14: 45931 | K14: 45962 | L14: 45992 | M14: 46023 | N14: 46054 | O14: 46082 | P14: 46113 | Q14: 46143 | R14: 46174 | S14: 46204 | T14: 46235 | U14: 46266 | V14: 46296 | W14: 46327 | X14: 46357 | Y14: 46388 | Z14: 46419 | AA14: 46447 | AB14: 46478 | AC14: 46508 | AD14: 46539 | AE14: 46569 | AF14: 46600 | AG14: 46631 | AH14: 46661 | AI14: 46692 | AJ14: 46722 | AK14: 46753 | AL14: 46784
B15: Groceries | C15: 2 | D15: week(s) | E15: {=_xlfn.XLOOKUP($A$2,_xlfn.CHOOSEROWS(_xlfn.HSTACK(_xlfn.ANCHORARRAY($F$2),_xlfn.ANCHORARRAY($G$2)),ROW()-1),_xlfn.CHOOSEROWS(_xlfn.HSTACK(_xlfn.ANCHORARRAY($F$2),_xlfn.ANCHORARRAY($G$2)),ROW()-1),"",1)} -> 46081 | F15: 45703 | G15: 45717 | H15: 45731 | I15: 45745 | J15: 45759 | K15: 45773 | L15: 45787 | M15: 45801 | N15: 45815 | O15: 45829 | P15: 45843 | Q15: 45857 | R15: 45871 | S15: 45885 | T15: 45899 | U15: 45913 | V15: 45927 | W15: 45941 | X15: 45955 | Y15: 45969 | Z15: 45983 | AA15: 45997 | AB15: 46011 | AC15: 46025 | AD15: 46039 | AE15: 46053 | AF15: 46067 | AG15: 46081 | AH15: 46095 | AI15: 46109 | AJ15: 46123 | AK15: 46137 | AL15: 46151 | AM15: 46165 | AN15: 46179 | AO15: 46193 | AP15: 46207 | AQ15: 46221 | AR15: 46235 | AS15: 46249 | AT15: 46263 | AU15: 46277 | AV15: 46291 | AW15: 46305 | AX15: 46319 | AY15: 46333 | AZ15: 46347 | BA15: 46361 | BB15: 46375 | BC15: 46389 | BD15: 46403 | BE15: 46417 | BF15: 46431 | BG15: 46445 | BH15: 46459 | BI15: 46473 | BJ15: 46487 | BK15: 46501 | BL15: 46515 | BM15: 46529 | BN15: 46543 | BO15: 46557 | BP15: 46571 | BQ15: 46585 | BR15: 46599 | BS15: 46613 | BT15: 46627 | BU15: 46641 | BV15: 46655 | BW15: 46669 | BX15: 46683 | BY15: 46697 | BZ15: 46711 | CA15: 46725 | CB15: 46739 | CC15: 46753 | CD15: 46767 | CE15: 46781 | CF15: 46795 | CG15: 46809
B16: Food & Drinks | C16: 2 | D16: week(s) | E16: {=_xlfn.XLOOKUP($A$2,_xlfn.CHOOSEROWS(_xlfn.HSTACK(_xlfn.ANCHORARRAY($F$2),_xlfn.ANCHORARRAY($G$2)),ROW()-1),_xlfn.CHOOSEROWS(_xlfn.HSTACK(_xlfn.ANCHORARRAY($F$2),_xlfn.ANCHORARRAY($G$2)),ROW()-1),"",1)} -> 46081 | F16: 45703 | G16: 45717 | H16: 45731 | I16: 45745 | J16: 45759 | K16: 45773 | L16: 45787 | M16: 45801 | N16: 45815 | O16: 45829 | P16: 45843 | Q16: 45857 | R16: 45871 | S16: 45885 | T16: 45899 | U16: 45913 | V16: 45927 | W16: 45941 | X16: 45955 | Y16: 45969 | Z16: 45983 | AA16: 45997 | AB16: 46011 | AC16: 46025 | AD16: 46039 | AE16: 46053 | AF16: 46067 | AG16: 46081 | AH16: 46095 | AI16: 46109 | AJ16: 46123 | AK16: 46137 | AL16: 46151 | AM16: 46165 | AN16: 46179 | AO16: 46193 | AP16: 46207 | AQ16: 46221 | AR16: 46235 | AS16: 46249 | AT16: 46263 | AU16: 46277 | AV16: 46291 | AW16: 46305 | AX16: 46319 | AY16: 46333 | AZ16: 46347 | BA16: 46361 | BB16: 46375 | BC16: 46389 | BD16: 46403 | BE16: 46417 | BF16: 46431 | BG16: 46445 | BH16: 46459 | BI16: 46473 | BJ16: 46487 | BK16: 46501 | BL16: 46515 | BM16: 46529 | BN16: 46543 | BO16: 46557 | BP16: 46571 | BQ16: 46585 | BR16: 46599 | BS16: 46613 | BT16: 46627 | BU16: 46641 | BV16: 46655 | BW16: 46669 | BX16: 46683 | BY16: 46697 | BZ16: 46711 | CA16: 46725 | CB16: 46739 | CC16: 46753 | CD16: 46767 | CE16: 46781 | CF16: 46795 | CG16: 46809
B17: Renters | C17: 1 | D17: month(s) | E17: {=_xlfn.XLOOKUP($A$2,_xlfn.CHOOSEROWS(_xlfn.HSTACK(_xlfn.ANCHORARRAY($F$2),_xlfn.ANCHORARRAY($G$2)),ROW()-1),_xlfn.CHOOSEROWS(_xlfn.HSTACK(_xlfn.ANCHORARRAY($F$2),_xlfn.ANCHORARRAY($G$2)),ROW()-1),"",1)} -> 46102 | F17: 45798 | G17: 45829 | H17: 45859 | I17: 45890 | J17: 45921 | K17: 45951 | L17: 45982 | M17: 46012 | N17: 46043 | O17: 46074 | P17: 46102 | Q17: 46133 | R17: 46163 | S17: 46194 | T17: 46224 | U17: 46255 | V17: 46286 | W17: 46316 | X17: 46347 | Y17: 46377 | Z17: 46408 | AA17: 46439 | AB17: 46467 | AC17: 46498 | AD17: 46528 | AE17: 46559 | AF17: 46589 | AG17: 46620 | AH17: 46651 | AI17: 46681 | AJ17: 46712 | AK17: 46742 | AL17: 46773 | AM17: 46804
B18: Sony | C18: 1 | D18: month(s) | E18: {=_xlfn.XLOOKUP($A$2,_xlfn.CHOOSEROWS(_xlfn.HSTACK(_xlfn.ANCHORARRAY($F$2),_xlfn.ANCHORARRAY($G$2)),ROW()-1),_xlfn.CHOOSEROWS(_xlfn.HSTACK(_xlfn.ANCHORARRAY($F$2),_xlfn.ANCHORARRAY($G$2)),ROW()-1),"",1)} -> 46089 | F18: 45724 | G18: 45755 | H18: 45785 | I18: 45816 | J18: 45846 | K18: 45877 | L18: 45908 | M18: 45938 | N18: 45969 | O18: 45999 | P18: 46030 | Q18: 46061 | R18: 46089 | S18: 46120 | T18: 46150 | U18: 46181 | V18: 46211 | W18: 46242 | X18: 46273 | Y18: 46303 | Z18: 46334 | AA18: 46364 | AB18: 46395 | AC18: 46426 | AD18: 46454 | AE18: 46485 | AF18: 46515 | AG18: 46546 | AH18: 46576 | AI18: 46607 | AJ18: 46638 | AK18: 46668 | AL18: 46699 | AM18: 46729 | AN18: 46760 | AO18: 46791
B19: Phone | C19: 1 | D19: month(s) | E19: {=_xlfn.XLOOKUP($A$2,_xlfn.CHOOSEROWS(_xlfn.HSTACK(_xlfn.ANCHORARRAY($F$2),_xlfn.ANCHORARRAY($G$2)),ROW()-1),_xlfn.CHOOSEROWS(_xlfn.HSTACK(_xlfn.ANCHORARRAY($F$2),_xlfn.ANCHORARRAY($G$2)),ROW()-1),"",1)} -> 46086 | F19: 45631 | G19: 45662 | H19: 45693 | I19: 45721 | J19: 45752 | K19: 45782 | L19: 45813 | M19: 45843 | N19: 45874 | O19: 45905 | P19: 45935 | Q19: 45966 | R19: 45996 | S19: 46027 | T19: 46058 | U19: 46086 | V19: 46117 | W19: 46147 | X19: 46178 | Y19: 46208 | Z19: 46239 | AA19: 46270 | AB19: 46300 | AC19: 46331 | AD19: 46361 | AE19: 46392 | AF19: 46423 | AG19: 46451 | AH19: 46482 | AI19: 46512 | AJ19: 46543 | AK19: 46573 | AL19: 46604 | AM19: 46635 | AN19: 46665 | AO19: 46696 | AP19: 46726 | AQ19: 46757 | AR19: 46788
B20: Amazon | C20: 1 | D20: month(s) | E20: {=_xlfn.XLOOKUP($A$2,_xlfn.CHOOSEROWS(_xlfn.HSTACK(_xlfn.ANCHORARRAY($F$2),_xlfn.ANCHORARRAY($G$2)),ROW()-1),_xlfn.CHOOSEROWS(_xlfn.HSTACK(_xlfn.ANCHORARRAY($F$2),_xlfn.ANCHORARRAY($G$2)),ROW()-1),"",1)} -> 46090 | F20: 45635 | G20: 45666 | H20: 45697 | I20: 45725 | J20: 45756 | K20: 45786 | L20: 45817 | M20: 45847 | N20: 45878 | O20: 45909 | P20: 45939 | Q20: 45970 | R20: 46000 | S20: 46031 | T20: 46062 | U20: 46090 | V20: 46121 | W20: 46151 | X20: 46182 | Y20: 46212 | Z20: 46243 | AA20: 46274 | AB20: 46304 | AC20: 46335 | AD20: 46365 | AE20: 46396 | AF20: 46427 | AG20: 46455 | AH20: 46486 | AI20: 46516 | AJ20: 46547 | AK20: 46577 | AL20: 46608 | AM20: 46639 | AN20: 46669 | AO20: 46700 | AP20: 46730 | AQ20: 46761 | AR20: 46792
B21: Motorcycle | C21: 1 | D21: month(s) | E21: {=_xlfn.XLOOKUP($A$2,_xlfn.CHOOSEROWS(_xlfn.HSTACK(_xlfn.ANCHORARRAY($F$2),_xlfn.ANCHORARRAY($G$2)),ROW()-1),_xlfn.CHOOSEROWS(_xlfn.HSTACK(_xlfn.ANCHORARRAY($F$2),_xlfn.ANCHORARRAY($G$2)),ROW()-1),"",1)} -> 46097 | F21: 45642 | G21: 45673 | H21: 45704 | I21: 45732 | J21: 45763 | K21: 45793 | L21: 45824 | M21: 45854 | N21: 45885 | O21: 45916 | P21: 45946 | Q21: 45977 | R21: 46007 | S21: 46038 | T21: 46069 | U21: 46097 | V21: 46128 | W21: 46158 | X21: 46189 | Y21: 46219 | Z21: 46250 | AA21: 46281 | AB21: 46311 | AC21: 46342 | AD21: 46372 | AE21: 46403 | AF21: 46434 | AG21: 46462 | AH21: 46493 | AI21: 46523 | AJ21: 46554 | AK21: 46584 | AL21: 46615 | AM21: 46646 | AN21: 46676 | AO21: 46707 | AP21: 46737 | AQ21: 46768 | AR21: 46799
B22: Bike Insurance | C22: 1 | D22: year(s) | E22: {=_xlfn.XLOOKUP($A$2,_xlfn.CHOOSEROWS(_xlfn.HSTACK(_xlfn.ANCHORARRAY($F$2),_xlfn.ANCHORARRAY($G$2)),ROW()-1),_xlfn.CHOOSEROWS(_xlfn.HSTACK(_xlfn.ANCHORARRAY($F$2),_xlfn.ANCHORARRAY($G$2)),ROW()-1),"",1)} -> 46334 | F22: 45604 | G22: 45969 | H22: 46334 | I22: 46699
B23: SDGE | C23: 1 | D23: month(s) | E23: {=_xlfn.XLOOKUP($A$2,_xlfn.CHOOSEROWS(_xlfn.HSTACK(_xlfn.ANCHORARRAY($F$2),_xlfn.ANCHORARRAY($G$2)),ROW()-1),_xlfn.CHOOSEROWS(_xlfn.HSTACK(_xlfn.ANCHORARRAY($F$2),_xlfn.ANCHORARRAY($G$2)),ROW()-1),"",1)} -> 46081 | F23: 45866 | G23: 45897 | H23: 45928 | I23: 45958 | J23: 45989 | K23: 46019 | L23: 46050 | M23: 46081 | N23: 46109 | O23: 46140 | P23: 46170 | Q23: 46201 | R23: 46231 | S23: 46262 | T23: 46293 | U23: 46323 | V23: 46354 | W23: 46384 | X23: 46415 | Y23: 46446 | Z23: 46474 | AA23: 46505 | AB23: 46535 | AC23: 46566 | AD23: 46596 | AE23: 46627 | AF23: 46658 | AG23: 46688 | AH23: 46719 | AI23: 46749 | AJ23: 46780
B24: Internet | C24: 1 | D24: month(s) | E24: {=_xlfn.XLOOKUP($A$2,_xlfn.CHOOSEROWS(_xlfn.HSTACK(_xlfn.ANCHORARRAY($F$2),_xlfn.ANCHORARRAY($G$2)),ROW()-1),_xlfn.CHOOSEROWS(_xlfn.HSTACK(_xlfn.ANCHORARRAY($F$2),_xlfn.ANCHORARRAY($G$2)),ROW()-1),"",1)} -> 46107 | F24: 45652 | G24: 45683 | H24: 45714 | I24: 45742 | J24: 45773 | K24: 45803 | L24: 45834 | M24: 45864 | N24: 45895 | O24: 45926 | P24: 45956 | Q24: 45987 | R24: 46017 | S24: 46048 | T24: 46079 | U24: 46107 | V24: 46138 | W24: 46168 | X24: 46199 | Y24: 46229 | Z24: 46260 | AA24: 46291 | AB24: 46321 | AC24: 46352 | AD24: 46382 | AE24: 46413 | AF24: 46444 | AG24: 46472 | AH24: 46503 | AI24: 46533 | AJ24: 46564 | AK24: 46594 | AL24: 46625 | AM24: 46656 | AN24: 46686 | AO24: 46717 | AP24: 46747 | AQ24: 46778 | AR24: 46809
B25: Netflix | C25: 1 | D25: month(s) | E25: {=_xlfn.XLOOKUP($A$2,_xlfn.CHOOSEROWS(_xlfn.HSTACK(_xlfn.ANCHORARRAY($F$2),_xlfn.ANCHORARRAY($G$2)),ROW()-1),_xlfn.CHOOSEROWS(_xlfn.HSTACK(_xlfn.ANCHORARRAY($F$2),_xlfn.ANCHORARRAY($G$2)),ROW()-1),"",1)} -> 46101 | F25: 45828 | G25: 45858 | H25: 45889 | I25: 45920 | J25: 45950 | K25: 45981 | L25: 46011 | M25: 46042 | N25: 46073 | O25: 46101 | P25: 46132 | Q25: 46162 | R25: 46193 | S25: 46223 | T25: 46254 | U25: 46285 | V25: 46315 | W25: 46346 | X25: 46376 | Y25: 46407 | Z25: 46438 | AA25: 46466 | AB25: 46497 | AC25: 46527 | AD25: 46558 | AE25: 46588 | AF25: 46619 | AG25: 46650 | AH25: 46680 | AI25: 46711 | AJ25: 46741 | AK25: 46772 | AL25: 46803
B26: Prime Ad-Free | C26: 1 | D26: month(s) | E26: {=_xlfn.XLOOKUP($A$2,_xlfn.CHOOSEROWS(_xlfn.HSTACK(_xlfn.ANCHORARRAY($F$2),_xlfn.ANCHORARRAY($G$2)),ROW()-1),_xlfn.CHOOSEROWS(_xlfn.HSTACK(_xlfn.ANCHORARRAY($F$2),_xlfn.ANCHORARRAY($G$2)),ROW()-1),"",1)} -> 46081 | F26: 45656 | G26: 45687 | H26: 45716 | I26: 45746 | J26: 45777 | K26: 45807 | L26: 45838 | M26: 45868 | N26: 45899 | O26: 45930 | P26: 45960 | Q26: 45991 | R26: 46021 | S26: 46052 | T26: 46081 | U26: 46111 | V26: 46142 | W26: 46172 | X26: 46203 | Y26: 46233 | Z26: 46264 | AA26: 46295 | AB26: 46325 | AC26: 46356 | AD26: 46386 | AE26: 46417 | AF26: 46446 | AG26: 46476 | AH26: 46507 | AI26: 46537 | AJ26: 46568 | AK26: 46598 | AL26: 46629 | AM26: 46660 | AN26: 46690 | AO26: 46721 | AP26: 46751 | AQ26: 46782
B27: Down Dog | C27: 1 | D27: year(s) | E27: {=_xlfn.XLOOKUP($A$2,_xlfn.CHOOSEROWS(_xlfn.HSTACK(_xlfn.ANCHORARRAY($F$2),_xlfn.ANCHORARRAY($G$2)),ROW()-1),_xlfn.CHOOSEROWS(_xlfn.HSTACK(_xlfn.ANCHORARRAY($F$2),_xlfn.ANCHORARRAY($G$2)),ROW()-1),"",1)} -> 46420 | F27: 45690 | G27: 46055 | H27: 46420 | I27: 46785
B28: Google+ | C28: 1 | D28: year(s) | E28: {=_xlfn.XLOOKUP($A$2,_xlfn.CHOOSEROWS(_xlfn.HSTACK(_xlfn.ANCHORARRAY($F$2),_xlfn.ANCHORARRAY($G$2)),ROW()-1),_xlfn.CHOOSEROWS(_xlfn.HSTACK(_xlfn.ANCHORARRAY($F$2),_xlfn.ANCHORARRAY($G$2)),ROW()-1),"",1)} -> 46445 | F28: 45715 | G28: 46080 | H28: 46445 | I28: 46810
B29: Phone Insurance | C29: 1 | D29: month(s) | E29: {=_xlfn.XLOOKUP($A$2,_xlfn.CHOOSEROWS(_xlfn.HSTACK(_xlfn.ANCHORARRAY($F$2),_xlfn.ANCHORARRAY($G$2)),ROW()-1),_xlfn.CHOOSEROWS(_xlfn.HSTACK(_xlfn.ANCHORARRAY($F$2),_xlfn.ANCHORARRAY($G$2)),ROW()-1),"",1)} -> 46089 | F29: 45634 | G29: 45665 | H29: 45696 | I29: 45724 | J29: 45755 | K29: 45785 | L29: 45816 | M29: 45846 | N29: 45877 | O29: 45908 | P29: 45938 | Q29: 45969 | R29: 45999 | S29: 46030 | T29: 46061 | U29: 46089 | V29: 46120 | W29: 46150 | X29: 46181 | Y29: 46211 | Z29: 46242 | AA29: 46273 | AB29: 46303 | AC29: 46334 | AD29: 46364 | AE29: 46395 | AF29: 46426 | AG29: 46454 | AH29: 46485 | AI29: 46515 | AJ29: 46546 | AK29: 46576 | AL29: 46607 | AM29: 46638 | AN29: 46668 | AO29: 46699 | AP29: 46729 | AQ29: 46760 | AR29: 46791
B30: Sniffies | C30: 6 | D30: month(s) | E30: {=_xlfn.XLOOKUP($A$2,_xlfn.CHOOSEROWS(_xlfn.HSTACK(_xlfn.ANCHORARRAY($F$2),_xlfn.ANCHORARRAY($G$2)),ROW()-1),_xlfn.CHOOSEROWS(_xlfn.HSTACK(_xlfn.ANCHORARRAY($F$2),_xlfn.ANCHORARRAY($G$2)),ROW()-1),"",1)} -> 46194 | F30: 45464 | G30: 45647 | H30: 45829 | I30: 46012 | J30: 46194 | K30: 46377 | L30: 46559 | M30: 46742
B31: Tidal | C31: 1 | D31: month(s) | E31: {=_xlfn.XLOOKUP($A$2,_xlfn.CHOOSEROWS(_xlfn.HSTACK(_xlfn.ANCHORARRAY($F$2),_xlfn.ANCHORARRAY($G$2)),ROW()-1),_xlfn.CHOOSEROWS(_xlfn.HSTACK(_xlfn.ANCHORARRAY($F$2),_xlfn.ANCHORARRAY($G$2)),ROW()-1),"",1)} -> 46108 | F31: 46049 | G31: 46080 | H31: 46108 | I31: 46139 | J31: 46169 | K31: 46200 | L31: 46230 | M31: 46261 | N31: 46292 | O31: 46322 | P31: 46353 | Q31: 46383 | R31: 46414 | S31: 46445 | T31: 46473 | U31: 46504 | V31: 46534 | W31: 46565 | X31: 46595 | Y31: 46626 | Z31: 46657 | AA31: 46687 | AB31: 46718 | AC31: 46748 | AD31: 46779 | AE31: 46810
B32: Windsurf | C32: 1 | D32: month(s) | E32: {=_xlfn.XLOOKUP($A$2,_xlfn.CHOOSEROWS(_xlfn.HSTACK(_xlfn.ANCHORARRAY($F$2),_xlfn.ANCHORARRAY($G$2)),ROW()-1),_xlfn.CHOOSEROWS(_xlfn.HSTACK(_xlfn.ANCHORARRAY($F$2),_xlfn.ANCHORARRAY($G$2)),ROW()-1),"",1)} -> 46107 | F32: 46048 | G32: 46079 | H32: 46107 | I32: 46138 | J32: 46168 | K32: 46199 | L32: 46229 | M32: 46260 | N32: 46291 | O32: 46321 | P32: 46352 | Q32: 46382 | R32: 46413 | S32: 46444 | T32: 46472 | U32: 46503 | V32: 46533 | W32: 46564 | X32: 46594 | Y32: 46625 | Z32: 46656 | AA32: 46686 | AB32: 46717 | AC32: 46747 | AD32: 46778 | AE32: 46809
E33: {=_xlfn.XLOOKUP($A$2,_xlfn.CHOOSEROWS(_xlfn.HSTACK(_xlfn.ANCHORARRAY($F$2),_xlfn.ANCHORARRAY($G$2)),ROW()-1),_xlfn.CHOOSEROWS(_xlfn.HSTACK(_xlfn.ANCHORARRAY($F$2),_xlfn.ANCHORARRAY($G$2)),ROW()-1),"",1)} -> #VALUE!
E34: {=_xlfn.XLOOKUP($A$2,_xlfn.CHOOSEROWS(_xlfn.HSTACK(_xlfn.ANCHORARRAY($F$2),_xlfn.ANCHORARRAY($G$2)),ROW()-1),_xlfn.CHOOSEROWS(_xlfn.HSTACK(_xlfn.ANCHORARRAY($F$2),_xlfn.ANCHORARRAY($G$2)),ROW()-1),"",1)} -> #VALUE!
E35: {=_xlfn.XLOOKUP($A$2,_xlfn.CHOOSEROWS(_xlfn.HSTACK(_xlfn.ANCHORARRAY($F$2),_xlfn.ANCHORARRAY($G$2)),ROW()-1),_xlfn.CHOOSEROWS(_xlfn.HSTACK(_xlfn.ANCHORARRAY($F$2),_xlfn.ANCHORARRAY($G$2)),ROW()-1),"",1)} -> #VALUE!
E36: {=_xlfn.XLOOKUP($A$2,_xlfn.CHOOSEROWS(_xlfn.HSTACK(_xlfn.ANCHORARRAY($F$2),_xlfn.ANCHORARRAY($G$2)),ROW()-1),_xlfn.CHOOSEROWS(_xlfn.HSTACK(_xlfn.ANCHORARRAY($F$2),_xlfn.ANCHORARRAY($G$2)),ROW()-1),"",1)} -> #VALUE!
E37: {=_xlfn.XLOOKUP($A$2,_xlfn.CHOOSEROWS(_xlfn.HSTACK(_xlfn.ANCHORARRAY($F$2),_xlfn.ANCHORARRAY($G$2)),ROW()-1),_xlfn.CHOOSEROWS(_xlfn.HSTACK(_xlfn.ANCHORARRAY($F$2),_xlfn.ANCHORARRAY($G$2)),ROW()-1),"",1)} -> #VALUE!
E38: {=_xlfn.XLOOKUP($A$2,_xlfn.CHOOSEROWS(_xlfn.HSTACK(_xlfn.ANCHORARRAY($F$2),_xlfn.ANCHORARRAY($G$2)),ROW()-1),_xlfn.CHOOSEROWS(_xlfn.HSTACK(_xlfn.ANCHORARRAY($F$2),_xlfn.ANCHORARRAY($G$2)),ROW()-1),"",1)} -> #VALUE!
E39: {=_xlfn.XLOOKUP($A$2,_xlfn.CHOOSEROWS(_xlfn.HSTACK(_xlfn.ANCHORARRAY($F$2),_xlfn.ANCHORARRAY($G$2)),ROW()-1),_xlfn.CHOOSEROWS(_xlfn.HSTACK(_xlfn.ANCHORARRAY($F$2),_xlfn.ANCHORARRAY($G$2)),ROW()-1),"",1)} -> #VALUE!
E40: {=_xlfn.XLOOKUP($A$2,_xlfn.CHOOSEROWS(_xlfn.HSTACK(_xlfn.ANCHORARRAY($F$2),_xlfn.ANCHORARRAY($G$2)),ROW()-1),_xlfn.CHOOSEROWS(_xlfn.HSTACK(_xlfn.ANCHORARRAY($F$2),_xlfn.ANCHORARRAY($G$2)),ROW()-1),"",1)} -> #VALUE!
E41: {=_xlfn.XLOOKUP($A$2,_xlfn.CHOOSEROWS(_xlfn.HSTACK(_xlfn.ANCHORARRAY($F$2),_xlfn.ANCHORARRAY($G$2)),ROW()-1),_xlfn.CHOOSEROWS(_xlfn.HSTACK(_xlfn.ANCHORARRAY($F$2),_xlfn.ANCHORARRAY($G$2)),ROW()-1),"",1)} -> #VALUE!
E42: {=_xlfn.XLOOKUP($A$2,_xlfn.CHOOSEROWS(_xlfn.HSTACK(_xlfn.ANCHORARRAY($F$2),_xlfn.ANCHORARRAY($G$2)),ROW()-1),_xlfn.CHOOSEROWS(_xlfn.HSTACK(_xlfn.ANCHORARRAY($F$2),_xlfn.ANCHORARRAY($G$2)),ROW()-1),"",1)} -> #VALUE!
E43: {=_xlfn.XLOOKUP($A$2,_xlfn.CHOOSEROWS(_xlfn.HSTACK(_xlfn.ANCHORARRAY($F$2),_xlfn.ANCHORARRAY($G$2)),ROW()-1),_xlfn.CHOOSEROWS(_xlfn.HSTACK(_xlfn.ANCHORARRAY($F$2),_xlfn.ANCHORARRAY($G$2)),ROW()-1),"",1)} -> #VALUE!
E44: {=_xlfn.XLOOKUP($A$2,_xlfn.CHOOSEROWS(_xlfn.HSTACK(_xlfn.ANCHORARRAY($F$2),_xlfn.ANCHORARRAY($G$2)),ROW()-1),_xlfn.CHOOSEROWS(_xlfn.HSTACK(_xlfn.ANCHORARRAY($F$2),_xlfn.ANCHORARRAY($G$2)),ROW()-1),"",1)} -> #VALUE!
... E99: {=_xlfn.XLOOKUP($A$2,_xlfn.CHOOSEROWS(_xlfn.HSTACK(_xlfn.ANCHORARRAY($F$2),_xlfn.ANCHORARRAY($G$2)),ROW()-1),_xlfn.CHOOSEROWS(_xlfn.HSTACK(_xlfn.ANCHORARRAY($F$2),_xlfn.ANCHORARRAY($G$2)),ROW()-1),"",1)} -> #VALUE!
